{
  "name": "hexways.entry.hexways",
  "category": "hexcasting:patterns/spells",
  "icon": "minecraft:end_portal_frame",
  "sortnum": 0,
  "advancement": "hexcasting:root",
  "read_by_default": true,
  "pages": [
    {
      "title": "hexways.page.hexways.pageintrotitle",
      "type": "text",
      "text": "hexways.page.hexways.pageintro"
    },
    {
      "title": "hexways.page.hexways.portalambittitle",
      "type": "text",
      "text": "hexways.page.hexways.portalambit"
    },
    {
      "type": "hexcasting:pattern",
      "op_id": "hexways:twowayportal",
      "anchor": "hexways:twowayportal",
      "input": "vec, vec, vec, num",
      "output": "",
      "text": "hexways.page.hexways.twowayportal"
    },
    {
      "type": "hexcasting:pattern",
      "op_id": "hexways:onewayportal",
      "anchor": "hexways:onewayportal",
      "input": "vec, vec, vec, num",
      "output": "",
      "text": "hexways.page.hexways.onewayportal"
    },
    {
      "type": "hexcasting:pattern",
      "op_id": "hexways:summonscry",
      "anchor": "hexways:summonscry",
      "input": "vec, vec, vec, num",
      "output": "",
      "text": "hexways.page.hexways.summonscry"
    },
    {
      "type": "hexcasting:pattern",
      "op_id": "hexways:rotateportal",
      "anchor": "hexways:rotateportal",
      "input": "entity (Portal), vec, bool",
      "output": "",
      "text": "hexways.page.hexways.rotateportal"
    },
    {
      "type": "hexcasting:pattern",
      "op_id": "hexways:moveportalinput",
      "anchor": "hexways:moveportalinput",
      "input": "entity (Portal), vec",
      "output": "",
      "text": "hexways.page.hexways.moveportalinput"
    },
    {
      "type": "hexcasting:pattern",
      "op_id": "hexways:moveportaloutput",
      "anchor": "hexways:moveportaloutput",
      "input": "entity (Portal), vec",
      "output": "",
      "text": "hexways.page.hexways.moveportaloutput"
    },
        {
      "type": "hexcasting:pattern",
      "op_id": "hexways:getoutputinfo",
      "anchor": "hexways:getoutputinfo",
      "input": "entity (Portal)",
      "output": "vec",
      "text": "hexways.page.hexways.getoutputinfo"
    },
    {
      "type": "text",
      "text": "hexways.page.hexways.getoutputinfocont"
    },
    {
      "type": "hexcasting:pattern",
      "op_id": "hexways:setportalsides",
      "anchor": "hexways:setportalsides",
      "input": "entity (Portal), num, num",
      "output": "",
      "text": "hexways.page.hexways.setportalsides"
    },
    {
      "type": "hexcasting:pattern",
      "op_id": "hexways:resizeportal",
      "anchor": "hexways:resizeportal",
      "input": "entity (Portal), num, num",
      "output": "",
      "text": "hexways.page.hexways.resizeportal"
    },
    {
      "type": "hexcasting:pattern",
      "op_id": "hexways:removeportal",
      "anchor": "hexways:removeportal",
      "input": "entity (Portal)",
      "output": "",
      "text": "hexways.page.hexways.removeportal"
    }
  ]
}