{
    "Ac206": 0.025,
    "Ac206m": 0.015,
    "Ac206n": 0.041,
    "Ac207": 0.027,
    "Ac208": 0.095,
    "Ac208m": 0.028,
    "Ac209": 0.098,
    "Ac210": 0.35,
    "Ac211": 0.21,
    "Ac212": 0.92,
    "Ac213": 0.8,
    "Ac214": 8.2,
    "Ac215": 0.17,
    "Ac216": 0.00044,
    "Ac216m": 0.000441,
    "Ac217": 6.9e-08,
    "Ac218": 1.08e-06,
    "Ac219": 1.18e-05,
    "Ac220": 0.0264,
    "Ac221": 0.052,
    "Ac222": 4.2,
    "Ac222m": 66.0,
    "Ac223": 132.0,
    "Ac224": 10008.0,
    "Ac225": 864000.0,
    "Ac226": 104400.0,
    "Ac227": 687057000.0,
    "Ac228": 22140.0,
    "Ac229": 3762.0,
    "Ac230": 122.0,
    "Ac231": 450.0,
    "Ac232": 119.0,
    "Ac233": 145.0,
    "Ac234": 44.0,
    "Ac235": 40.0,
    "Ac236": 120.0,
    "Ag93": 0.005,
    "Ag94": 0.037,
    "Ag94m": 0.422,
    "Ag94n": 0.3,
    "Ag95": 1.74,
    "Ag95m": 0.5,
    "Ag95n": 0.016,
    "Ag95o": 0.04,
    "Ag96": 4.45,
    "Ag96m": 6.9,
    "Ag97": 25.5,
    "Ag98": 47.5,
    "Ag99": 124.0,
    "Ag99m": 10.5,
    "Ag100": 121.0,
    "Ag100m": 134.0,
    "Ag101": 666.0,
    "Ag101m": 3.099999,
    "Ag102": 774.0,
    "Ag102m": 460.0,
    "Ag103": 3942.0,
    "Ag103m": 5.7,
    "Ag104": 4150.0,
    "Ag104m": 2010.0,
    "Ag105": 3568320.0,
    "Ag105m": 433.8,
    "Ag106": 1440.0,
    "Ag106m": 730944.0,
    "Ag107": "STABLE",
    "Ag107m": 44.3,
    "Ag108": 142.92,
    "Ag108m": 13821900000.0,
    "Ag109": "STABLE",
    "Ag109m": 39.7,
    "Ag110": 24.56,
    "Ag110m": 21581000.0,
    "Ag111": 643680.0,
    "Ag111m": 64.8,
    "Ag112": 11268.0,
    "Ag113": 19332.0,
    "Ag113m": 68.7,
    "Ag114": 4.6,
    "Ag114m": 0.0015,
    "Ag115": 1200.0,
    "Ag115m": 18.6,
    "Ag116": 237.0,
    "Ag116m": 8.6,
    "Ag116n": 9.3,
    "Ag117": 72.8,
    "Ag117m": 5.34,
    "Ag118": 3.7,
    "Ag118m": 2.0,
    "Ag119": 2.1,
    "Ag119m": 2.1,
    "Ag120": 1.17,
    "Ag120m": 0.371,
    "Ag121": 0.78,
    "Ag122": 0.529,
    "Ag122m": 1.5,
    "Ag123": 0.3,
    "Ag124": 0.172,
    "Ag124m": 0.2,
    "Ag125": 0.166,
    "Ag126": 0.107,
    "Ag127": 0.079,
    "Ag128": 0.058,
    "Ag129": 0.044,
    "Ag130": 0.05,
    "Ag131": 0.01253,
    "Ag132": 0.0114,
    "Ag133": 0.008655,
    "Al21": 3.5e-08,
    "Al22": 0.059,
    "Al23": 0.47,
    "Al24": 2.053,
    "Al24m": 0.13,
    "Al25": 7.183,
    "Al26": 22626300000000.0,
    "Al26m": 6.345,
    "Al27": "STABLE",
    "Al28": 134.46,
    "Al29": 393.6,
    "Al30": 3.65,
    "Al31": 0.644,
    "Al32": 0.033,
    "Al33": 0.0417,
    "Al34": 0.0563,
    "Al35": 0.0386,
    "Al36": 0.09,
    "Al37": 0.02,
    "Al38": 0.04,
    "Al39": 0.01,
    "Al40": 0.01,
    "Al41": 0.002,
    "Al42": 0.001,
    "Am231": 30.0,
    "Am232": 78.6,
    "Am233": 192.0,
    "Am234": 139.2,
    "Am235": 594.0,
    "Am236": 1800.0,
    "Am236m": 174.0,
    "Am237": 4380.0,
    "Am238": 5880.0,
    "Am239": 42840.0,
    "Am240": 182880.0,
    "Am241": 13658100000.0,
    "Am242": 57636.0,
    "Am242m": 4449620000.0,
    "Am242n": 0.014,
    "Am243": 232416000000.0,
    "Am244": 36360.0,
    "Am244m": 1560.0,
    "Am245": 7380.0,
    "Am246": 2340.0,
    "Am246m": 1500.0,
    "Am247": 1380.0,
    "Am248": 180.0,
    "Am249": 60.0,
    "Am250": 306.0,
    "Ar30": 2e-08,
    "Ar31": 0.0144,
    "Ar32": 0.098,
    "Ar33": 0.173,
    "Ar34": 0.8438,
    "Ar35": 1.7756,
    "Ar36": "STABLE",
    "Ar37": 3024860.0,
    "Ar38": "STABLE",
    "Ar39": 8488990000.0,
    "Ar40": "STABLE",
    "Ar41": 6576.48,
    "Ar42": 1041400000.0,
    "Ar43": 322.2,
    "Ar44": 712.0002,
    "Ar45": 21.48,
    "Ar46": 8.4,
    "Ar47": 0.58,
    "Ar48": 0.5,
    "Ar49": 0.17,
    "Ar50": 0.085,
    "Ar51": 0.06,
    "Ar52": 0.01,
    "Ar53": 0.003,
    "As60": 1e-09,
    "As60m": 1e-09,
    "As61": 1e-09,
    "As62": 1e-09,
    "As63": 1e-09,
    "As64": 0.04,
    "As65": 0.17,
    "As66": 0.09577,
    "As67": 42.5,
    "As68": 151.6,
    "As69": 913.8,
    "As70": 3156.0,
    "As71": 235080.0,
    "As72": 93600.0,
    "As73": 6937920.0,
    "As74": 1536190.0,
    "As75": "STABLE",
    "As75m": 0.01762,
    "As76": 94392.0,
    "As77": 139644.0,
    "As78": 5442.0,
    "As79": 540.6,
    "As80": 15.2,
    "As81": 33.3,
    "As82": 19.1,
    "As82m": 13.6,
    "As83": 13.4,
    "As84": 5.5,
    "As84m": 0.65,
    "As85": 2.04,
    "As86": 0.945,
    "As87": 0.61,
    "As88": 0.3,
    "As89": 0.2,
    "As90": 0.08,
    "As91": 0.05,
    "As92": 0.03,
    "As93": 0.01862,
    "As94": 0.01295,
    "As95": 0.009955,
    "At191": 0.0017,
    "At191m": 0.0021,
    "At193": 0.04,
    "At193m": 0.021,
    "At193n": 0.027,
    "At194": 0.04,
    "At194m": 0.25,
    "At195": 0.328,
    "At195m": 0.147,
    "At196": 0.253,
    "At196m": 0.02,
    "At197": 0.35,
    "At197m": 3.7,
    "At198": 4.2,
    "At198m": 1.0,
    "At199": 7.2,
    "At200": 43.2,
    "At200m": 47.0,
    "At200n": 3.5,
    "At201": 85.0,
    "At202": 184.0,
    "At202m": 182.0,
    "At202n": 0.46,
    "At203": 444.0,
    "At204": 552.0,
    "At204m": 0.108,
    "At205": 1570.0,
    "At206": 1800.0,
    "At207": 6480.0,
    "At208": 5870.0,
    "At209": 19476.0,
    "At210": 29160.0,
    "At211": 25977.6,
    "At212": 0.314,
    "At212m": 0.119,
    "At213": 1.25e-07,
    "At214": 5.58e-07,
    "At215": 0.0001,
    "At216": 0.0003,
    "At217": 0.0323,
    "At218": 1.5,
    "At219": 56.0,
    "At220": 222.6,
    "At221": 138.0,
    "At222": 54.0,
    "At223": 50.0,
    "Au169": 0.00015,
    "Au170": 0.00031,
    "Au170m": 0.00063,
    "Au171": 1.7e-05,
    "Au171m": 0.001014,
    "Au172": 0.0047,
    "Au172m": 0.0077,
    "Au173": 0.025,
    "Au173m": 0.0142,
    "Au174": 0.139,
    "Au174m": 0.171,
    "Au175": 0.1,
    "Au175m": 0.156,
    "Au176": 1.08,
    "Au176m": 0.86,
    "Au177": 1.46,
    "Au177m": 1.18,
    "Au178": 2.6,
    "Au179": 7.1,
    "Au180": 8.1,
    "Au181": 13.7,
    "Au182": 15.5,
    "Au183": 42.0,
    "Au184": 20.6,
    "Au184m": 47.6,
    "Au185": 255.0,
    "Au186": 642.0,
    "Au187": 504.0,
    "Au187m": 2.3,
    "Au188": 530.0,
    "Au189": 1722.0,
    "Au189m": 275.4,
    "Au190": 2568.0,
    "Au190m": 0.125,
    "Au191": 11448.0,
    "Au191m": 0.92,
    "Au192": 17784.0,
    "Au192m": 0.029,
    "Au192n": 0.16,
    "Au193": 63540.0,
    "Au193m": 3.9,
    "Au194": 136872.0,
    "Au194m": 0.6,
    "Au194n": 0.42,
    "Au195": 16078500.0,
    "Au195m": 30.5,
    "Au196": 532820.0,
    "Au196m": 8.1,
    "Au196n": 34560.0,
    "Au197": "STABLE",
    "Au197m": 7.74,
    "Au198": 232788.0,
    "Au198m": 198720.0,
    "Au199": 271210.0,
    "Au200": 2904.0,
    "Au200m": 67300.0,
    "Au201": 1560.0,
    "Au202": 28.4,
    "Au203": 60.0,
    "Au204": 39.8,
    "Au205": 31.0,
    "Au206": 1.59,
    "B6": 1e-09,
    "B7": 3.5e-22,
    "B8": 0.77,
    "B9": 8e-19,
    "B10": "STABLE",
    "B11": "STABLE",
    "B12": 0.0202,
    "B13": 0.01733,
    "B14": 0.0125,
    "B15": 0.00987,
    "B16": 1.9e-10,
    "B17": 0.00508,
    "B18": 2.6e-08,
    "B19": 0.00292,
    "Ba114": 0.53,
    "Ba115": 0.45,
    "Ba116": 1.3,
    "Ba117": 1.75,
    "Ba118": 5.2,
    "Ba119": 5.4,
    "Ba120": 24.0,
    "Ba121": 29.7,
    "Ba122": 117.0,
    "Ba123": 162.0,
    "Ba124": 660.0,
    "Ba125": 210.0,
    "Ba126": 6000.0,
    "Ba127": 762.0,
    "Ba127m": 1.9,
    "Ba128": 209952.0,
    "Ba129": 8568.0,
    "Ba129m": 7704.0,
    "Ba130": "STABLE",
    "Ba130m": 0.00954,
    "Ba131": 997920.0,
    "Ba131m": 876.0,
    "Ba132": "STABLE",
    "Ba133": 332578000.0,
    "Ba133m": 137520.0,
    "Ba134": "STABLE",
    "Ba135": "STABLE",
    "Ba135m": 103320.0,
    "Ba136": "STABLE",
    "Ba136m": 0.3084,
    "Ba137": "STABLE",
    "Ba137m": 153.12,
    "Ba138": "STABLE",
    "Ba139": 4983.6,
    "Ba140": 1101860.0,
    "Ba141": 1096.2,
    "Ba142": 636.0,
    "Ba143": 14.5,
    "Ba144": 11.5,
    "Ba145": 4.31,
    "Ba146": 2.22,
    "Ba147": 0.894,
    "Ba148": 0.612,
    "Ba149": 0.344,
    "Ba150": 0.3,
    "Ba151": 0.2,
    "Ba152": 0.1,
    "Ba153": 0.08,
    "Ba154": 0.06759,
    "Be5": 1e-09,
    "Be6": 5e-21,
    "Be7": 4598210.0,
    "Be8": 7e-17,
    "Be9": "STABLE",
    "Be10": 50492200000000.0,
    "Be11": 13.81,
    "Be12": 0.0213,
    "Be13": 5e-10,
    "Be14": 0.00435,
    "Be15": 2e-07,
    "Be16": 2e-07,
    "Bh260": 0.0003,
    "Bh261": 0.013,
    "Bh262": 0.29,
    "Bh262m": 0.014,
    "Bh263": 0.2,
    "Bh264": 1.3,
    "Bh265": 0.5,
    "Bh266": 5.0,
    "Bh267": 22.0,
    "Bh269": 25.0,
    "Bi184": 0.0066,
    "Bi184m": 0.013,
    "Bi185": 0.002,
    "Bi186": 0.0148,
    "Bi186m": 0.0098,
    "Bi187": 0.032,
    "Bi187m": 0.00032,
    "Bi188": 0.044,
    "Bi188m": 0.22,
    "Bi189": 0.674,
    "Bi189m": 0.005,
    "Bi190": 6.3,
    "Bi190m": 6.2,
    "Bi191": 12.3,
    "Bi191m": 0.124,
    "Bi192": 34.6,
    "Bi192m": 39.6,
    "Bi193": 67.0,
    "Bi193m": 3.2,
    "Bi194": 95.0,
    "Bi194m": 125.0,
    "Bi194n": 115.0,
    "Bi195": 183.0,
    "Bi195m": 87.0,
    "Bi196": 306.0,
    "Bi196m": 0.6,
    "Bi196n": 240.0,
    "Bi197": 558.0,
    "Bi197m": 302.4,
    "Bi198": 618.0,
    "Bi198m": 711.0002,
    "Bi198n": 7.7,
    "Bi199": 1620.0,
    "Bi199m": 1482.0,
    "Bi200": 2180.0,
    "Bi200m": 1860.0,
    "Bi200n": 0.4,
    "Bi201": 6480.0,
    "Bi201m": 3348.0,
    "Bi202": 6156.0,
    "Bi203": 42340.0,
    "Bi203m": 0.305,
    "Bi204": 40392.0,
    "Bi204m": 0.013,
    "Bi204n": 0.00107,
    "Bi205": 1322780.0,
    "Bi206": 539395.0,
    "Bi207": 1038220000.0,
    "Bi208": 11613200000000.0,
    "Bi208m": 0.00258,
    "Bi209": 5.99594e+26,
    "Bi210": 432950.0,
    "Bi210m": 94672800000000.0,
    "Bi211": 129.0,
    "Bi212": 3632.4,
    "Bi212m": 1500.0,
    "Bi212n": 540.0,
    "Bi213": 2735.4,
    "Bi214": 1188.0,
    "Bi215": 456.0,
    "Bi215m": 36.9,
    "Bi216": 130.2,
    "Bi217": 98.5,
    "Bi218": 33.0,
    "Bk235": 20.0,
    "Bk236": 60.0,
    "Bk237": 60.0,
    "Bk238": 144.0,
    "Bk239": 180.0,
    "Bk240": 288.0,
    "Bk241": 276.0,
    "Bk242": 420.0,
    "Bk243": 16200.0,
    "Bk244": 15660.0,
    "Bk245": 426816.0,
    "Bk246": 155520.0,
    "Bk247": 43549500000.0,
    "Bk248": 284018000.0,
    "Bk248m": 85320.0,
    "Bk249": 27648000.0,
    "Bk250": 11581.2,
    "Bk251": 3336.0,
    "Bk252": 108.0,
    "Bk253": 600.0,
    "Bk254": 60.0,
    "Br67": 1e-09,
    "Br68": 1.5e-06,
    "Br69": 2.4e-08,
    "Br70": 0.0791,
    "Br70m": 2.2,
    "Br71": 21.4,
    "Br72": 78.6,
    "Br72m": 10.6,
    "Br73": 204.0,
    "Br74": 1524.0,
    "Br74m": 2760.0,
    "Br75": 5802.0,
    "Br76": 57960.0,
    "Br76m": 1.31,
    "Br77": 205326.0,
    "Br77m": 256.8,
    "Br78": 387.0,
    "Br79": "STABLE",
    "Br79m": 4.864,
    "Br80": 1056.0,
    "Br80m": 15876.0,
    "Br81": "STABLE",
    "Br82": 127152.0,
    "Br82m": 365.4,
    "Br83": 8640.0,
    "Br84": 1905.6,
    "Br84m": 360.0,
    "Br85": 174.0,
    "Br86": 55.0,
    "Br87": 55.7,
    "Br88": 16.5,
    "Br89": 4.37,
    "Br90": 1.9,
    "Br91": 0.538,
    "Br92": 0.343,
    "Br93": 0.102,
    "Br94": 0.07,
    "Br95": 0.05,
    "Br96": 0.02,
    "Br97": 0.01,
    "Br98": 0.02362,
    "Br99": 0.01513,
    "Br100": 0.01155,
    "C8": 2e-21,
    "C9": 0.1265,
    "C10": 19.29,
    "C11": 1221.66,
    "C12": "STABLE",
    "C13": "STABLE",
    "C14": 179874000000.0,
    "C15": 2.449,
    "C16": 0.747,
    "C17": 0.193,
    "C18": 0.092,
    "C19": 0.0462,
    "C20": 0.016,
    "C21": 3e-08,
    "C22": 0.0062,
    "Ca34": 3.5e-08,
    "Ca35": 0.0257,
    "Ca36": 0.102,
    "Ca37": 0.175,
    "Ca38": 0.44,
    "Ca39": 0.8596,
    "Ca40": "STABLE",
    "Ca41": 3162000000000.0,
    "Ca42": "STABLE",
    "Ca43": "STABLE",
    "Ca44": "STABLE",
    "Ca45": 14052100.0,
    "Ca46": "STABLE",
    "Ca47": 392083.0,
    "Ca48": 1.67255e+27,
    "Ca49": 523.2,
    "Ca50": 13.9,
    "Ca51": 10.0,
    "Ca52": 4.6,
    "Ca53": 0.09,
    "Ca54": 0.05,
    "Ca55": 0.03,
    "Ca56": 0.01,
    "Ca57": 0.005,
    "Cd95": 0.005,
    "Cd96": 1.0,
    "Cd97": 2.8,
    "Cd98": 9.2,
    "Cd99": 16.0,
    "Cd100": 49.1,
    "Cd101": 81.6,
    "Cd102": 330.0,
    "Cd103": 438.0,
    "Cd104": 3460.0,
    "Cd105": 3330.0,
    "Cd106": 2.0828e+26,
    "Cd107": 23472.0,
    "Cd108": 1.29386e+25,
    "Cd109": 39908200.0,
    "Cd110": "STABLE",
    "Cd111": "STABLE",
    "Cd111m": 2924.4,
    "Cd112": "STABLE",
    "Cd113": 2.46144e+23,
    "Cd113m": 460731000.0,
    "Cd114": 2.90324e+24,
    "Cd115": 192456.0,
    "Cd115m": 3840480.0,
    "Cd116": 9.46708e+26,
    "Cd117": 8964.0,
    "Cd117m": 12096.0,
    "Cd118": 3018.0,
    "Cd119": 161.4,
    "Cd119m": 132.0,
    "Cd120": 50.8,
    "Cd121": 13.5,
    "Cd121m": 8.3,
    "Cd122": 5.24,
    "Cd123": 2.1,
    "Cd123m": 1.82,
    "Cd124": 1.0,
    "Cd125": 0.68,
    "Cd125m": 0.48,
    "Cd126": 0.515,
    "Cd127": 0.37,
    "Cd128": 0.28,
    "Cd129": 0.242,
    "Cd129m": 0.104,
    "Cd130": 0.162,
    "Cd131": 0.068,
    "Cd132": 0.097,
    "Cd133": 0.01836,
    "Cd134": 0.01433,
    "Cd135": 0.01276,
    "Cd136": 0.009252,
    "Ce119": 0.2,
    "Ce120": 0.25,
    "Ce121": 1.1,
    "Ce122": 2.0,
    "Ce123": 3.8,
    "Ce124": 9.1,
    "Ce125": 9.3,
    "Ce126": 51.0,
    "Ce127": 29.0,
    "Ce127m": 34.0,
    "Ce128": 235.8,
    "Ce129": 210.0,
    "Ce130": 1374.0,
    "Ce131": 600.0,
    "Ce131m": 300.0,
    "Ce132": 12636.0,
    "Ce132m": 0.0094,
    "Ce133": 5820.0,
    "Ce133m": 17640.0,
    "Ce134": 273024.0,
    "Ce135": 63720.0,
    "Ce135m": 20.0,
    "Ce136": 2.20903e+21,
    "Ce137": 32400.0,
    "Ce137m": 123840.0,
    "Ce138": "STABLE",
    "Ce138m": 0.00865,
    "Ce139": 11893000.0,
    "Ce139m": 56.1,
    "Ce140": "STABLE",
    "Ce141": 2808260.0,
    "Ce142": 1.57785e+24,
    "Ce143": 118940.0,
    "Ce144": 24614500.0,
    "Ce145": 177.0,
    "Ce146": 811.2,
    "Ce147": 57.0,
    "Ce148": 56.0,
    "Ce149": 5.3,
    "Ce150": 4.0,
    "Ce151": 1.02,
    "Ce151m": 1.02,
    "Ce152": 1.1,
    "Ce153": 1.5,
    "Ce154": 2.0,
    "Ce155": 0.2,
    "Ce156": 0.15,
    "Ce157": 0.05,
    "Ce158": 0.1118,
    "Ce159": 0.09227,
    "Ce160": 0.06401,
    "Cf237": 2.1,
    "Cf238": 0.0211,
    "Cf239": 60.0,
    "Cf240": 57.6,
    "Cf241": 228.0,
    "Cf242": 209.4,
    "Cf243": 642.0,
    "Cf244": 1164.0,
    "Cf245": 2700.0,
    "Cf246": 128520.0,
    "Cf247": 11200.0,
    "Cf248": 28814400.0,
    "Cf249": 11076700000.0,
    "Cf250": 412773000.0,
    "Cf251": 28338700000.0,
    "Cf252": 83469800.0,
    "Cf253": 1538780.0,
    "Cf254": 5227200.0,
    "Cf255": 5100.0,
    "Cf256": 738.0,
    "Cl28": 1e-09,
    "Cl29": 2e-08,
    "Cl30": 3e-08,
    "Cl31": 0.15,
    "Cl32": 0.298,
    "Cl33": 2.511,
    "Cl34": 1.526,
    "Cl34m": 1926.0,
    "Cl35": "STABLE",
    "Cl36": 9530190000000.0,
    "Cl37": "STABLE",
    "Cl38": 2232.0,
    "Cl38m": 0.715,
    "Cl39": 3336.0,
    "Cl40": 81.0,
    "Cl41": 38.4,
    "Cl42": 6.8,
    "Cl43": 3.07,
    "Cl44": 0.56,
    "Cl45": 0.4,
    "Cl46": 0.22,
    "Cl47": 0.2,
    "Cl48": 0.1,
    "Cl49": 0.05,
    "Cl50": 0.02,
    "Cl51": 0.002,
    "Cm233": 60.0,
    "Cm234": 51.0,
    "Cm235": 300.0,
    "Cm236": 600.0,
    "Cm237": 1200.0,
    "Cm238": 8640.0,
    "Cm239": 10800.0,
    "Cm240": 2332800.0,
    "Cm241": 2833920.0,
    "Cm242": 14077200.0,
    "Cm243": 911995000.0,
    "Cm244": 568037000.0,
    "Cm244m": 0.034,
    "Cm245": 260345000000.0,
    "Cm246": 149267000000.0,
    "Cm247": 504922000000000.0,
    "Cm248": 10729600000000.0,
    "Cm249": 3849.0,
    "Cm250": 252461000000.0,
    "Cm251": 1008.0,
    "Cm252": 86400.0,
    "Co47": 1e-09,
    "Co48": 1e-09,
    "Co49": 3.5e-08,
    "Co50": 0.044,
    "Co51": 0.06,
    "Co52": 0.115,
    "Co52m": 0.104,
    "Co53": 0.24,
    "Co53m": 0.247,
    "Co54": 0.19328,
    "Co54m": 88.8,
    "Co55": 63108.0,
    "Co56": 6673190.0,
    "Co57": 23483500.0,
    "Co58": 6121440.0,
    "Co58m": 32760.0,
    "Co59": "STABLE",
    "Co60": 166340000.0,
    "Co60m": 628.02,
    "Co61": 5940.0,
    "Co62": 92.4,
    "Co62m": 834.6,
    "Co63": 27.4,
    "Co64": 0.3,
    "Co65": 1.2,
    "Co66": 0.2,
    "Co67": 0.425,
    "Co68": 0.2,
    "Co68m": 1.6,
    "Co69": 0.227,
    "Co70": 0.119,
    "Co70m": 0.5,
    "Co71": 0.097,
    "Co72": 0.09,
    "Co73": 0.08,
    "Co74": 0.05,
    "Co75": 0.04,
    "Co76": 0.01747,
    "Co77": 0.01135,
    "Co78": 0.004836,
    "Cr42": 0.014,
    "Cr43": 0.0216,
    "Cr44": 0.054,
    "Cr45": 0.05,
    "Cr45m": 0.001,
    "Cr46": 0.26,
    "Cr47": 0.5,
    "Cr48": 77616.0,
    "Cr49": 2514.0,
    "Cr50": 5.68037e+24,
    "Cr51": 2393630.0,
    "Cr52": "STABLE",
    "Cr53": "STABLE",
    "Cr54": "STABLE",
    "Cr55": 212.4,
    "Cr56": 356.4,
    "Cr57": 21.1,
    "Cr58": 7.0,
    "Cr59": 0.46,
    "Cr60": 0.56,
    "Cr61": 0.261,
    "Cr62": 0.199,
    "Cr63": 0.129,
    "Cr64": 0.043,
    "Cr65": 0.027,
    "Cr66": 0.01,
    "Cr67": 0.01,
    "Cr68": 0.01723,
    "Cr69": 0.01157,
    "Cr70": 0.007143,
    "Cs112": 0.0005,
    "Cs113": 1.67e-05,
    "Cs114": 0.57,
    "Cs115": 1.4,
    "Cs116": 0.7,
    "Cs116m": 3.85,
    "Cs117": 8.4,
    "Cs117m": 6.5,
    "Cs118": 14.0,
    "Cs118m": 17.0,
    "Cs119": 43.0,
    "Cs119m": 30.4,
    "Cs120": 61.2,
    "Cs120m": 57.0,
    "Cs121": 155.0,
    "Cs121m": 122.0,
    "Cs122": 21.18,
    "Cs122m": 270.0,
    "Cs122n": 0.36,
    "Cs123": 354.6,
    "Cs123m": 1.7,
    "Cs124": 30.8,
    "Cs124m": 6.3,
    "Cs125": 2802.0,
    "Cs125m": 0.9,
    "Cs126": 98.4,
    "Cs127": 22500.0,
    "Cs128": 217.2,
    "Cs129": 115920.0,
    "Cs130": 1752.6,
    "Cs130m": 207.6,
    "Cs131": 837216.0,
    "Cs132": 564192.0,
    "Cs133": "STABLE",
    "Cs134": 65146100.0,
    "Cs134m": 10468.8,
    "Cs135": 72580900000000.0,
    "Cs135m": 3180.0,
    "Cs136": 1125790.0,
    "Cs136m": 19.0,
    "Cs137": 948286000.0,
    "Cs138": 2004.6,
    "Cs138m": 174.6,
    "Cs139": 556.2,
    "Cs140": 64.0,
    "Cs141": 24.84,
    "Cs142": 1.684,
    "Cs143": 1.791,
    "Cs144": 0.994,
    "Cs144m": 1.0,
    "Cs145": 0.594,
    "Cs146": 0.323,
    "Cs147": 0.225,
    "Cs148": 0.146,
    "Cs149": 0.15,
    "Cs150": 0.1,
    "Cs151": 0.06,
    "Cs152": 0.05062,
    "Cu52": 1e-09,
    "Cu53": 3e-07,
    "Cu54": 7.5e-08,
    "Cu55": 0.04,
    "Cu56": 0.093,
    "Cu57": 0.1963,
    "Cu58": 3.204,
    "Cu59": 81.5,
    "Cu60": 1422.0,
    "Cu61": 12117.6,
    "Cu62": 585.0,
    "Cu63": "STABLE",
    "Cu64": 45721.4,
    "Cu65": "STABLE",
    "Cu66": 306.0,
    "Cu67": 222840.0,
    "Cu68": 31.1,
    "Cu68m": 225.0,
    "Cu69": 171.0,
    "Cu70": 44.5,
    "Cu70m": 33.0,
    "Cu70n": 6.6,
    "Cu71": 19.5,
    "Cu72": 6.63,
    "Cu73": 4.2,
    "Cu74": 1.594,
    "Cu75": 1.224,
    "Cu76": 0.641,
    "Cu76m": 1.27,
    "Cu77": 0.469,
    "Cu78": 0.342,
    "Cu79": 0.188,
    "Cu80": 0.1,
    "Cu81": 0.028,
    "Cu82": 0.01883,
    "Cu83": 0.01222,
    "Cu84": 0.0101,
    "Db255": 1.7,
    "Db256": 1.9,
    "Db257": 1.53,
    "Db257m": 0.79,
    "Db258": 4.5,
    "Db258m": 20.0,
    "Db259": 0.51,
    "Db260": 1.52,
    "Db261": 1.8,
    "Db262": 35.0,
    "Db263": 29.0,
    "Db264": 180.0,
    "Db265": 900.0,
    "Ds267": 1e-05,
    "Ds268": 0.0001,
    "Ds269": 0.00023,
    "Ds270": 0.00016,
    "Ds270m": 0.01,
    "Ds271": 0.21,
    "Ds271m": 0.0013,
    "Ds272": 1.0,
    "Ds273": 0.00036,
    "Ds273m": 0.12,
    "Ds279m": 0.19,
    "Ds281": 14.0,
    "Dy138": 0.2,
    "Dy139": 0.6,
    "Dy140": 0.7,
    "Dy141": 0.9,
    "Dy142": 2.3,
    "Dy143": 5.6,
    "Dy143m": 3.0,
    "Dy144": 9.1,
    "Dy145": 9.5,
    "Dy145m": 14.1,
    "Dy146": 29.0,
    "Dy146m": 0.15,
    "Dy147": 40.0,
    "Dy147m": 59.0,
    "Dy148": 198.0,
    "Dy149": 252.0,
    "Dy149m": 0.49,
    "Dy150": 430.2,
    "Dy151": 1074.0,
    "Dy152": 8568.0,
    "Dy153": 23040.0,
    "Dy154": 94670800000000.0,
    "Dy155": 35640.0,
    "Dy156": 3.15576e+25,
    "Dy157": 29304.0,
    "Dy157m": 0.0216,
    "Dy158": "STABLE",
    "Dy159": 12476200.0,
    "Dy160": "STABLE",
    "Dy161": "STABLE",
    "Dy162": "STABLE",
    "Dy163": "STABLE",
    "Dy164": "STABLE",
    "Dy165": 8402.4,
    "Dy165m": 75.48,
    "Dy166": 293760.0,
    "Dy167": 372.0,
    "Dy168": 522.0,
    "Dy169": 39.0,
    "Dy170": 30.0,
    "Dy171": 6.0,
    "Dy172": 3.0,
    "Dy173": 2.0,
    "Er143": 0.2,
    "Er144": 0.4,
    "Er145": 0.9,
    "Er146": 1.7,
    "Er147": 2.5,
    "Er147m": 2.5,
    "Er148": 4.6,
    "Er149": 4.0,
    "Er149m": 8.9,
    "Er150": 18.5,
    "Er151": 23.5,
    "Er151m": 0.58,
    "Er152": 10.3,
    "Er153": 37.1,
    "Er154": 223.8,
    "Er155": 318.0,
    "Er156": 1170.0,
    "Er157": 1119.0,
    "Er157m": 0.076,
    "Er158": 8100.0,
    "Er159": 2160.0,
    "Er160": 102888.0,
    "Er161": 11560.0,
    "Er162": 4.41806e+21,
    "Er163": 4500.0,
    "Er164": "STABLE",
    "Er165": 37296.0,
    "Er166": "STABLE",
    "Er167": "STABLE",
    "Er167m": 2.27,
    "Er168": "STABLE",
    "Er169": 810432.0,
    "Er170": "STABLE",
    "Er171": 27057.6,
    "Er172": 177480.0,
    "Er173": 84.0,
    "Er174": 192.0,
    "Er175": 72.0,
    "Er176": 20.0,
    "Er177": 3.0,
    "Es240": 1.0,
    "Es241": 10.0,
    "Es242": 13.5,
    "Es243": 21.0,
    "Es244": 37.0,
    "Es245": 66.0,
    "Es246": 462.0,
    "Es247": 276.0,
    "Es247m": 54000000.0,
    "Es248": 1620.0,
    "Es249": 6132.0,
    "Es250": 30960.0,
    "Es250m": 7992.0,
    "Es251": 118800.0,
    "Es252": 40754880.0,
    "Es253": 1768610.0,
    "Es254": 23820500.0,
    "Es254m": 141500.0,
    "Es255": 3438700.0,
    "Es256": 1320.0,
    "Es256m": 27360.0,
    "Es257": 665280.0,
    "Es258": 180.0,
    "Eu130": 0.0011,
    "Eu131": 0.0178,
    "Eu132": 0.1,
    "Eu133": 0.2,
    "Eu134": 0.5,
    "Eu135": 1.5,
    "Eu136": 3.8,
    "Eu136m": 3.8,
    "Eu136n": 3.8,
    "Eu137": 8.4,
    "Eu138": 12.1,
    "Eu139": 17.9,
    "Eu140": 1.51,
    "Eu140m": 0.125,
    "Eu141": 40.7,
    "Eu141m": 2.7,
    "Eu142": 2.34,
    "Eu142m": 73.38,
    "Eu143": 155.4,
    "Eu144": 10.2,
    "Eu145": 512352.0,
    "Eu146": 396576.0,
    "Eu147": 2082240.0,
    "Eu148": 4708800.0,
    "Eu149": 8043840.0,
    "Eu150": 1147390000.0,
    "Eu150m": 46080.0,
    "Eu151": "STABLE",
    "Eu152": 426713000.0,
    "Eu152m": 33390.0,
    "Eu152n": 5760.0,
    "Eu153": "STABLE",
    "Eu154": 271421000.0,
    "Eu154m": 2784.0,
    "Eu155": 149990000.0,
    "Eu156": 1312420.0,
    "Eu157": 54648.0,
    "Eu158": 2754.0,
    "Eu159": 1086.0,
    "Eu160": 38.0,
    "Eu161": 26.0,
    "Eu162": 10.6,
    "Eu163": 6.0,
    "Eu164": 2.0,
    "Eu165": 1.0,
    "Eu166": 0.4,
    "Eu167": 0.2,
    "Eu168": 0.3651,
    "Eu169": 0.2635,
    "Eu170": 0.1628,
    "F14": 1e-09,
    "F15": 4.1e-22,
    "F16": 1.1e-20,
    "F17": 64.49,
    "F18": 6584.04,
    "F19": "STABLE",
    "F20": 11.03,
    "F21": 4.158,
    "F22": 4.23,
    "F23": 2.23,
    "F24": 0.4,
    "F25": 0.05,
    "F26": 0.0102,
    "F27": 0.0049,
    "F28": 4e-08,
    "F29": 0.0026,
    "F30": 2.6e-07,
    "F31": 0.001,
    "Fe45": 0.0049,
    "Fe46": 0.009,
    "Fe47": 0.0218,
    "Fe48": 0.044,
    "Fe49": 0.07,
    "Fe50": 0.155,
    "Fe51": 0.305,
    "Fe52": 29782.8,
    "Fe52m": 45.9,
    "Fe53": 510.6,
    "Fe53m": 154.8,
    "Fe54": "STABLE",
    "Fe55": 86686900.0,
    "Fe56": "STABLE",
    "Fe57": "STABLE",
    "Fe58": "STABLE",
    "Fe59": 3844280.0,
    "Fe60": 47336400000000.0,
    "Fe61": 358.8,
    "Fe62": 68.0,
    "Fe63": 6.1,
    "Fe64": 2.0,
    "Fe65": 1.3,
    "Fe65m": 1.12,
    "Fe66": 0.44,
    "Fe67": 0.394,
    "Fe68": 0.187,
    "Fe69": 0.109,
    "Fe70": 0.094,
    "Fe71": 0.03,
    "Fe72": 0.01,
    "Fe73": 0.02584,
    "Fe74": 0.01404,
    "Fe75": 0.01043,
    "Fe76": 0.01043,
    "Fm242": 0.0008,
    "Fm243": 0.21,
    "Fm244": 0.0033,
    "Fm245": 4.2,
    "Fm246": 1.1,
    "Fm247": 35.0,
    "Fm248": 36.0,
    "Fm249": 156.0,
    "Fm250": 1800.0,
    "Fm250m": 1.8,
    "Fm251": 19100.0,
    "Fm252": 91404.0,
    "Fm253": 259200.0,
    "Fm254": 11664.0,
    "Fm255": 72252.0,
    "Fm256": 9456.0,
    "Fm257": 8683200.0,
    "Fm258": 0.00037,
    "Fm259": 1.5,
    "Fm260": 0.004,
    "Fr199": 0.016,
    "Fr200": 0.024,
    "Fr200m": 0.65,
    "Fr201": 0.069,
    "Fr202": 0.29,
    "Fr202m": 0.34,
    "Fr203": 0.55,
    "Fr204": 1.7,
    "Fr204m": 2.6,
    "Fr204n": 1.7,
    "Fr205": 3.92,
    "Fr206": 16.0,
    "Fr206m": 15.9,
    "Fr206n": 0.7,
    "Fr207": 14.8,
    "Fr208": 59.1,
    "Fr209": 50.0,
    "Fr210": 190.8,
    "Fr211": 186.0,
    "Fr212": 1200.0,
    "Fr213": 34.6,
    "Fr214": 0.005,
    "Fr214m": 0.00335,
    "Fr215": 8.6e-08,
    "Fr216": 7e-07,
    "Fr217": 1.9e-05,
    "Fr218": 0.001,
    "Fr218m": 0.022,
    "Fr219": 0.02,
    "Fr220": 27.4,
    "Fr221": 287.4,
    "Fr222": 852.0,
    "Fr223": 1320.0,
    "Fr224": 199.8,
    "Fr225": 240.0,
    "Fr226": 49.0,
    "Fr227": 148.2,
    "Fr228": 38.0,
    "Fr229": 50.2,
    "Fr230": 19.1,
    "Fr231": 17.6,
    "Fr232": 5.0,
    "Ga56": 1e-09,
    "Ga57": 1e-09,
    "Ga58": 1e-09,
    "Ga59": 1e-09,
    "Ga60": 0.07,
    "Ga61": 0.168,
    "Ga62": 0.116121,
    "Ga63": 32.4,
    "Ga64": 157.62,
    "Ga65": 912.0,
    "Ga66": 34164.0,
    "Ga67": 281768.0,
    "Ga68": 4069.8,
    "Ga69": "STABLE",
    "Ga70": 1268.4,
    "Ga71": "STABLE",
    "Ga72": 50760.0,
    "Ga72m": 0.03968,
    "Ga73": 17496.0,
    "Ga74": 487.2,
    "Ga74m": 9.5,
    "Ga75": 130.2,
    "Ga76": 32.6,
    "Ga77": 13.0,
    "Ga78": 5.09,
    "Ga79": 3.0,
    "Ga80": 1.676,
    "Ga81": 1.217,
    "Ga82": 0.599,
    "Ga83": 0.308,
    "Ga84": 0.085,
    "Ga85": 0.05,
    "Ga86": 0.03,
    "Ga87": 0.01943,
    "Ga88": 0.01421,
    "Ga89": 0.00952,
    "Gd134": 0.4,
    "Gd135": 1.1,
    "Gd136": 1.0,
    "Gd137": 2.2,
    "Gd138": 4.7,
    "Gd139": 5.7,
    "Gd139m": 4.8,
    "Gd140": 15.8,
    "Gd141": 14.0,
    "Gd141m": 24.5,
    "Gd142": 70.2,
    "Gd143": 39.0,
    "Gd143m": 110.0,
    "Gd144": 270.0,
    "Gd145": 1380.0,
    "Gd145m": 85.0,
    "Gd146": 4170530.0,
    "Gd147": 137200.0,
    "Gd148": 2366770000.0,
    "Gd149": 801792.0,
    "Gd150": 57434800000000.0,
    "Gd151": 10713600.0,
    "Gd152": 3.40815e+21,
    "Gd153": 20779200.0,
    "Gd154": "STABLE",
    "Gd155": "STABLE",
    "Gd155m": 0.032,
    "Gd156": "STABLE",
    "Gd157": "STABLE",
    "Gd158": "STABLE",
    "Gd159": 66524.4,
    "Gd160": 4.10249e+24,
    "Gd161": 219.6,
    "Gd162": 504.0,
    "Gd163": 68.0,
    "Gd164": 45.0,
    "Gd165": 10.3,
    "Gd166": 4.8,
    "Gd167": 3.0,
    "Gd168": 0.3,
    "Gd169": 1.0,
    "Gd170": 0.9662,
    "Gd171": 0.5118,
    "Gd172": 0.3505,
    "Ge58": 1e-09,
    "Ge59": 1e-09,
    "Ge60": 0.03,
    "Ge61": 0.039,
    "Ge62": 0.13,
    "Ge63": 0.142,
    "Ge64": 63.7,
    "Ge65": 30.89999,
    "Ge66": 8136.0,
    "Ge67": 1134.0,
    "Ge68": 23410100.0,
    "Ge69": 140580.0,
    "Ge70": "STABLE",
    "Ge71": 987552.0,
    "Ge71m": 0.0204,
    "Ge72": "STABLE",
    "Ge73": "STABLE",
    "Ge73m": 0.499,
    "Ge74": "STABLE",
    "Ge75": 4966.8,
    "Ge75m": 48.0,
    "Ge76": 4.9861e+28,
    "Ge77": 40359.6,
    "Ge77m": 53.7,
    "Ge78": 5280.0,
    "Ge79": 18.98,
    "Ge79m": 39.0,
    "Ge80": 27.0,
    "Ge81": 7.6,
    "Ge81m": 7.6,
    "Ge82": 4.55,
    "Ge83": 1.85,
    "Ge84": 0.954,
    "Ge85": 0.54,
    "Ge86": 0.3,
    "Ge87": 0.15,
    "Ge88": 0.08,
    "Ge89": 0.05,
    "Ge90": 0.02137,
    "Ge91": 0.01598,
    "H1": "STABLE",
    "H2": "STABLE",
    "H3": 389105000.0,
    "H4": 1.39e-22,
    "H5": 9.1e-22,
    "H6": 2.9e-22,
    "H7": 2.3e-23,
    "He3": "STABLE",
    "He4": "STABLE",
    "He5": 7e-22,
    "He6": 0.8081,
    "He7": 2.9e-21,
    "He8": 0.122,
    "He9": 7e-21,
    "He10": 2.7e-21,
    "Hf153": 0.4,
    "Hf153m": 0.5,
    "Hf154": 2.0,
    "Hf155": 0.89,
    "Hf156": 0.023,
    "Hf156m": 0.00052,
    "Hf157": 0.115,
    "Hf158": 2.85,
    "Hf159": 5.2,
    "Hf160": 13.6,
    "Hf161": 18.2,
    "Hf162": 39.4,
    "Hf163": 40.0,
    "Hf164": 111.0,
    "Hf165": 102.0,
    "Hf166": 406.0,
    "Hf167": 123.0,
    "Hf168": 1557.0,
    "Hf169": 194.4,
    "Hf170": 57600.0,
    "Hf171": 43600.0,
    "Hf171m": 29.5,
    "Hf172": 59011500.0,
    "Hf173": 86040.0,
    "Hf174": 6.31152e+22,
    "Hf175": 6048000.0,
    "Hf176": "STABLE",
    "Hf177": "STABLE",
    "Hf177m": 1.08,
    "Hf177n": 3084.0,
    "Hf178": "STABLE",
    "Hf178m": 4.0,
    "Hf178n": 978286000.0,
    "Hf179": "STABLE",
    "Hf179m": 18.67,
    "Hf179n": 2168640.0,
    "Hf180": "STABLE",
    "Hf180m": 19800.0,
    "Hf181": 3661630.0,
    "Hf181m": 0.0015,
    "Hf182": 280857000000000.0,
    "Hf182m": 3690.0,
    "Hf183": 3841.2,
    "Hf184": 14832.0,
    "Hf184m": 48.0,
    "Hf185": 210.0,
    "Hf186": 156.0,
    "Hf187": 30.0,
    "Hf188": 20.0,
    "Hg171": 8e-05,
    "Hg172": 0.00042,
    "Hg173": 0.0011,
    "Hg174": 0.0019,
    "Hg175": 0.0107,
    "Hg176": 0.0204,
    "Hg177": 0.1273,
    "Hg178": 0.269,
    "Hg179": 1.09,
    "Hg180": 2.58,
    "Hg181": 3.6,
    "Hg182": 10.83,
    "Hg183": 9.4,
    "Hg183m": 5.0,
    "Hg184": 30.6,
    "Hg185": 49.1,
    "Hg185m": 21.6,
    "Hg186": 82.8,
    "Hg187": 144.0,
    "Hg187m": 144.0,
    "Hg188": 195.0,
    "Hg189": 456.0,
    "Hg189m": 522.0,
    "Hg190": 1200.0,
    "Hg191": 2900.0,
    "Hg191m": 3050.0,
    "Hg192": 17460.0,
    "Hg193": 13680.0,
    "Hg193m": 42500.0,
    "Hg194": 14011300000.0,
    "Hg195": 37908.0,
    "Hg195m": 150000.0,
    "Hg196": 7.8894e+25,
    "Hg197": 232560.0,
    "Hg197m": 86040.0,
    "Hg198": "STABLE",
    "Hg199": "STABLE",
    "Hg199m": 2526.0,
    "Hg200": "STABLE",
    "Hg201": "STABLE",
    "Hg202": "STABLE",
    "Hg203": 4025720.0,
    "Hg204": "STABLE",
    "Hg205": 312.0,
    "Hg205m": 0.00109,
    "Hg206": 499.2,
    "Hg207": 174.0,
    "Hg208": 2520.0,
    "Hg209": 37.0,
    "Hg210": 600.0,
    "Ho140": 0.006,
    "Ho141": 0.0041,
    "Ho142": 0.4,
    "Ho143": 0.3,
    "Ho144": 0.7,
    "Ho145": 2.4,
    "Ho145m": 0.1,
    "Ho146": 3.6,
    "Ho147": 5.8,
    "Ho148": 2.2,
    "Ho148m": 0.00236,
    "Ho148n": 0.00235,
    "Ho149": 21.1,
    "Ho149m": 56.0,
    "Ho150": 76.8,
    "Ho150m": 23.3,
    "Ho151": 35.2,
    "Ho151m": 47.2,
    "Ho152": 161.8,
    "Ho152m": 49.5,
    "Ho153": 120.6,
    "Ho153m": 560.0,
    "Ho154": 710.0002,
    "Ho154m": 195.0,
    "Ho155": 2880.0,
    "Ho155m": 0.00088,
    "Ho156": 3360.0,
    "Ho156m": 9.5,
    "Ho156n": 468.0,
    "Ho157": 756.0002,
    "Ho158": 660.0,
    "Ho158m": 1620.0,
    "Ho158n": 1280.0,
    "Ho159": 1983.0,
    "Ho159m": 8.3,
    "Ho160": 1518.0,
    "Ho160m": 18000.0,
    "Ho160n": 2.9,
    "Ho161": 8928.0,
    "Ho161m": 6.77,
    "Ho162": 840.0,
    "Ho162m": 4020.0,
    "Ho163": 144218000000.0,
    "Ho163m": 1.1,
    "Ho164": 1716.0,
    "Ho164m": 2256.0,
    "Ho165": "STABLE",
    "Ho166": 96462.0,
    "Ho166m": 35754000000.0,
    "Ho167": 11160.0,
    "Ho168": 179.4,
    "Ho168m": 132.0,
    "Ho169": 264.0,
    "Ho170": 166.8,
    "Ho170m": 43.0,
    "Ho171": 53.0,
    "Ho172": 25.0,
    "Ho173": 10.0,
    "Ho174": 8.0,
    "Ho175": 5.0,
    "Hs263": 0.001,
    "Hs264": 0.00054,
    "Hs265": 0.0021,
    "Hs265m": 0.00078,
    "Hs266": 0.0027,
    "Hs267": 0.032,
    "Hs268": 2.0,
    "Hs269": 27.0,
    "Hs273": 50.0,
    "Hs277": 0.011,
    "I108": 0.036,
    "I109": 0.000103,
    "I110": 0.65,
    "I111": 2.5,
    "I112": 3.42,
    "I113": 6.6,
    "I114": 2.1,
    "I114m": 6.2,
    "I115": 78.0,
    "I116": 2.91,
    "I117": 138.0,
    "I118": 822.0,
    "I118m": 510.0,
    "I119": 1146.0,
    "I120": 4896.0,
    "I120m": 3180.0,
    "I121": 7632.0,
    "I122": 217.8,
    "I123": 47604.2,
    "I124": 360806.0,
    "I125": 5131120.0,
    "I126": 1121470.0,
    "I127": "STABLE",
    "I128": 1499.4,
    "I129": 508067000000000.0,
    "I130": 44496.0,
    "I130m": 540.0,
    "I131": 693213.0,
    "I132": 8262.0,
    "I132m": 4980.0,
    "I133": 75132.0,
    "I133m": 9.0,
    "I134": 3150.0,
    "I134m": 216.0,
    "I135": 23688.0,
    "I136": 83.5,
    "I136m": 47.0,
    "I137": 24.51,
    "I138": 6.46,
    "I139": 2.3,
    "I140": 0.86,
    "I141": 0.43,
    "I142": 0.2,
    "I143": 0.1,
    "I144": 0.05,
    "I145": 0.127,
    "I146": 0.0464,
    "I147": 0.03127,
    "I148": 0.02973,
    "In97": 0.005,
    "In98": 0.045,
    "In98m": 1.7,
    "In99": 3.1,
    "In99m": 1.0,
    "In100": 5.9,
    "In101": 15.1,
    "In101m": 10.0,
    "In102": 22.0,
    "In103": 60.0,
    "In103m": 34.0,
    "In104": 108.0,
    "In104m": 15.7,
    "In105": 304.2,
    "In105m": 48.0,
    "In106": 372.0,
    "In106m": 312.0,
    "In107": 1944.0,
    "In107m": 50.4,
    "In108": 3480.0,
    "In108m": 2380.0,
    "In109": 15001.2,
    "In109m": 80.4,
    "In109n": 0.209,
    "In110": 17640.0,
    "In110m": 4146.0,
    "In111": 242343.0,
    "In111m": 474.0,
    "In112": 882.0,
    "In112m": 1242.0,
    "In113": "STABLE",
    "In113m": 5968.44,
    "In114": 71.9,
    "In114m": 4320000.0,
    "In114n": 0.043,
    "In115": 1.39166e+22,
    "In115m": 16149.6,
    "In116": 14.2,
    "In116m": 3276.0,
    "In116n": 2.17,
    "In117": 2592.0,
    "In117m": 6972.0,
    "In118": 5.0,
    "In118m": 267.0,
    "In118n": 8.5,
    "In119": 144.0,
    "In119m": 1080.0,
    "In120": 3.08,
    "In120m": 46.2,
    "In120n": 46.2,
    "In121": 23.1,
    "In121m": 232.8,
    "In122": 1.5,
    "In122m": 10.8,
    "In122n": 10.8,
    "In123": 6.17,
    "In123m": 47.8,
    "In124": 3.12,
    "In124m": 3.7,
    "In125": 2.36,
    "In125m": 12.2,
    "In126": 1.53,
    "In126m": 1.45,
    "In127": 1.09,
    "In127m": 3.7,
    "In127n": 1.04,
    "In128": 0.84,
    "In128m": 0.01,
    "In128n": 0.72,
    "In129": 0.61,
    "In129m": 1.23,
    "In129n": 0.67,
    "In130": 0.29,
    "In130m": 0.54,
    "In130n": 0.54,
    "In131": 0.28,
    "In131m": 0.35,
    "In131n": 0.32,
    "In132": 0.207,
    "In133": 0.165,
    "In133m": 0.18,
    "In134": 0.14,
    "In135": 0.092,
    "In136": 0.01623,
    "In137": 0.01219,
    "In138": 0.01035,
    "Ir164": 0.001,
    "Ir164m": 9.4e-05,
    "Ir165": 1e-06,
    "Ir166": 0.0105,
    "Ir166m": 0.0151,
    "Ir167": 0.0352,
    "Ir167m": 0.03,
    "Ir168": 0.161,
    "Ir168m": 0.125,
    "Ir169": 0.64,
    "Ir169m": 0.308,
    "Ir170": 0.91,
    "Ir170m": 0.44,
    "Ir171": 3.5,
    "Ir171m": 1.4,
    "Ir172": 4.4,
    "Ir172m": 2.0,
    "Ir173": 9.0,
    "Ir173m": 2.2,
    "Ir174": 7.9,
    "Ir174m": 4.9,
    "Ir175": 9.0,
    "Ir176": 8.3,
    "Ir177": 30.0,
    "Ir178": 12.0,
    "Ir179": 79.0,
    "Ir180": 90.0,
    "Ir181": 294.0,
    "Ir182": 900.0002,
    "Ir183": 3480.0,
    "Ir184": 10870.0,
    "Ir185": 50000.0,
    "Ir186": 59900.0,
    "Ir186m": 7200.0,
    "Ir187": 37800.0,
    "Ir187m": 0.0303,
    "Ir188": 149400.0,
    "Ir188m": 0.0042,
    "Ir189": 1140480.0,
    "Ir189m": 0.0133,
    "Ir189n": 0.0037,
    "Ir190": 1036800.0,
    "Ir190m": 4032.0,
    "Ir190n": 11113.2,
    "Ir191": "STABLE",
    "Ir191m": 4.9,
    "Ir191n": 5.5,
    "Ir192": 6378220.0,
    "Ir192m": 86.4,
    "Ir192n": 7605220000.0,
    "Ir193": "STABLE",
    "Ir193m": 909792.0,
    "Ir194": 69480.0,
    "Ir194m": 0.03183,
    "Ir194n": 14774400.0,
    "Ir195": 9000.0,
    "Ir195m": 13680.0,
    "Ir196": 52.0,
    "Ir196m": 5040.0,
    "Ir197": 348.0,
    "Ir197m": 534.0,
    "Ir198": 8.0,
    "Ir199": 20.0,
    "Ir200": 5.19,
    "Ir201": 18.5,
    "Ir202": 8.5,
    "K32": 1e-09,
    "K33": 2.5e-08,
    "K34": 4e-08,
    "K35": 0.178,
    "K36": 0.342,
    "K37": 1.225,
    "K38": 456.6,
    "K38m": 0.924,
    "K39": "STABLE",
    "K40": 3.94588e+16,
    "K41": "STABLE",
    "K42": 44492.4,
    "K43": 79920.0,
    "K44": 1327.8,
    "K45": 1068.6,
    "K46": 105.0,
    "K47": 17.5,
    "K48": 6.8,
    "K49": 1.26,
    "K50": 0.472,
    "K51": 0.365,
    "K52": 0.105,
    "K53": 0.03,
    "K54": 0.01,
    "K55": 0.003,
    "Kr69": 0.032,
    "Kr70": 0.052,
    "Kr71": 0.1,
    "Kr72": 17.2,
    "Kr73": 27.3,
    "Kr74": 690.0,
    "Kr75": 276.0,
    "Kr76": 53300.0,
    "Kr77": 4464.0,
    "Kr78": 3.47134e+27,
    "Kr79": 126144.0,
    "Kr79m": 50.0,
    "Kr80": "STABLE",
    "Kr81": 6627100000000.0,
    "Kr81m": 13.2,
    "Kr82": "STABLE",
    "Kr83": "STABLE",
    "Kr83m": 6588.0,
    "Kr84": "STABLE",
    "Kr85": 339300000.0,
    "Kr85m": 16128.0,
    "Kr86": "STABLE",
    "Kr87": 4578.0,
    "Kr88": 10224.0,
    "Kr89": 189.0,
    "Kr90": 32.32,
    "Kr91": 8.57,
    "Kr92": 1.84,
    "Kr93": 1.286,
    "Kr94": 0.21,
    "Kr95": 0.114,
    "Kr96": 0.08,
    "Kr97": 0.063,
    "Kr98": 0.046,
    "Kr99": 0.04,
    "Kr100": 0.01,
    "Kr101": 0.02426,
    "Kr102": 0.015,
    "La117": 0.0235,
    "La117m": 0.01,
    "La118": 0.2,
    "La119": 1.0,
    "La120": 2.8,
    "La121": 5.3,
    "La122": 8.7,
    "La123": 17.0,
    "La124": 29.21,
    "La124m": 21.0,
    "La125": 64.8,
    "La125m": 0.39,
    "La126": 54.0,
    "La126m": 20.0,
    "La127": 306.0,
    "La127m": 222.0,
    "La128": 300.0,
    "La128m": 84.0,
    "La129": 696.0,
    "La129m": 0.56,
    "La130": 522.0,
    "La131": 3540.0,
    "La132": 17280.0,
    "La132m": 1458.0,
    "La133": 14083.2,
    "La134": 387.0,
    "La135": 70200.0,
    "La136": 592.2,
    "La136m": 0.114,
    "La137": 1893460000000.0,
    "La138": 3.2693e+18,
    "La139": "STABLE",
    "La140": 145029.0,
    "La141": 14112.0,
    "La142": 5466.0,
    "La143": 848.4,
    "La144": 40.8,
    "La145": 24.8,
    "La146": 6.27,
    "La146m": 10.0,
    "La147": 4.06,
    "La148": 1.26,
    "La149": 1.05,
    "La150": 0.51,
    "La151": 0.3,
    "La152": 0.28,
    "La153": 0.15,
    "La154": 0.1,
    "La155": 0.06,
    "La156": 0.0769,
    "La157": 0.05919,
    "Li4": 9.1e-23,
    "Li5": 3.7e-22,
    "Li6": "STABLE",
    "Li7": "STABLE",
    "Li8": 0.838,
    "Li9": 0.1783,
    "Li10": 2e-21,
    "Li11": 0.00875,
    "Li12": 1e-08,
    "Lr251": 0.00015,
    "Lr252": 0.39,
    "Lr253": 0.58,
    "Lr253m": 1.5,
    "Lr254": 13.0,
    "Lr255": 22.0,
    "Lr255m": 2.53,
    "Lr256": 27.0,
    "Lr257": 4.0,
    "Lr258": 4.1,
    "Lr259": 6.2,
    "Lr260": 180.0,
    "Lr261": 2340.0,
    "Lr262": 14400.0,
    "Lr263": 18000.0,
    "Lu150": 0.046,
    "Lu151": 0.0806,
    "Lu152": 0.65,
    "Lu153": 0.9,
    "Lu153m": 1.0,
    "Lu154": 1.0,
    "Lu154m": 1.12,
    "Lu155": 0.0686,
    "Lu155m": 0.138,
    "Lu155n": 0.0027,
    "Lu156": 0.494,
    "Lu156m": 0.198,
    "Lu157": 6.8,
    "Lu157m": 4.79,
    "Lu158": 10.6,
    "Lu159": 12.1,
    "Lu159m": 10.0,
    "Lu160": 36.1,
    "Lu160m": 40.0,
    "Lu161": 77.0,
    "Lu161m": 0.0073,
    "Lu162": 82.2,
    "Lu162m": 90.0,
    "Lu162n": 114.0,
    "Lu163": 238.0,
    "Lu164": 188.4,
    "Lu165": 644.0,
    "Lu166": 159.0,
    "Lu166m": 85.0,
    "Lu166n": 127.0,
    "Lu167": 3090.0,
    "Lu167m": 60.0,
    "Lu168": 330.0,
    "Lu168m": 402.0,
    "Lu169": 122620.0,
    "Lu169m": 160.0,
    "Lu170": 173000.0,
    "Lu170m": 0.67,
    "Lu171": 712800.0,
    "Lu171m": 78.0,
    "Lu172": 578880.0,
    "Lu172m": 222.0,
    "Lu173": 42163200.0,
    "Lu174": 112320000.0,
    "Lu174m": 12268800.0,
    "Lu175": "STABLE",
    "Lu176": 1.18654e+18,
    "Lu176m": 13086.0,
    "Lu177": 574301.0,
    "Lu177m": 13849900.0,
    "Lu177n": 420.0,
    "Lu178": 1704.0,
    "Lu178m": 1386.0,
    "Lu179": 16524.0,
    "Lu179m": 0.0031,
    "Lu180": 342.0,
    "Lu180m": 1.0,
    "Lu180n": 0.001,
    "Lu181": 210.0,
    "Lu182": 120.0,
    "Lu183": 58.0,
    "Lu184": 20.0,
    "Md245": 0.0009,
    "Md245m": 0.4,
    "Md246": 1.0,
    "Md247": 0.27,
    "Md247m": 1.12,
    "Md248": 7.0,
    "Md249": 24.0,
    "Md249m": 1.9,
    "Md250": 52.0,
    "Md251": 240.0,
    "Md252": 138.0,
    "Md253": 720.0,
    "Md254": 600.0,
    "Md254m": 1680.0,
    "Md255": 1620.0,
    "Md256": 4620.0,
    "Md257": 19872.0,
    "Md258": 4449600.0,
    "Md258m": 3420.0,
    "Md259": 5760.0,
    "Md260": 2401920.0,
    "Md261": 2400.0,
    "Mg19": 4e-12,
    "Mg20": 0.09,
    "Mg21": 0.122,
    "Mg22": 3.8755,
    "Mg23": 11.317,
    "Mg24": "STABLE",
    "Mg25": "STABLE",
    "Mg26": "STABLE",
    "Mg27": 567.48,
    "Mg28": 75240.0,
    "Mg29": 1.3,
    "Mg30": 0.335,
    "Mg31": 0.23,
    "Mg32": 0.095,
    "Mg33": 0.0905,
    "Mg34": 0.02,
    "Mg35": 0.07,
    "Mg36": 0.005,
    "Mg37": 0.04,
    "Mg38": 0.001,
    "Mg39": 2.6e-07,
    "Mg40": 0.001,
    "Mn44": 1.05e-07,
    "Mn45": 7e-08,
    "Mn46": 0.037,
    "Mn46m": 0.001,
    "Mn47": 0.1,
    "Mn48": 0.1581,
    "Mn49": 0.382,
    "Mn50": 0.28319,
    "Mn50m": 105.0,
    "Mn51": 2772.0,
    "Mn52": 483408.0,
    "Mn52m": 1272.0,
    "Mn53": 116132000000000.0,
    "Mn54": 26973200.0,
    "Mn55": "STABLE",
    "Mn56": 9283.61,
    "Mn57": 85.4,
    "Mn58": 65.2,
    "Mn58m": 2.7,
    "Mn59": 4.59,
    "Mn60": 51.0,
    "Mn60m": 1.79,
    "Mn61": 0.67,
    "Mn62": 0.88,
    "Mn62m": 0.092,
    "Mn63": 0.275,
    "Mn64": 0.0888,
    "Mn64m": 0.0005,
    "Mn65": 0.092,
    "Mn66": 0.0644,
    "Mn67": 0.045,
    "Mn68": 0.028,
    "Mn69": 0.014,
    "Mn70": 0.02418,
    "Mn71": 0.01322,
    "Mn72": 0.009036,
    "Mn73": 0.005936,
    "Mo83": 0.023,
    "Mo84": 0.0038,
    "Mo85": 3.2,
    "Mo86": 19.6,
    "Mo87": 14.02,
    "Mo88": 480.0,
    "Mo89": 126.6,
    "Mo89m": 0.19,
    "Mo90": 20412.0,
    "Mo91": 929.4,
    "Mo91m": 64.6,
    "Mo92": 5.99594e+27,
    "Mo93": 95040000000.0,
    "Mo93m": 24660.0,
    "Mo94": "STABLE",
    "Mo95": "STABLE",
    "Mo96": "STABLE",
    "Mo97": "STABLE",
    "Mo98": 3.15569e+21,
    "Mo99": 237419.0,
    "Mo100": 2.30366e+26,
    "Mo101": 876.6,
    "Mo102": 678.0,
    "Mo103": 67.9,
    "Mo104": 60.0,
    "Mo105": 35.6,
    "Mo106": 8.73,
    "Mo107": 3.5,
    "Mo108": 1.09,
    "Mo109": 0.5,
    "Mo110": 0.3,
    "Mo111": 0.5,
    "Mo112": 1.0,
    "Mo113": 0.1,
    "Mo114": 0.08,
    "Mo115": 0.06,
    "Mo116": 0.03454,
    "Mo117": 0.03003,
    "Mt265": 0.002,
    "Mt266": 0.0012,
    "Mt266m": 0.006,
    "Mt267": 0.01,
    "Mt268": 0.053,
    "Mt269": 0.2,
    "Mt270": 2.0,
    "Mt271": 5.0,
    "Mt273": 20.0,
    "N10": 2e-22,
    "N11": 5.9e-22,
    "N12": 0.011,
    "N13": 598.02,
    "N14": "STABLE",
    "N15": "STABLE",
    "N16": 7.13,
    "N17": 4.17,
    "N18": 0.63,
    "N19": 0.271,
    "N20": 0.13,
    "N21": 0.087,
    "N22": 0.0139,
    "N23": 0.0145,
    "N24": 5.2e-08,
    "N25": 2.6e-07,
    "Na18": 1.3e-21,
    "Na19": 4e-08,
    "Na20": 0.446,
    "Na21": 22.49,
    "Na22": 82139500.0,
    "Na23": "STABLE",
    "Na24": 53848.8,
    "Na24m": 0.0202,
    "Na25": 59.6,
    "Na26": 1.08,
    "Na27": 0.301,
    "Na28": 0.0305,
    "Na29": 0.0449,
    "Na30": 0.0484,
    "Na31": 0.017,
    "Na32": 0.0129,
    "Na33": 0.0082,
    "Na34": 0.0055,
    "Na35": 0.0015,
    "Na36": 1.8e-07,
    "Na37": 0.001,
    "Nb81": 4.4e-08,
    "Nb82": 0.05,
    "Nb83": 4.1,
    "Nb84": 9.8,
    "Nb85": 20.9,
    "Nb85m": 12.0,
    "Nb86": 88.0,
    "Nb86m": 56.0,
    "Nb87": 225.0,
    "Nb87m": 156.0,
    "Nb88": 870.0002,
    "Nb88m": 466.8,
    "Nb89": 7308.0,
    "Nb89m": 3960.0,
    "Nb90": 52524.0,
    "Nb90m": 18.81,
    "Nb90n": 0.00622,
    "Nb91": 21459200000.0,
    "Nb91m": 5261760.0,
    "Nb92": 1104520000000000.0,
    "Nb92m": 876960.0,
    "Nb93": "STABLE",
    "Nb93m": 508698000.0,
    "Nb94": 630720000000.0,
    "Nb94m": 375.6,
    "Nb95": 3023220.0,
    "Nb95m": 311904.0,
    "Nb96": 84060.0,
    "Nb97": 4326.0,
    "Nb97m": 52.7,
    "Nb98": 2.86,
    "Nb98m": 3078.0,
    "Nb99": 15.0,
    "Nb99m": 156.0,
    "Nb100": 1.5,
    "Nb100m": 2.9,
    "Nb101": 7.1,
    "Nb102": 1.3,
    "Nb102m": 1.3,
    "Nb103": 1.5,
    "Nb104": 4.9,
    "Nb104m": 0.94,
    "Nb105": 2.95,
    "Nb106": 0.92,
    "Nb107": 0.3,
    "Nb108": 0.193,
    "Nb109": 0.19,
    "Nb110": 0.17,
    "Nb111": 0.08,
    "Nb112": 0.06,
    "Nb113": 0.03,
    "Nb114": 0.02491,
    "Nb115": 0.01925,
    "Nd124": 0.5,
    "Nd125": 0.6,
    "Nd126": 1.0,
    "Nd127": 1.8,
    "Nd128": 5.0,
    "Nd129": 4.9,
    "Nd130": 21.0,
    "Nd131": 33.0,
    "Nd132": 94.0,
    "Nd133": 70.0,
    "Nd133m": 70.0,
    "Nd134": 510.0,
    "Nd135": 740.0002,
    "Nd135m": 330.0,
    "Nd136": 3039.0,
    "Nd137": 2310.0,
    "Nd137m": 1.6,
    "Nd138": 18144.0,
    "Nd139": 1782.0,
    "Nd139m": 19800.0,
    "Nd140": 291168.0,
    "Nd140m": 0.0006,
    "Nd141": 8952.0,
    "Nd141m": 62.0,
    "Nd142": "STABLE",
    "Nd143": "STABLE",
    "Nd144": 7.22654e+22,
    "Nd145": "STABLE",
    "Nd146": "STABLE",
    "Nd147": 952128.0,
    "Nd148": 9.46708e+25,
    "Nd149": 6220.8,
    "Nd150": 2.11431e+26,
    "Nd151": 746.4,
    "Nd152": 684.0,
    "Nd153": 31.6,
    "Nd154": 25.9,
    "Nd155": 8.9,
    "Nd156": 5.49,
    "Nd157": 2.5,
    "Nd158": 0.7,
    "Nd159": 0.5,
    "Nd160": 0.3,
    "Nd161": 0.2,
    "Nd162": 0.2041,
    "Nd163": 0.1474,
    "Nd164": 0.1081,
    "Ne16": 9e-21,
    "Ne17": 0.1092,
    "Ne18": 1.672,
    "Ne19": 17.22,
    "Ne20": "STABLE",
    "Ne21": "STABLE",
    "Ne22": "STABLE",
    "Ne23": 37.2,
    "Ne24": 202.8,
    "Ne25": 0.602,
    "Ne26": 0.197,
    "Ne27": 0.032,
    "Ne28": 0.0183,
    "Ne29": 0.0156,
    "Ne30": 0.0058,
    "Ne31": 0.0034,
    "Ne32": 0.0035,
    "Ne33": 2.6e-07,
    "Ne34": 0.001,
    "Ni48": 0.0021,
    "Ni49": 0.013,
    "Ni50": 0.0091,
    "Ni51": 0.03,
    "Ni52": 0.038,
    "Ni53": 0.045,
    "Ni54": 0.104,
    "Ni55": 0.2047,
    "Ni56": 524880.0,
    "Ni57": 129254.0,
    "Ni58": 2.20903e+28,
    "Ni59": 2398330000000.0,
    "Ni60": "STABLE",
    "Ni61": "STABLE",
    "Ni62": "STABLE",
    "Ni63": 3114670000.0,
    "Ni64": "STABLE",
    "Ni65": 9072.0,
    "Ni66": 195840.0,
    "Ni67": 21.0,
    "Ni68": 29.0,
    "Ni69": 11.4,
    "Ni69m": 3.5,
    "Ni70": 6.0,
    "Ni71": 2.56,
    "Ni72": 1.57,
    "Ni73": 0.84,
    "Ni74": 0.68,
    "Ni75": 0.6,
    "Ni76": 0.47,
    "Ni77": 0.3,
    "Ni78": 0.2,
    "Ni79": 0.02489,
    "Ni80": 0.01582,
    "Ni81": 0.01228,
    "Ni82": 0.008741,
    "No249": 5.7e-05,
    "No250": 5.7e-06,
    "No251": 0.76,
    "No251m": 1.7,
    "No252": 2.44,
    "No253": 97.2,
    "No254": 51.0,
    "No254m": 0.28,
    "No255": 186.0,
    "No256": 2.91,
    "No257": 24.5,
    "No258": 0.0012,
    "No259": 3480.0,
    "No260": 0.106,
    "No261": 10800.0,
    "No262": 0.005,
    "Np225": 0.003,
    "Np226": 0.035,
    "Np227": 0.51,
    "Np228": 61.4,
    "Np229": 240.0,
    "Np230": 276.0,
    "Np231": 2928.0,
    "Np232": 882.0,
    "Np233": 2172.0,
    "Np234": 380160.0,
    "Np235": 34207700.0,
    "Np236": 4891320000000.0,
    "Np236m": 81000.0,
    "Np237": 67658000000000.0,
    "Np238": 181613.0,
    "Np239": 203558.0,
    "Np240": 3900.0,
    "Np240m": 444.0,
    "Np241": 834.0,
    "Np242": 132.0,
    "Np242m": 330.0,
    "Np243": 111.0,
    "Np244": 137.4,
    "Np245": 38.4,
    "Np246": 16.0,
    "O12": 5.8e-22,
    "O13": 0.00858,
    "O14": 70.606,
    "O15": 122.46,
    "O16": "STABLE",
    "O17": "STABLE",
    "O18": "STABLE",
    "O19": 26.91,
    "O20": 13.51,
    "O21": 3.42,
    "O22": 2.25,
    "O23": 0.09,
    "O24": 0.065,
    "O25": 5e-08,
    "O26": 4e-08,
    "O27": 2.6e-07,
    "O28": 1e-07,
    "Os162": 0.00205,
    "Os163": 0.0055,
    "Os164": 0.021,
    "Os165": 0.071,
    "Os166": 0.216,
    "Os167": 0.81,
    "Os168": 2.06,
    "Os169": 3.46,
    "Os170": 7.46,
    "Os171": 8.3,
    "Os172": 19.2,
    "Os173": 22.4,
    "Os174": 44.0,
    "Os175": 84.0,
    "Os176": 180.0,
    "Os177": 180.0,
    "Os178": 300.0,
    "Os179": 390.0,
    "Os180": 1290.0,
    "Os181": 162.0,
    "Os181m": 6300.0,
    "Os182": 78624.0,
    "Os183": 46800.0,
    "Os183m": 35600.0,
    "Os184": 1.76723e+21,
    "Os185": 8104320.0,
    "Os186": 6.31152e+22,
    "Os187": "STABLE",
    "Os188": "STABLE",
    "Os189": "STABLE",
    "Os189m": 20916.0,
    "Os190": "STABLE",
    "Os190m": 594.0,
    "Os191": 1321920.0,
    "Os191m": 47160.0,
    "Os192": "STABLE",
    "Os192m": 5.9,
    "Os193": 108396.0,
    "Os194": 189342000.0,
    "Os195": 390.0,
    "Os196": 2094.0,
    "Os197": 3.41,
    "Os198": 32.9,
    "Os199": 36.6,
    "Os200": 16.0,
    "Os201": 9.44,
    "P24": 1e-09,
    "P25": 3e-08,
    "P26": 0.03,
    "P27": 0.26,
    "P28": 0.2703,
    "P29": 4.14,
    "P30": 149.88,
    "P31": "STABLE",
    "P32": 1232930.0,
    "P33": 2193090.0,
    "P34": 12.4,
    "P35": 47.3,
    "P36": 5.6,
    "P37": 2.31,
    "P38": 0.64,
    "P39": 0.19,
    "P40": 0.15,
    "P41": 0.15,
    "P42": 0.12,
    "P43": 0.033,
    "P44": 0.03,
    "P45": 0.008,
    "P46": 0.004,
    "Pa212": 0.008,
    "Pa213": 0.007,
    "Pa214": 0.017,
    "Pa215": 0.014,
    "Pa216": 0.105,
    "Pa217": 0.0049,
    "Pa217m": 0.0012,
    "Pa218": 0.00012,
    "Pa219": 5.3e-08,
    "Pa220": 7.8e-07,
    "Pa221": 5.9e-06,
    "Pa222": 0.0032,
    "Pa223": 0.0051,
    "Pa224": 0.844,
    "Pa225": 1.7,
    "Pa226": 108.0,
    "Pa227": 2298.0,
    "Pa228": 79200.0,
    "Pa229": 129600.0,
    "Pa230": 1503400.0,
    "Pa231": 1033830000000.0,
    "Pa232": 113184.0,
    "Pa233": 2331070.0,
    "Pa234": 24120.0,
    "Pa234m": 69.54,
    "Pa235": 1452.0,
    "Pa236": 546.0,
    "Pa237": 522.0,
    "Pa238": 138.0,
    "Pa239": 6480.0,
    "Pa240": 120.0,
    "Pb178": 0.00023,
    "Pb179": 0.003,
    "Pb180": 0.005,
    "Pb181": 0.045,
    "Pb181m": 0.045,
    "Pb182": 0.06,
    "Pb183": 0.535,
    "Pb183m": 0.415,
    "Pb184": 0.49,
    "Pb185": 6.3,
    "Pb185m": 4.07,
    "Pb186": 4.82,
    "Pb187": 15.2,
    "Pb187m": 18.3,
    "Pb188": 25.5,
    "Pb189": 51.0,
    "Pb189m": 60.0,
    "Pb190": 71.0,
    "Pb191": 79.8,
    "Pb191m": 130.8,
    "Pb192": 210.0,
    "Pb193": 300.0,
    "Pb193m": 348.0,
    "Pb194": 720.0,
    "Pb195": 900.0,
    "Pb195m": 900.0002,
    "Pb196": 2220.0,
    "Pb197": 480.0,
    "Pb197m": 2680.0,
    "Pb198": 8640.0,
    "Pb199": 5400.0,
    "Pb199m": 732.0002,
    "Pb200": 77400.0,
    "Pb201": 33840.0,
    "Pb201m": 61.0,
    "Pb202": 1672550000000.0,
    "Pb202m": 12852.0,
    "Pb203": 186944.0,
    "Pb203m": 6.29,
    "Pb203n": 0.48,
    "Pb204": 4.41806e+24,
    "Pb204m": 4050.0,
    "Pb205": 482831000000000.0,
    "Pb205m": 0.0051,
    "Pb206": "STABLE",
    "Pb207": "STABLE",
    "Pb207m": 0.806,
    "Pb208": "STABLE",
    "Pb209": 11797.2,
    "Pb210": 701510000.0,
    "Pb211": 2166.0,
    "Pb212": 38304.0,
    "Pb213": 612.0,
    "Pb214": 1614.96,
    "Pb215": 36.0,
    "Pd91": 0.01,
    "Pd92": 1.1,
    "Pd93": 1.07,
    "Pd94": 9.0,
    "Pd95": 10.0,
    "Pd95m": 13.3,
    "Pd96": 122.0,
    "Pd97": 186.0,
    "Pd98": 1062.0,
    "Pd99": 1284.0,
    "Pd100": 313632.0,
    "Pd101": 30492.0,
    "Pd102": "STABLE",
    "Pd103": 1467070.0,
    "Pd104": "STABLE",
    "Pd105": "STABLE",
    "Pd106": "STABLE",
    "Pd107": 205120000000000.0,
    "Pd107m": 21.3,
    "Pd108": "STABLE",
    "Pd109": 48888.0,
    "Pd109m": 281.4,
    "Pd110": 1.89342e+25,
    "Pd111": 1404.0,
    "Pd111m": 19800.0,
    "Pd112": 73080.0,
    "Pd113": 91.0,
    "Pd113m": 0.3,
    "Pd114": 145.2,
    "Pd115": 25.0,
    "Pd115m": 50.0,
    "Pd116": 11.8,
    "Pd117": 4.3,
    "Pd117m": 0.0191,
    "Pd118": 1.9,
    "Pd119": 0.92,
    "Pd120": 0.5,
    "Pd121": 0.6,
    "Pd122": 0.3,
    "Pd123": 0.2,
    "Pd124": 0.1,
    "Pd125": 0.3987,
    "Pd126": 0.2499,
    "Pd127": 0.06249,
    "Pd128": 0.04493,
    "Pd129": 0.01268,
    "Pd130": 0.009564,
    "Pd131": 0.008902,
    "Pm126": 0.5,
    "Pm127": 1.0,
    "Pm128": 1.0,
    "Pm129": 3.0,
    "Pm130": 2.6,
    "Pm131": 6.3,
    "Pm132": 6.3,
    "Pm133": 15.0,
    "Pm133m": 10.0,
    "Pm134": 5.0,
    "Pm134m": 5.0,
    "Pm135": 49.0,
    "Pm135m": 40.0,
    "Pm136": 107.0,
    "Pm136m": 47.0,
    "Pm137": 120.0,
    "Pm137m": 144.0,
    "Pm138": 10.0,
    "Pm138m": 194.0,
    "Pm139": 249.0,
    "Pm139m": 0.18,
    "Pm140": 9.2,
    "Pm140m": 357.0,
    "Pm141": 1254.0,
    "Pm142": 40.5,
    "Pm142m": 0.002,
    "Pm143": 22982400.0,
    "Pm144": 31363200.0,
    "Pm145": 558570000.0,
    "Pm146": 174528000.0,
    "Pm147": 82744000.0,
    "Pm148": 463968.0,
    "Pm148m": 3567460.0,
    "Pm149": 191088.0,
    "Pm150": 9712.8,
    "Pm151": 102240.0,
    "Pm152": 247.2,
    "Pm152m": 451.2,
    "Pm152n": 864.0,
    "Pm153": 315.0,
    "Pm154": 102.0,
    "Pm154m": 162.0,
    "Pm155": 41.5,
    "Pm156": 26.7,
    "Pm157": 10.56,
    "Pm158": 4.8,
    "Pm159": 3.0,
    "Pm160": 2.0,
    "Pm161": 0.7,
    "Pm162": 0.5,
    "Pm163": 0.2,
    "Pm164": 0.1916,
    "Pm165": 0.1519,
    "Pm166": 0.09856,
    "Po188": 0.00043,
    "Po189": 0.005,
    "Po190": 0.00245,
    "Po191": 0.022,
    "Po191m": 0.098,
    "Po192": 0.0332,
    "Po193": 0.37,
    "Po193m": 0.245,
    "Po194": 0.392,
    "Po195": 4.64,
    "Po195m": 1.92,
    "Po196": 5.56,
    "Po197": 53.6,
    "Po197m": 25.8,
    "Po198": 106.2,
    "Po199": 328.8,
    "Po199m": 250.2,
    "Po200": 690.0,
    "Po201": 918.0,
    "Po201m": 534.0,
    "Po202": 2680.0,
    "Po203": 2202.0,
    "Po203m": 45.0,
    "Po204": 12710.0,
    "Po205": 6264.0,
    "Po205m": 0.0574,
    "Po205n": 0.0574,
    "Po206": 760320.0,
    "Po207": 20880.0,
    "Po207m": 2.79,
    "Po208": 92463800.0,
    "Po209": 3629050000.0,
    "Po210": 11955700.0,
    "Po211": 0.516,
    "Po211m": 25.5,
    "Po212": 3e-07,
    "Po212m": 45.1,
    "Po213": 3.7e-06,
    "Po214": 0.0001623,
    "Po215": 0.001781,
    "Po216": 0.148,
    "Po217": 1.47,
    "Po218": 184.26,
    "Po219": 120.0,
    "Po220": 40.0,
    "Pr121": 0.6,
    "Pr122": 0.5,
    "Pr123": 0.8,
    "Pr124": 1.2,
    "Pr125": 3.3,
    "Pr126": 3.12,
    "Pr127": 4.2,
    "Pr127m": 0.05,
    "Pr128": 2.85,
    "Pr129": 30.0,
    "Pr129m": 0.001,
    "Pr130": 40.0,
    "Pr130m": 10.0,
    "Pr131": 90.0,
    "Pr131m": 5.7,
    "Pr132": 89.4,
    "Pr132m": 20.0,
    "Pr133": 390.0,
    "Pr133m": 1.1,
    "Pr134": 660.0,
    "Pr134m": 660.0,
    "Pr135": 1440.0,
    "Pr136": 786.0,
    "Pr137": 4608.0,
    "Pr138": 87.0,
    "Pr138m": 7632.0,
    "Pr139": 15876.0,
    "Pr140": 203.4,
    "Pr141": "STABLE",
    "Pr142": 68832.0,
    "Pr142m": 876.0002,
    "Pr143": 1171580.0,
    "Pr144": 1037.4,
    "Pr144m": 432.0,
    "Pr145": 21542.4,
    "Pr146": 1449.0,
    "Pr147": 816.0002,
    "Pr148": 137.4,
    "Pr148m": 121.2,
    "Pr149": 135.6,
    "Pr150": 6.1,
    "Pr151": 18.9,
    "Pr152": 3.63,
    "Pr153": 4.28,
    "Pr154": 2.3,
    "Pr155": 1.0,
    "Pr156": 0.5,
    "Pr157": 0.3,
    "Pr158": 0.2,
    "Pr159": 0.1,
    "Pr160": 0.1422,
    "Pr161": 0.08787,
    "Pr162": 0.06418,
    "Pt166": 0.0003,
    "Pt167": 0.0007,
    "Pt168": 0.002,
    "Pt169": 0.0037,
    "Pt170": 0.0138,
    "Pt171": 0.044,
    "Pt172": 0.0984,
    "Pt173": 0.365,
    "Pt174": 0.889,
    "Pt175": 2.53,
    "Pt176": 6.33,
    "Pt177": 10.6,
    "Pt177m": 1.18,
    "Pt178": 21.1,
    "Pt179": 21.2,
    "Pt180": 56.0,
    "Pt181": 52.0,
    "Pt182": 156.0,
    "Pt183": 390.0,
    "Pt183m": 43.0,
    "Pt184": 1038.0,
    "Pt184m": 0.00101,
    "Pt185": 4260.0,
    "Pt185m": 1980.0,
    "Pt186": 7488.0,
    "Pt187": 8460.0,
    "Pt188": 881280.0,
    "Pt189": 39132.0,
    "Pt190": 2.0512e+19,
    "Pt191": 242093.0,
    "Pt192": "STABLE",
    "Pt193": 1577880000.0,
    "Pt193m": 374976.0,
    "Pt194": "STABLE",
    "Pt195": "STABLE",
    "Pt195m": 354240.0,
    "Pt196": "STABLE",
    "Pt197": 71609.4,
    "Pt197m": 5718.0,
    "Pt198": "STABLE",
    "Pt199": 1848.0,
    "Pt199m": 13.6,
    "Pt200": 45000.0,
    "Pt201": 150.0,
    "Pt202": 158400.0,
    "Pt203": 41.1,
    "Pu228": 0.01,
    "Pu229": 120.0,
    "Pu230": 102.0,
    "Pu231": 516.0,
    "Pu232": 2022.0,
    "Pu233": 1254.0,
    "Pu234": 31680.0,
    "Pu235": 1518.0,
    "Pu236": 90191600.0,
    "Pu237": 3913920.0,
    "Pu237m": 0.18,
    "Pu238": 2767540000.0,
    "Pu239": 760948000000.0,
    "Pu240": 207108000000.0,
    "Pu241": 452211000.0,
    "Pu242": 11786800000000.0,
    "Pu243": 17841.6,
    "Pu244": 2524610000000000.0,
    "Pu245": 37800.0,
    "Pu246": 937440.0,
    "Pu247": 196128.0,
    "Ra202": 0.0026,
    "Ra203": 0.031,
    "Ra203m": 0.024,
    "Ra204": 0.06,
    "Ra205": 0.22,
    "Ra205m": 0.18,
    "Ra206": 0.24,
    "Ra207": 1.3,
    "Ra207m": 0.057,
    "Ra208": 1.3,
    "Ra209": 4.6,
    "Ra210": 3.7,
    "Ra211": 13.0,
    "Ra212": 13.0,
    "Ra213": 164.4,
    "Ra213m": 0.00215,
    "Ra214": 2.46,
    "Ra215": 0.00159,
    "Ra216": 1.82e-07,
    "Ra217": 1.6e-06,
    "Ra218": 2.56e-05,
    "Ra219": 0.01,
    "Ra220": 0.018,
    "Ra221": 28.0,
    "Ra222": 36.17,
    "Ra223": 987552.0,
    "Ra224": 313718.0,
    "Ra225": 1280450.0,
    "Ra226": 50491100000.0,
    "Ra227": 2532.0,
    "Ra228": 181452000.0,
    "Ra229": 240.0,
    "Ra230": 5580.0,
    "Ra231": 103.0,
    "Ra232": 250.0,
    "Ra233": 30.0,
    "Ra234": 30.0,
    "Rb71": 1e-09,
    "Rb72": 1.5e-06,
    "Rb73": 3e-08,
    "Rb74": 0.064776,
    "Rb75": 19.0,
    "Rb76": 36.5,
    "Rb77": 226.8,
    "Rb78": 1059.6,
    "Rb78m": 344.4,
    "Rb79": 1374.0,
    "Rb80": 34.0,
    "Rb81": 16474.0,
    "Rb81m": 1815.0,
    "Rb82": 75.912,
    "Rb82m": 23299.2,
    "Rb83": 7447680.0,
    "Rb83m": 0.0078,
    "Rb84": 2894400.0,
    "Rb84m": 1224.0,
    "Rb85": "STABLE",
    "Rb86": 1610500.0,
    "Rb86m": 61.0,
    "Rb87": 1.51789e+18,
    "Rb88": 1068.0,
    "Rb89": 924.0,
    "Rb90": 157.0,
    "Rb90m": 258.0,
    "Rb91": 58.4,
    "Rb92": 4.48,
    "Rb93": 5.8,
    "Rb94": 2.702,
    "Rb95": 0.381,
    "Rb96": 0.199,
    "Rb96m": 0.2,
    "Rb97": 0.1699,
    "Rb98": 0.114,
    "Rb98m": 0.096,
    "Rb99": 0.0503,
    "Rb100": 0.051,
    "Rb101": 0.032,
    "Rb102": 0.037,
    "Rb103": 0.02375,
    "Rb104": 0.01859,
    "Rb105": 0.01253,
    "Re160": 0.00086,
    "Re161": 0.00037,
    "Re161m": 0.0156,
    "Re162": 0.107,
    "Re162m": 0.077,
    "Re163": 0.39,
    "Re163m": 0.214,
    "Re164": 0.53,
    "Re164m": 0.53,
    "Re165": 1.0,
    "Re165m": 2.1,
    "Re166": 2.0,
    "Re166m": 2.5,
    "Re167": 5.9,
    "Re167m": 5.9,
    "Re168": 4.4,
    "Re169": 8.1,
    "Re169m": 15.1,
    "Re170": 9.2,
    "Re171": 15.2,
    "Re172": 15.0,
    "Re172m": 55.0,
    "Re173": 120.0,
    "Re174": 138.0,
    "Re175": 353.4,
    "Re176": 318.0,
    "Re177": 840.0002,
    "Re178": 792.0,
    "Re179": 1170.0,
    "Re180": 146.4,
    "Re181": 71640.0,
    "Re182": 230400.0,
    "Re182m": 45720.0,
    "Re183": 6048000.0,
    "Re183m": 0.00103,
    "Re184": 3058560.0,
    "Re184m": 14515200.0,
    "Re185": "STABLE",
    "Re186": 324000.0,
    "Re186m": 5995820000000.0,
    "Re187": 1.36641e+18,
    "Re188": 61218.0,
    "Re188m": 1116.0,
    "Re189": 87480.0,
    "Re190": 186.0,
    "Re190m": 11500.0,
    "Re191": 582.0,
    "Re192": 6.2,
    "Re193": 30.0,
    "Re194": 2.0,
    "Re195": 10.2,
    "Re196": 3.97,
    "Re197": 4.87,
    "Re198": 2.28,
    "Rf253": 0.013,
    "Rf254": 2.3e-05,
    "Rf255": 1.68,
    "Rf255m": 1.0,
    "Rf256": 0.00645,
    "Rf257": 4.7,
    "Rf257m": 3.9,
    "Rf258": 0.012,
    "Rf259": 2.8,
    "Rf260": 0.021,
    "Rf261": 65.0,
    "Rf261m": 81.0,
    "Rf262": 2.3,
    "Rf262m": 0.047,
    "Rf263": 660.0,
    "Rf264": 3600.0,
    "Rf265": 46800.0,
    "Rg272": 0.002,
    "Rh89": 0.01,
    "Rh90": 0.015,
    "Rh90m": 0.0011,
    "Rh91": 1.74,
    "Rh92": 4.3,
    "Rh93": 13.9,
    "Rh94": 70.6,
    "Rh94m": 25.8,
    "Rh95": 301.0,
    "Rh95m": 117.6,
    "Rh96": 594.0,
    "Rh96m": 90.6,
    "Rh97": 1842.0,
    "Rh97m": 2772.0,
    "Rh98": 523.2,
    "Rh98m": 210.0,
    "Rh99": 1391000.0,
    "Rh99m": 16900.0,
    "Rh100": 74880.0,
    "Rh100m": 276.0,
    "Rh101": 100982000.0,
    "Rh101m": 375840.0,
    "Rh102": 91584000.0,
    "Rh102m": 17971200.0,
    "Rh103": "STABLE",
    "Rh103m": 3366.9,
    "Rh104": 42.3,
    "Rh104m": 260.4,
    "Rh105": 127296.0,
    "Rh105m": 40.0,
    "Rh106": 30.1,
    "Rh106m": 7920.0,
    "Rh107": 1302.0,
    "Rh108": 16.8,
    "Rh108m": 360.0,
    "Rh109": 80.0,
    "Rh110": 28.5,
    "Rh110m": 3.2,
    "Rh111": 12.0,
    "Rh112": 2.1,
    "Rh112m": 6.8,
    "Rh113": 2.8,
    "Rh114": 1.85,
    "Rh114m": 1.85,
    "Rh115": 0.99,
    "Rh116": 0.68,
    "Rh116m": 0.57,
    "Rh117": 0.44,
    "Rh118": 0.32,
    "Rh119": 0.3,
    "Rh120": 0.17,
    "Rh121": 0.25,
    "Rh122": 0.05,
    "Rh123": 0.0489,
    "Rh124": 0.04513,
    "Rh125": 0.03502,
    "Rh126": 0.03277,
    "Rh127": 0.02447,
    "Rh128": 0.007834,
    "Rn193": 0.0012,
    "Rn195": 0.006,
    "Rn195m": 0.006,
    "Rn196": 0.0044,
    "Rn197": 0.066,
    "Rn197m": 0.021,
    "Rn198": 0.065,
    "Rn199": 0.62,
    "Rn199m": 0.32,
    "Rn200": 1.03,
    "Rn201": 7.0,
    "Rn201m": 3.8,
    "Rn202": 9.94,
    "Rn203": 43.5,
    "Rn203m": 26.7,
    "Rn204": 74.4,
    "Rn205": 168.0,
    "Rn206": 340.2,
    "Rn207": 555.0,
    "Rn208": 1461.0,
    "Rn209": 1728.0,
    "Rn210": 8640.0,
    "Rn211": 52600.0,
    "Rn212": 1434.0,
    "Rn213": 0.025,
    "Rn214": 2.7e-07,
    "Rn215": 2.3e-06,
    "Rn216": 4.5e-05,
    "Rn217": 0.00054,
    "Rn218": 0.036,
    "Rn219": 3.98,
    "Rn220": 55.8,
    "Rn221": 1500.0,
    "Rn222": 330324.0,
    "Rn223": 1452.0,
    "Rn224": 6420.0,
    "Rn225": 279.6,
    "Rn226": 444.0,
    "Rn227": 20.8,
    "Rn228": 65.0,
    "Ru87": 0.05,
    "Ru88": 1.3,
    "Ru89": 1.38,
    "Ru90": 11.0,
    "Ru91": 9.0,
    "Ru91m": 7.6,
    "Ru92": 219.0,
    "Ru93": 59.7,
    "Ru93m": 10.8,
    "Ru94": 3108.0,
    "Ru95": 5914.8,
    "Ru96": 2.11436e+24,
    "Ru97": 244512.0,
    "Ru98": "STABLE",
    "Ru99": "STABLE",
    "Ru100": "STABLE",
    "Ru101": "STABLE",
    "Ru102": "STABLE",
    "Ru103": 3392060.0,
    "Ru103m": 0.00169,
    "Ru104": "STABLE",
    "Ru105": 15984.0,
    "Ru106": 32097600.0,
    "Ru107": 225.0,
    "Ru108": 270.0,
    "Ru109": 34.5,
    "Ru110": 12.04,
    "Ru111": 2.12,
    "Ru112": 1.75,
    "Ru113": 0.8,
    "Ru113m": 0.51,
    "Ru114": 0.53,
    "Ru115": 0.7,
    "Ru116": 1.7,
    "Ru117": 0.34,
    "Ru118": 0.7,
    "Ru119": 0.19,
    "Ru120": 0.08,
    "Ru121": 0.05009,
    "Ru122": 0.03724,
    "Ru123": 0.03372,
    "Ru124": 0.02507,
    "S26": 0.01,
    "S27": 0.021,
    "S28": 0.125,
    "S29": 0.187,
    "S30": 1.178,
    "S31": 2.5534,
    "S32": "STABLE",
    "S33": "STABLE",
    "S34": "STABLE",
    "S35": 7538400.0,
    "S36": "STABLE",
    "S37": 299.4,
    "S38": 10218.0,
    "S39": 11.5,
    "S40": 8.8,
    "S41": 1.99,
    "S42": 0.001013,
    "S43": 0.26,
    "S44": 0.123,
    "S45": 0.082,
    "S46": 0.03,
    "S47": 0.02,
    "S48": 0.01,
    "S49": 2e-07,
    "Sb103": 0.1,
    "Sb104": 0.47,
    "Sb105": 1.12,
    "Sb106": 0.6,
    "Sb107": 4.6,
    "Sb108": 7.4,
    "Sb109": 17.0,
    "Sb110": 23.6,
    "Sb111": 75.0,
    "Sb112": 51.4,
    "Sb113": 400.0,
    "Sb114": 209.4,
    "Sb115": 1926.0,
    "Sb116": 948.0,
    "Sb116m": 3618.0,
    "Sb117": 10080.0,
    "Sb118": 216.0,
    "Sb118m": 18000.0,
    "Sb119": 137880.0,
    "Sb119m": 0.85,
    "Sb120": 954.0,
    "Sb120m": 497664.0,
    "Sb121": "STABLE",
    "Sb122": 232920.0,
    "Sb122m": 251.4,
    "Sb123": "STABLE",
    "Sb124": 5201970.0,
    "Sb124m": 93.0,
    "Sb124n": 1212.0,
    "Sb125": 87051400.0,
    "Sb126": 1072220.0,
    "Sb126m": 1146.0,
    "Sb126n": 11.0,
    "Sb127": 332640.0,
    "Sb128": 32436.0,
    "Sb128m": 624.0,
    "Sb129": 15696.0,
    "Sb129m": 1062.0,
    "Sb130": 2370.0,
    "Sb130m": 378.0,
    "Sb131": 1381.8,
    "Sb132": 167.4,
    "Sb132m": 246.0,
    "Sb133": 150.0,
    "Sb134": 0.78,
    "Sb134m": 10.07,
    "Sb135": 1.74,
    "Sb136": 0.923,
    "Sb137": 0.45,
    "Sb138": 0.5,
    "Sb139": 0.3,
    "Sb140": 0.07019,
    "Sb141": 0.04783,
    "Sb142": 0.03986,
    "Sb143": 0.02739,
    "Sc36": 1e-09,
    "Sc37": 1e-09,
    "Sc38": 3e-07,
    "Sc39": 3e-07,
    "Sc40": 0.1823,
    "Sc41": 0.5963,
    "Sc42": 0.6808,
    "Sc42m": 62.0,
    "Sc43": 14007.6,
    "Sc44": 14292.0,
    "Sc44m": 210960.0,
    "Sc45": "STABLE",
    "Sc45m": 0.325,
    "Sc46": 7239200.0,
    "Sc46m": 18.7,
    "Sc47": 289310.0,
    "Sc48": 157212.0,
    "Sc49": 3432.0,
    "Sc50": 102.5,
    "Sc50m": 0.35,
    "Sc51": 12.4,
    "Sc52": 8.2,
    "Sc53": 3.0,
    "Sc54": 0.26,
    "Sc55": 0.12,
    "Sc56": 0.08,
    "Sc57": 0.013,
    "Sc58": 0.012,
    "Sc59": 0.01,
    "Sc60": 0.003,
    "Se65": 0.05,
    "Se66": 0.033,
    "Se67": 0.133,
    "Se68": 35.5,
    "Se69": 27.4,
    "Se70": 2466.0,
    "Se71": 284.4,
    "Se72": 725760.0,
    "Se73": 25560.0,
    "Se73m": 2388.0,
    "Se74": "STABLE",
    "Se75": 10349100.0,
    "Se76": "STABLE",
    "Se77": "STABLE",
    "Se77m": 17.36,
    "Se78": "STABLE",
    "Se79": 11897000000000.0,
    "Se79m": 234.0,
    "Se80": "STABLE",
    "Se81": 1103.4,
    "Se81m": 3436.8,
    "Se82": 3.06102e+27,
    "Se83": 1340.0,
    "Se83m": 70.1,
    "Se84": 195.6,
    "Se85": 31.7,
    "Se86": 15.3,
    "Se87": 5.5,
    "Se88": 1.53,
    "Se89": 0.41,
    "Se90": 0.3,
    "Se91": 0.27,
    "Se92": 0.1,
    "Se93": 0.05,
    "Se94": 0.02,
    "Se95": 0.03173,
    "Se96": 0.01942,
    "Sg258": 0.0033,
    "Sg259": 0.58,
    "Sg260": 0.0038,
    "Sg261": 0.23,
    "Sg262": 0.008,
    "Sg263": 1.0,
    "Sg263m": 0.12,
    "Sg264": 0.4,
    "Sg265": 8.0,
    "Sg266": 21.0,
    "Sg269": 35.0,
    "Si22": 0.029,
    "Si23": 4.23e-08,
    "Si24": 0.14,
    "Si25": 0.22,
    "Si26": 2.234,
    "Si27": 4.17,
    "Si28": "STABLE",
    "Si29": "STABLE",
    "Si30": "STABLE",
    "Si31": 9432.0,
    "Si32": 10414000000.0,
    "Si33": 6.18,
    "Si34": 2.77,
    "Si35": 0.78,
    "Si36": 0.45,
    "Si37": 0.09,
    "Si38": 0.09,
    "Si39": 0.09,
    "Si40": 0.033,
    "Si41": 0.03,
    "Si42": 0.005,
    "Si43": 0.015,
    "Si44": 0.01,
    "Sm128": 0.5,
    "Sm129": 0.55,
    "Sm130": 1.0,
    "Sm131": 1.2,
    "Sm132": 4.0,
    "Sm133": 2.9,
    "Sm134": 10.0,
    "Sm135": 10.3,
    "Sm135m": 2.4,
    "Sm136": 47.0,
    "Sm137": 45.0,
    "Sm137m": 20.0,
    "Sm138": 186.0,
    "Sm139": 154.2,
    "Sm139m": 10.7,
    "Sm140": 889.0002,
    "Sm141": 612.0,
    "Sm141m": 1356.0,
    "Sm142": 4349.4,
    "Sm143": 525.0,
    "Sm143m": 66.0,
    "Sm143n": 0.03,
    "Sm144": "STABLE",
    "Sm145": 29376000.0,
    "Sm146": 3155760000000000.0,
    "Sm147": 3.37659e+18,
    "Sm148": 2.20898e+23,
    "Sm149": 6.31152e+22,
    "Sm150": "STABLE",
    "Sm151": 2988440000.0,
    "Sm152": "STABLE",
    "Sm153": 166627.0,
    "Sm153m": 0.0106,
    "Sm154": "STABLE",
    "Sm155": 1338.0,
    "Sm156": 33840.0,
    "Sm157": 484.0,
    "Sm158": 331.0,
    "Sm159": 11.37,
    "Sm160": 9.6,
    "Sm161": 4.8,
    "Sm162": 2.4,
    "Sm163": 1.0,
    "Sm164": 0.5,
    "Sm165": 0.2,
    "Sm166": 0.4564,
    "Sm167": 0.2686,
    "Sm168": 0.1963,
    "Sn99": 0.005,
    "Sn100": 1.1,
    "Sn101": 3.0,
    "Sn102": 4.6,
    "Sn103": 7.0,
    "Sn104": 20.8,
    "Sn105": 34.0,
    "Sn106": 115.0,
    "Sn107": 174.0,
    "Sn108": 618.0,
    "Sn109": 1080.0,
    "Sn110": 14760.0,
    "Sn111": 2118.0,
    "Sn112": "STABLE",
    "Sn113": 9943780.0,
    "Sn113m": 1254.0,
    "Sn114": "STABLE",
    "Sn115": "STABLE",
    "Sn116": "STABLE",
    "Sn117": "STABLE",
    "Sn117m": 1209600.0,
    "Sn118": "STABLE",
    "Sn119": "STABLE",
    "Sn119m": 25315200.0,
    "Sn120": "STABLE",
    "Sn121": 97164.0,
    "Sn121m": 1385350000.0,
    "Sn122": "STABLE",
    "Sn123": 11162900.0,
    "Sn123m": 2403.6,
    "Sn124": 3.15569e+24,
    "Sn125": 832896.0,
    "Sn125m": 571.8,
    "Sn126": 7258090000000.0,
    "Sn127": 7560.0,
    "Sn127m": 247.8,
    "Sn128": 3544.2,
    "Sn128m": 6.5,
    "Sn129": 133.8,
    "Sn129m": 432.0,
    "Sn130": 223.8,
    "Sn130m": 102.0,
    "Sn131": 39.0,
    "Sn131m": 61.2,
    "Sn132": 39.7,
    "Sn133": 1.46,
    "Sn134": 1.05,
    "Sn135": 0.53,
    "Sn136": 0.25,
    "Sn137": 0.19,
    "Sn138": 0.06692,
    "Sn139": 0.05841,
    "Sn140": 0.04157,
    "Sr73": 0.025,
    "Sr74": 0.05,
    "Sr75": 0.088,
    "Sr76": 8.9,
    "Sr77": 9.0,
    "Sr78": 159.0,
    "Sr79": 135.0,
    "Sr80": 6378.0,
    "Sr81": 1338.0,
    "Sr82": 2189980.0,
    "Sr83": 116676.0,
    "Sr83m": 4.95,
    "Sr84": "STABLE",
    "Sr85": 5603040.0,
    "Sr85m": 4056.6,
    "Sr86": "STABLE",
    "Sr87": "STABLE",
    "Sr87m": 10137.6,
    "Sr88": "STABLE",
    "Sr89": 4369250.0,
    "Sr90": 908839000.0,
    "Sr91": 34740.0,
    "Sr92": 9756.0,
    "Sr93": 445.38,
    "Sr94": 75.3,
    "Sr95": 23.9,
    "Sr96": 1.07,
    "Sr97": 0.429,
    "Sr98": 0.653,
    "Sr99": 0.27,
    "Sr100": 0.202,
    "Sr101": 0.118,
    "Sr102": 0.069,
    "Sr103": 0.05,
    "Sr104": 0.03,
    "Sr105": 0.02,
    "Sr106": 0.02448,
    "Sr107": 0.01942,
    "Ta155": 1.3e-05,
    "Ta156": 0.144,
    "Ta156m": 0.36,
    "Ta157": 0.0101,
    "Ta157m": 0.0043,
    "Ta157n": 0.0017,
    "Ta158": 0.049,
    "Ta158m": 0.036,
    "Ta159": 1.04,
    "Ta159m": 0.514,
    "Ta160": 1.7,
    "Ta160m": 1.55,
    "Ta161": 3.0,
    "Ta161m": 2.89,
    "Ta162": 3.57,
    "Ta163": 10.6,
    "Ta164": 14.2,
    "Ta165": 31.0,
    "Ta166": 34.4,
    "Ta167": 79.8,
    "Ta168": 120.0,
    "Ta169": 294.0,
    "Ta170": 405.6,
    "Ta171": 1398.0,
    "Ta172": 2208.0,
    "Ta173": 11304.0,
    "Ta174": 4104.0,
    "Ta175": 37800.0,
    "Ta176": 29124.0,
    "Ta176m": 0.0011,
    "Ta176n": 0.00097,
    "Ta177": 203040.0,
    "Ta178": 558.6,
    "Ta178m": 8500.0,
    "Ta178n": 0.059,
    "Ta179": 50803200.0,
    "Ta179m": 0.009,
    "Ta179n": 0.0541,
    "Ta180": 29088.0,
    "Ta180m": 5.68037e+22,
    "Ta181": "STABLE",
    "Ta182": 9910080.0,
    "Ta182m": 0.283,
    "Ta182n": 950.4,
    "Ta183": 439776.0,
    "Ta184": 31320.0,
    "Ta185": 2964.0,
    "Ta185m": 0.001,
    "Ta186": 630.0,
    "Ta187": 120.0,
    "Ta188": 20.0,
    "Ta189": 3.0,
    "Ta190": 0.3,
    "Tb135": 0.995,
    "Tb136": 0.2,
    "Tb137": 0.6,
    "Tb138": 0.8,
    "Tb139": 1.6,
    "Tb140": 2.4,
    "Tb141": 3.5,
    "Tb141m": 7.9,
    "Tb142": 0.597,
    "Tb142m": 0.303,
    "Tb143": 12.0,
    "Tb143m": 21.0,
    "Tb144": 1.0,
    "Tb144m": 4.25,
    "Tb145": 1200.0,
    "Tb145m": 29.5,
    "Tb146": 8.0,
    "Tb146m": 24.0,
    "Tb146n": 0.00118,
    "Tb147": 5904.0,
    "Tb147m": 109.8,
    "Tb148": 3600.0,
    "Tb148m": 132.0,
    "Tb149": 14824.8,
    "Tb149m": 249.6,
    "Tb150": 12500.0,
    "Tb150m": 348.0,
    "Tb151": 63392.4,
    "Tb151m": 25.0,
    "Tb152": 63000.0,
    "Tb152m": 258.0,
    "Tb153": 202176.0,
    "Tb154": 77400.0,
    "Tb154m": 32400.0,
    "Tb154n": 81700.0,
    "Tb155": 459648.0,
    "Tb156": 446688.0,
    "Tb156m": 87840.0,
    "Tb156n": 18360.0,
    "Tb157": 3124200000.0,
    "Tb158": 5680250000.0,
    "Tb158m": 10.8,
    "Tb158n": 0.0004,
    "Tb159": "STABLE",
    "Tb160": 6246720.0,
    "Tb161": 595296.0,
    "Tb162": 456.0,
    "Tb163": 1170.0,
    "Tb164": 180.0,
    "Tb165": 126.6,
    "Tb166": 25.6,
    "Tb167": 19.0,
    "Tb168": 8.2,
    "Tb169": 2.0,
    "Tb170": 3.0,
    "Tb171": 0.5,
    "Tb172": 0.6902,
    "Tc85": 1.1e-07,
    "Tc86": 0.055,
    "Tc86m": 1.1e-06,
    "Tc87": 2.2,
    "Tc87m": 2.0,
    "Tc88": 5.8,
    "Tc88m": 6.4,
    "Tc89": 12.8,
    "Tc89m": 12.9,
    "Tc90": 8.7,
    "Tc90m": 49.2,
    "Tc91": 188.3999,
    "Tc91m": 198.0,
    "Tc92": 264.0,
    "Tc93": 9900.0,
    "Tc93m": 2610.0,
    "Tc94": 17580.0,
    "Tc94m": 3114.0,
    "Tc95": 72000.0,
    "Tc95m": 5270400.0,
    "Tc96": 369792.0,
    "Tc96m": 3090.0,
    "Tc97": 82049800000000.0,
    "Tc97m": 7793280.0,
    "Tc98": 135695000000000.0,
    "Tc99": 6674290000000.0,
    "Tc99m": 21624.1,
    "Tc100": 15.46,
    "Tc101": 852.0,
    "Tc102": 5.28,
    "Tc102m": 261.0,
    "Tc103": 54.2,
    "Tc104": 1098.0,
    "Tc105": 456.0,
    "Tc106": 35.6,
    "Tc107": 21.2,
    "Tc108": 5.17,
    "Tc109": 0.86,
    "Tc110": 0.92,
    "Tc111": 0.29,
    "Tc112": 0.29,
    "Tc113": 0.13,
    "Tc114": 0.2,
    "Tc115": 0.27,
    "Tc116": 0.12,
    "Tc117": 0.04,
    "Tc118": 0.03,
    "Tc119": 0.03247,
    "Tc120": 0.02697,
    "Te105": 1e-06,
    "Te106": 6e-05,
    "Te107": 0.0031,
    "Te108": 2.1,
    "Te109": 4.6,
    "Te110": 18.6,
    "Te111": 19.3,
    "Te112": 120.0,
    "Te113": 102.0,
    "Te114": 912.0,
    "Te115": 348.0,
    "Te115m": 402.0,
    "Te116": 8964.0,
    "Te117": 3720.0,
    "Te117m": 0.103,
    "Te118": 518400.0,
    "Te119": 57780.0,
    "Te119m": 406080.0,
    "Te120": "STABLE",
    "Te121": 1655420.0,
    "Te121m": 13305600.0,
    "Te122": "STABLE",
    "Te123": 2.90324e+24,
    "Te123m": 10324800.0,
    "Te124": "STABLE",
    "Te125": "STABLE",
    "Te125m": 4959360.0,
    "Te126": "STABLE",
    "Te127": 33660.0,
    "Te127m": 9167040.0,
    "Te128": 6.94252e+31,
    "Te129": 4176.0,
    "Te129m": 2903040.0,
    "Te130": 2.493e+28,
    "Te131": 1500.0,
    "Te131m": 108000.0,
    "Te132": 279072.0,
    "Te133": 747.0,
    "Te133m": 3324.0,
    "Te134": 2508.0,
    "Te135": 19.0,
    "Te136": 17.5,
    "Te137": 2.49,
    "Te138": 1.4,
    "Te139": 0.5,
    "Te140": 0.3,
    "Te141": 0.1,
    "Te142": 0.05,
    "Te143": 0.06384,
    "Te144": 0.04356,
    "Te145": 0.03794,
    "Th209": 0.007,
    "Th209m": 0.004,
    "Th210": 0.009,
    "Th211": 0.048,
    "Th212": 0.036,
    "Th213": 0.14,
    "Th214": 0.1,
    "Th215": 1.2,
    "Th216": 0.0268,
    "Th217": 0.000251,
    "Th218": 1.17e-07,
    "Th219": 1.05e-06,
    "Th220": 9.7e-06,
    "Th221": 0.00173,
    "Th222": 0.0028,
    "Th223": 0.6,
    "Th224": 1.05,
    "Th225": 523.2,
    "Th226": 1834.2,
    "Th227": 1617240.0,
    "Th228": 60355800.0,
    "Th229": 231633000000.0,
    "Th229m": 252000.0,
    "Th230": 2379440000000.0,
    "Th231": 91879.2,
    "Th232": 4.43384e+17,
    "Th233": 1329.0,
    "Th234": 2082240.0,
    "Th235": 414.0,
    "Th236": 2250.0,
    "Th237": 288.0,
    "Th238": 564.0,
    "Ti38": 1.2e-07,
    "Ti39": 0.031,
    "Ti40": 0.0533,
    "Ti41": 0.08,
    "Ti42": 0.199,
    "Ti43": 0.509,
    "Ti44": 1893420000.0,
    "Ti45": 11088.0,
    "Ti46": "STABLE",
    "Ti47": "STABLE",
    "Ti48": "STABLE",
    "Ti49": "STABLE",
    "Ti50": "STABLE",
    "Ti51": 348.0,
    "Ti52": 102.0,
    "Ti53": 32.7,
    "Ti54": 1.5,
    "Ti55": 0.49,
    "Ti56": 0.164,
    "Ti57": 0.06,
    "Ti58": 0.054,
    "Ti59": 0.03,
    "Ti60": 0.022,
    "Ti61": 0.01,
    "Ti62": 0.01,
    "Ti63": 0.003,
    "Tl176": 0.01,
    "Tl177": 0.018,
    "Tl177m": 0.00023,
    "Tl178": 0.255,
    "Tl179": 0.27,
    "Tl179m": 0.0016,
    "Tl180": 1.5,
    "Tl181": 3.2,
    "Tl181m": 0.0017,
    "Tl182": 2.0,
    "Tl182m": 2.9,
    "Tl183": 6.9,
    "Tl183m": 0.06,
    "Tl184": 9.7,
    "Tl184m": 10.0,
    "Tl185": 19.5,
    "Tl185m": 1.83,
    "Tl186": 40.0,
    "Tl186m": 2.9,
    "Tl186n": 2.9,
    "Tl187": 51.0,
    "Tl187m": 15.6,
    "Tl188": 71.0,
    "Tl188m": 71.0,
    "Tl188n": 0.041,
    "Tl189": 138.0,
    "Tl189m": 84.0,
    "Tl190": 156.0,
    "Tl190m": 222.0,
    "Tl191": 1200.0,
    "Tl191m": 313.2,
    "Tl192": 576.0,
    "Tl192m": 648.0,
    "Tl193": 1308.0,
    "Tl193m": 126.6,
    "Tl194": 1980.0,
    "Tl194m": 1968.0,
    "Tl195": 4180.0,
    "Tl195m": 3.6,
    "Tl196": 6624.0,
    "Tl196m": 5080.0,
    "Tl197": 10224.0,
    "Tl197m": 0.54,
    "Tl198": 19080.0,
    "Tl198m": 6732.0,
    "Tl198n": 0.0321,
    "Tl199": 26712.0,
    "Tl199m": 0.0284,
    "Tl200": 93960.0,
    "Tl200m": 0.0343,
    "Tl201": 262837.0,
    "Tl201m": 0.002035,
    "Tl202": 1057540.0,
    "Tl203": "STABLE",
    "Tl204": 119538000.0,
    "Tl205": "STABLE",
    "Tl206": 252.12,
    "Tl206m": 225.6,
    "Tl207": 286.44,
    "Tl207m": 1.33,
    "Tl208": 183.48,
    "Tl209": 129.66,
    "Tl210": 78.0,
    "Tl211": 60.0,
    "Tl212": 30.0,
    "Tm145": 3.1e-06,
    "Tm146": 0.08,
    "Tm146m": 0.072,
    "Tm147": 0.58,
    "Tm148": 0.7,
    "Tm149": 0.9,
    "Tm150": 3.0,
    "Tm150m": 2.2,
    "Tm150n": 0.0052,
    "Tm151": 4.17,
    "Tm151m": 6.6,
    "Tm152": 8.0,
    "Tm152m": 5.2,
    "Tm153": 1.48,
    "Tm153m": 2.5,
    "Tm154": 8.1,
    "Tm154m": 3.3,
    "Tm155": 21.6,
    "Tm155m": 45.0,
    "Tm156": 83.8,
    "Tm157": 217.8,
    "Tm158": 238.8,
    "Tm159": 549.0,
    "Tm160": 564.0,
    "Tm160m": 74.5,
    "Tm161": 2280.0,
    "Tm161m": 300.0,
    "Tm162": 1302.0,
    "Tm162m": 24.3,
    "Tm163": 6516.0,
    "Tm164": 120.0,
    "Tm164m": 306.0,
    "Tm165": 108216.0,
    "Tm166": 27720.0,
    "Tm166m": 0.34,
    "Tm167": 799200.0,
    "Tm168": 8043840.0,
    "Tm169": "STABLE",
    "Tm170": 11111000.0,
    "Tm171": 60480000.0,
    "Tm172": 228960.0,
    "Tm173": 29664.0,
    "Tm174": 324.0,
    "Tm175": 910.0002,
    "Tm176": 114.0,
    "Tm177": 90.0,
    "Tm178": 30.0,
    "Tm179": 20.0,
    "U217": 0.026,
    "U218": 0.006,
    "U219": 4.2e-05,
    "U220": 6e-08,
    "U221": 7e-07,
    "U222": 1.4e-06,
    "U223": 5.5e-05,
    "U224": 0.00094,
    "U225": 0.061,
    "U226": 0.35,
    "U227": 66.0,
    "U228": 546.0,
    "U229": 3480.0,
    "U230": 1797120.0,
    "U231": 362880.0,
    "U232": 2202720000.0,
    "U233": 5025550000000.0,
    "U234": 7753700000000.0,
    "U235": 2.22102e+16,
    "U235m": 1560.0,
    "U236": 747915000000000.0,
    "U237": 583114.0,
    "U238": 1.40996e+17,
    "U239": 1407.6,
    "U240": 50760.0,
    "U241": 300.0,
    "U242": 1008.0,
    "U243": 160.0,
    "U244": 157.0,
    "U245": 11.4,
    "V40": 1e-09,
    "V41": 1e-09,
    "V42": 5.5e-08,
    "V43": 0.08,
    "V44": 0.111,
    "V44m": 0.15,
    "V45": 0.547,
    "V46": 0.4225,
    "V46m": 0.00102,
    "V47": 1956.0,
    "V48": 1380150.0,
    "V49": 28512000.0,
    "V50": 4.41797e+24,
    "V51": "STABLE",
    "V52": 224.7,
    "V53": 97.2,
    "V54": 49.8,
    "V55": 6.54,
    "V56": 0.216,
    "V57": 0.35,
    "V58": 0.191,
    "V59": 0.075,
    "V60": 0.122,
    "V61": 0.047,
    "V62": 0.0335,
    "V63": 0.017,
    "V64": 0.01,
    "V65": 0.01,
    "V66": 0.00999,
    "W158": 0.00137,
    "W158m": 0.000143,
    "W159": 0.0082,
    "W160": 0.09,
    "W161": 0.409,
    "W162": 1.36,
    "W163": 2.8,
    "W164": 6.3,
    "W165": 5.1,
    "W166": 19.2,
    "W167": 19.9,
    "W168": 51.0,
    "W169": 76.0,
    "W170": 145.2,
    "W171": 142.8,
    "W172": 400.0,
    "W173": 456.0,
    "W174": 1760.0,
    "W175": 2112.0,
    "W176": 9000.0,
    "W177": 7920.0,
    "W178": 1866240.0,
    "W179": 2223.0,
    "W179m": 384.0,
    "W180": "STABLE",
    "W180m": 0.00547,
    "W181": 10452700.0,
    "W182": "STABLE",
    "W183": 3.47134e+24,
    "W183m": 5.25,
    "W184": 1.2623e+25,
    "W185": 6488640.0,
    "W185m": 100.0,
    "W186": 1.8619e+25,
    "W186m": 0.003,
    "W187": 85860.0,
    "W188": 6028990.0,
    "W189": 690.0,
    "W190": 1800.0,
    "W190m": 0.0031,
    "W191": 20.0,
    "W192": 10.0,
    "W193": 102.0,
    "W194": 24.43,
    "Xe109": 0.013,
    "Xe110": 0.31,
    "Xe111": 0.74,
    "Xe112": 2.7,
    "Xe113": 2.74,
    "Xe114": 10.0,
    "Xe115": 18.0,
    "Xe116": 59.0,
    "Xe117": 61.0,
    "Xe118": 360.0,
    "Xe119": 348.0,
    "Xe120": 2400.0,
    "Xe121": 2406.0,
    "Xe122": 72360.0,
    "Xe123": 7488.0,
    "Xe124": 6.31152e+21,
    "Xe125": 60840.0,
    "Xe125m": 56.0,
    "Xe126": "STABLE",
    "Xe127": 3141330.0,
    "Xe127m": 69.6,
    "Xe128": "STABLE",
    "Xe129": "STABLE",
    "Xe129m": 767232.0,
    "Xe130": "STABLE",
    "Xe131": "STABLE",
    "Xe131m": 1033520.0,
    "Xe132": "STABLE",
    "Xe132m": 0.00839,
    "Xe133": 453375.0,
    "Xe133m": 189907.0,
    "Xe134": 3.47126e+23,
    "Xe134m": 0.29,
    "Xe135": 32904.0,
    "Xe135m": 918.0,
    "Xe136": 3.15569e+29,
    "Xe137": 229.08,
    "Xe138": 844.8,
    "Xe139": 39.68,
    "Xe140": 13.6,
    "Xe141": 1.73,
    "Xe142": 1.22,
    "Xe143": 0.511,
    "Xe144": 0.388,
    "Xe145": 0.188,
    "Xe146": 0.146,
    "Xe147": 0.13,
    "Xe148": 0.05883,
    "Xe149": 0.05735,
    "Xe150": 0.03675,
    "Y76": 5e-07,
    "Y77": 0.063,
    "Y78": 0.054,
    "Y78m": 0.0058,
    "Y79": 14.8,
    "Y80": 35.0,
    "Y80m": 4.8,
    "Y81": 70.4,
    "Y82": 9.5,
    "Y83": 425.0,
    "Y83m": 171.0,
    "Y84": 2370.0,
    "Y84m": 4.6,
    "Y85": 9650.0,
    "Y85m": 17500.0,
    "Y86": 53064.0,
    "Y86m": 2880.0,
    "Y87": 287280.0,
    "Y87m": 48132.0,
    "Y88": 9212830.0,
    "Y88m": 0.0139,
    "Y88n": 0.01397,
    "Y89": "STABLE",
    "Y89m": 15.663,
    "Y90": 230400.0,
    "Y90m": 11484.0,
    "Y91": 5055260.0,
    "Y91m": 2982.6,
    "Y92": 12744.0,
    "Y93": 36648.0,
    "Y93m": 0.82,
    "Y94": 1122.0,
    "Y95": 618.0,
    "Y96": 5.34,
    "Y96m": 9.62,
    "Y97": 3.75,
    "Y97m": 1.17,
    "Y97n": 0.142,
    "Y98": 0.59,
    "Y98m": 2.0,
    "Y99": 1.477,
    "Y100": 0.735,
    "Y100m": 0.94,
    "Y101": 0.45,
    "Y102": 0.3,
    "Y102m": 0.36,
    "Y103": 0.224,
    "Y104": 0.13,
    "Y105": 0.15,
    "Y106": 0.05,
    "Y107": 0.03,
    "Y108": 0.02,
    "Y109": 0.0189,
    "Yb148": 0.25,
    "Yb149": 0.7,
    "Yb150": 0.7,
    "Yb151": 1.6,
    "Yb151m": 1.6,
    "Yb152": 3.04,
    "Yb153": 4.2,
    "Yb154": 0.409,
    "Yb155": 1.793,
    "Yb156": 26.1,
    "Yb157": 38.6,
    "Yb158": 89.4,
    "Yb159": 84.0,
    "Yb160": 288.0,
    "Yb161": 252.0,
    "Yb162": 1132.2,
    "Yb163": 663.0,
    "Yb164": 4548.0,
    "Yb165": 594.0,
    "Yb166": 204120.0,
    "Yb167": 1050.0,
    "Yb168": 4.10249e+21,
    "Yb169": 2766360.0,
    "Yb169m": 46.0,
    "Yb170": "STABLE",
    "Yb171": "STABLE",
    "Yb171m": 0.00525,
    "Yb172": "STABLE",
    "Yb173": "STABLE",
    "Yb174": "STABLE",
    "Yb175": 361584.0,
    "Yb175m": 0.0682,
    "Yb176": "STABLE",
    "Yb176m": 11.4,
    "Yb177": 6879.6,
    "Yb177m": 6.41,
    "Yb178": 4440.0,
    "Yb179": 480.0,
    "Yb180": 144.0,
    "Yb181": 60.0,
    "Zn54": 1e-09,
    "Zn55": 0.02,
    "Zn56": 0.036,
    "Zn57": 0.038,
    "Zn58": 0.084,
    "Zn59": 0.182,
    "Zn60": 142.8,
    "Zn61": 89.1,
    "Zn61m": 0.43,
    "Zn61n": 0.14,
    "Zn61o": 0.13,
    "Zn62": 33094.8,
    "Zn63": 2299.8,
    "Zn64": 7.25825e+25,
    "Zn65": 21082500.0,
    "Zn66": "STABLE",
    "Zn67": "STABLE",
    "Zn68": "STABLE",
    "Zn69": 3384.0,
    "Zn69m": 49608.0,
    "Zn70": "STABLE",
    "Zn71": 147.0,
    "Zn71m": 14256.0,
    "Zn72": 167400.0,
    "Zn73": 23.5,
    "Zn73m": 13.0,
    "Zn73n": 5.8,
    "Zn74": 95.6,
    "Zn75": 10.2,
    "Zn76": 5.7,
    "Zn77": 2.08,
    "Zn77m": 1.05,
    "Zn78": 1.47,
    "Zn79": 0.995,
    "Zn80": 0.54,
    "Zn81": 0.29,
    "Zn82": 0.1,
    "Zn83": 0.08,
    "Zn84": 0.02534,
    "Zn85": 0.01936,
    "Zn86": 0.01328,
    "Zr78": 0.05,
    "Zr79": 0.056,
    "Zr80": 4.6,
    "Zr81": 5.5,
    "Zr82": 32.0,
    "Zr83": 41.6,
    "Zr84": 1550.0,
    "Zr85": 471.6,
    "Zr85m": 10.9,
    "Zr86": 59400.0,
    "Zr87": 6048.0,
    "Zr87m": 14.0,
    "Zr88": 7205760.0,
    "Zr89": 282312.0,
    "Zr89m": 250.8,
    "Zr90": "STABLE",
    "Zr90m": 0.8082,
    "Zr91": "STABLE",
    "Zr92": "STABLE",
    "Zr93": 48282100000000.0,
    "Zr94": 3.47126e+24,
    "Zr95": 5532360.0,
    "Zr96": 6.31139e+26,
    "Zr97": 60278.4,
    "Zr98": 30.7,
    "Zr99": 2.2,
    "Zr100": 7.1,
    "Zr101": 2.3,
    "Zr102": 2.9,
    "Zr103": 1.3,
    "Zr104": 1.2,
    "Zr105": 0.6,
    "Zr106": 0.9,
    "Zr107": 0.24,
    "Zr108": 0.08,
    "Zr109": 0.06,
    "Zr110": 0.03,
    "Zr111": 0.02864,
    "Zr112": 0.02143
}