{"ceplan":{"Amazonas":"Norte","Apurímac":"Sur","Arequipa":"Sur","Ayacucho":"Sur","Cajamarca":"Norte","Cusco":"Sur","Huancavelica":"Sur","Huánuco":"Centro","Ica":"Sur","Junín":"Centro","La Libertad":"Norte","Lambayeque":"Norte","Lima Metropolitana":"Centro","Lima Región":"Centro","Loreto":"Nororiente","Madre de Dios":"Sur","Moquegua":"Sur","Pasco":"Centro","Piura":"Norte","Puno":"Sur","San Martín":"Norte","Tacna":"Sur","Tumbes":"Norte","Ucayali":"Nororiente","Áncash":"Centro"},"inei":{"Amazonas":"Oriente","Apurímac":"Sur","Arequipa":"Sur","Ayacucho":"Centro","Cajamarca":"Norte","Callao":"Lima Metropolitana","Cusco":"Sur","Huancavelica":"Centro","Huánuco":"Centro","Ica":"Centro","Junín":"Centro","La Libertad":"Norte","Lambayeque":"Norte","Lima":"Lima Metropolitana", "Lima Metropolitana":"Lima Metropolitana", "Lima Región": "Lima Región", "Loreto":"Oriente","Madre de Dios":"Sur","Moquegua":"Sur","Pasco":"Centro","Piura":"Norte","Puno":"Sur","San Martín":"Oriente","Tacna":"Sur","Tumbes":"Norte","Ucayali":"Oriente","Áncash":"Centro"},"minsa":{"Amazonas":"Oriente","Apurímac":"Centro","Arequipa":"Sur","Ayacucho":"Centro","Cajamarca":"Norte","Callao":"Lima y Callao","Cusco":"Sur","Huancavelica":"Centro","Huánuco":"Centro","Ica":"Centro","Junín":"Centro","La Libertad":"Norte","Lambayeque":"Norte","Lima":"Lima y Callao","Loreto":"Oriente","Madre de Dios":"Sur","Moquegua":"Sur","Pasco":"Centro","Piura":"Norte","Puno":"Sur","San Martín":"Oriente","Tacna":"Sur","Tumbes":"Norte","Ucayali":"Oriente","Áncash":"Norte"}}