{
  "license": {
    "compatibility": {
      "contamination_effect": "none",
      "dynamic_linking": {
        "compatible_with": [
          "MIT",
          "Apache-2.0",
          "BSD-3-Clause",
          "ISC"
        ],
        "incompatible_with": [
          "GPL-2.0",
          "GPL-3.0",
          "AGPL-3.0"
        ],
        "requires_review": [
          "LGPL-2.1",
          "LGPL-3.0"
        ]
      },
      "notes": "C-UDA-1.0 is a permissive license, allowing for broad compatibility with other permissive licenses. However, it is incompatible with copyleft licenses like GPL.",
      "static_linking": {
        "compatible_with": [
          "MIT",
          "Apache-2.0",
          "BSD-3-Clause",
          "ISC"
        ],
        "incompatible_with": [
          "GPL-2.0",
          "GPL-3.0",
          "AGPL-3.0"
        ],
        "requires_review": [
          "LGPL-2.1",
          "LGPL-3.0"
        ]
      }
    },
    "id": "C-UDA-1.0",
    "key_requirements": [
      "Follow the terms of the C-UDA when using, modifying, or distributing the Data.",
      "Provide Data on an 'as is' basis without warranties.",
      "No liability for damages from the use of Data or Results."
    ],
    "limitations": {
      "liability": true,
      "trademark_use": false,
      "warranty": true
    },
    "name": "C-UDA-1.0",
    "obligations": [
      "Use the Data solely for Computational Use.",
      "Include all credit or attribution information with redistributed Data.",
      "Bind each Downstream Recipient to the terms of the C-UDA."
    ],
    "properties": {
      "commercial_use": true,
      "distribution": true,
      "modification": true,
      "patent_grant": true,
      "private_use": true
    },
    "requirements": {
      "disclose_source": true,
      "include_copyright": true,
      "include_license": true,
      "include_notice": true,
      "network_use_disclosure": false,
      "same_license": true,
      "state_changes": false
    },
    "spdx_id": "C-UDA-1.0",
    "type": "permissive"
  }
}