{
  "license": {
    "compatibility": {
      "contamination_effect": "none",
      "dynamic_linking": {
        "compatible_with": [
          "MIT",
          "BSD",
          "Apache-2.0",
          "Zlib",
          "ISC"
        ],
        "incompatible_with": [
          "GPL-2.0",
          "GPL-3.0",
          "AGPL-3.0"
        ],
        "requires_review": [
          "MPL-2.0",
          "LGPL-2.1",
          "LGPL-3.0"
        ]
      },
      "notes": "The Gnuplot license is permissive and allows for integration with other permissive licenses without imposing restrictions. However, care should be taken when combining with copyleft licenses.",
      "static_linking": {
        "compatible_with": [
          "MIT",
          "BSD",
          "Apache-2.0",
          "Zlib",
          "ISC"
        ],
        "incompatible_with": [
          "GPL-2.0",
          "GPL-3.0",
          "AGPL-3.0"
        ],
        "requires_review": [
          "MPL-2.0",
          "LGPL-2.1",
          "LGPL-3.0"
        ]
      }
    },
    "id": "gnuplot",
    "key_requirements": [
      "Distribute corresponding source modifications in the form of a patch file along with binaries.",
      "Add special version identification to distinguish your version.",
      "Provide your name and address as the primary contact for support."
    ],
    "limitations": {
      "liability": true,
      "trademark_use": false,
      "warranty": true
    },
    "name": "gnuplot",
    "obligations": [
      "Include the copyright notice in all copies of the software.",
      "Include the permission notice in supporting documentation.",
      "Distribute modifications as patches to the released version.",
      "Add special version identification to distinguish modified versions.",
      "Provide contact information for support of modified versions.",
      "Retain original authors' contact information for the base software."
    ],
    "properties": {
      "commercial_use": true,
      "distribution": true,
      "modification": true,
      "patent_grant": false,
      "private_use": true
    },
    "requirements": {
      "disclose_source": false,
      "include_copyright": true,
      "include_license": true,
      "include_notice": true,
      "network_use_disclosure": false,
      "same_license": false,
      "state_changes": true
    },
    "spdx_id": "gnuplot",
    "type": "permissive"
  }
}