[{"id":1087486,"title":"Account Manager (Renewals)","company":"GitLab","companyDomain":"gitlab.com","department":"Renewals","category":"customer-success","location":"Remote, North America","url":"https://job-boards.greenhouse.io/gitlab/jobs/8347845002","firstSeen":"2026-01-10T09:23:59.596Z","lastSeen":"2026-01-11T01:52:53.701Z"},{"id":1087490,"title":"Associate Support Engineer (AMER - PST / MST)","company":"GitLab","companyDomain":"gitlab.com","department":"Customer Support","category":"customer-success","location":"Remote, Canada; Remote, Chile; Remote, Costa Rica; Remote, Mexico; Remote, US","url":"https://job-boards.greenhouse.io/gitlab/jobs/8231973002","firstSeen":"2026-01-10T09:23:59.596Z","lastSeen":"2026-01-11T01:52:53.701Z"},{"id":1087491,"title":"Associate Support Engineer (EMEA)","company":"GitLab","companyDomain":"gitlab.com","department":"Customer Support","category":"customer-success","location":"Remote, EMEA","url":"https://job-boards.greenhouse.io/gitlab/jobs/8324426002","firstSeen":"2026-01-10T09:23:59.596Z","lastSeen":"2026-01-11T01:52:53.701Z"},{"id":1087538,"title":"Manager, Customer Success Engineers","company":"GitLab","companyDomain":"gitlab.com","department":"Customer Success Architecture","category":"customer-success","location":"Remote, Canada; Remote, US","url":"https://job-boards.greenhouse.io/gitlab/jobs/8340423002","firstSeen":"2026-01-10T09:23:59.596Z","lastSeen":"2026-01-11T01:52:53.701Z"},{"id":1087046,"title":"Product Support Specialist, APAC","company":"Linear","companyDomain":"linear.app","department":"Product Support","category":"customer-success","location":"Australia - Remote","url":"https://jobs.ashbyhq.com/linear/0b120d06-575f-4e71-9724-68f38de6824a","firstSeen":"2026-01-10T09:16:06.042Z","lastSeen":"2026-01-11T01:51:58.965Z"},{"id":1087053,"title":"Scaled Customer Success Manager","company":"Linear","companyDomain":"linear.app","department":"GTM","category":"customer-success","location":"North America - Remote","url":"https://jobs.ashbyhq.com/linear/ef9037bf-747d-4575-93b9-906959438a6c","firstSeen":"2026-01-10T09:16:06.042Z","lastSeen":"2026-01-11T01:51:58.965Z"},{"id":1087054,"title":"Customer Success Manager, EU","company":"Linear","companyDomain":"linear.app","department":"GTM","category":"customer-success","location":"London - Remote","url":"https://jobs.ashbyhq.com/linear/c3457e89-9ac2-4017-93d5-d1a7935782a0","firstSeen":"2026-01-10T09:16:06.042Z","lastSeen":"2026-01-11T01:51:58.965Z"},{"id":1086846,"title":"Provider Experience Specialist (Atlanta)","company":"Zocdoc","companyDomain":"zocdoc.com","department":"Customer Experience","category":"customer-success","location":"USA Remote","url":"https://job-boards.greenhouse.io/zocdoc/jobs/7244150","firstSeen":"2026-01-10T09:10:07.281Z","lastSeen":"2026-01-11T01:50:45.392Z"},{"id":1086847,"title":"Provider Experience Specialist (Cleveland)","company":"Zocdoc","companyDomain":"zocdoc.com","department":"Customer Experience","category":"customer-success","location":"USA Remote","url":"https://job-boards.greenhouse.io/zocdoc/jobs/7316163","firstSeen":"2026-01-10T09:10:07.281Z","lastSeen":"2026-01-11T01:50:45.392Z"},{"id":1086848,"title":"Provider Experience Specialist (Denver)","company":"Zocdoc","companyDomain":"zocdoc.com","department":"Customer Experience","category":"customer-success","location":"USA Remote","url":"https://job-boards.greenhouse.io/zocdoc/jobs/7251166","firstSeen":"2026-01-10T09:10:07.281Z","lastSeen":"2026-01-11T01:50:45.392Z"},{"id":1086849,"title":"Provider Experience Specialist (Detroit)","company":"Zocdoc","companyDomain":"zocdoc.com","department":"Customer Experience","category":"customer-success","location":"USA Remote","url":"https://job-boards.greenhouse.io/zocdoc/jobs/7347889","firstSeen":"2026-01-10T09:10:07.281Z","lastSeen":"2026-01-11T01:50:45.392Z"},{"id":1086850,"title":"Provider Experience Specialist (Indianapolis)","company":"Zocdoc","companyDomain":"zocdoc.com","department":"Customer Experience","category":"customer-success","location":"USA Remote","url":"https://job-boards.greenhouse.io/zocdoc/jobs/7347939","firstSeen":"2026-01-10T09:10:07.281Z","lastSeen":"2026-01-11T01:50:45.392Z"},{"id":1086851,"title":"Provider Experience Specialist (New York)","company":"Zocdoc","companyDomain":"zocdoc.com","department":"Customer Experience","category":"customer-success","location":"USA Remote","url":"https://job-boards.greenhouse.io/zocdoc/jobs/7251172","firstSeen":"2026-01-10T09:10:07.281Z","lastSeen":"2026-01-11T01:50:45.392Z"},{"id":1086852,"title":"Provider Experience Specialist (Philadelphia)","company":"Zocdoc","companyDomain":"zocdoc.com","department":"Customer Experience","category":"customer-success","location":"USA Remote","url":"https://job-boards.greenhouse.io/zocdoc/jobs/7316185","firstSeen":"2026-01-10T09:10:07.281Z","lastSeen":"2026-01-11T01:50:45.392Z"},{"id":1086853,"title":"Provider Experience Specialist (Phoenix)","company":"Zocdoc","companyDomain":"zocdoc.com","department":"Customer Experience","category":"customer-success","location":"USA Remote","url":"https://job-boards.greenhouse.io/zocdoc/jobs/7251161","firstSeen":"2026-01-10T09:10:07.281Z","lastSeen":"2026-01-11T01:50:45.392Z"},{"id":1086854,"title":"Provider Experience Specialist (Portland)","company":"Zocdoc","companyDomain":"zocdoc.com","department":"Customer Experience","category":"customer-success","location":"USA Remote","url":"https://job-boards.greenhouse.io/zocdoc/jobs/7316144","firstSeen":"2026-01-10T09:10:07.281Z","lastSeen":"2026-01-11T01:50:45.392Z"},{"id":1086855,"title":"Provider Experience Specialist (Seattle)","company":"Zocdoc","companyDomain":"zocdoc.com","department":"Customer Experience","category":"customer-success","location":"USA Remote","url":"https://job-boards.greenhouse.io/zocdoc/jobs/7508764","firstSeen":"2026-01-10T09:10:07.281Z","lastSeen":"2026-01-11T01:50:45.392Z"},{"id":1086856,"title":"Provider Experience Specialist (St. Louis)","company":"Zocdoc","companyDomain":"zocdoc.com","department":"Customer Experience","category":"customer-success","location":"USA Remote","url":"https://job-boards.greenhouse.io/zocdoc/jobs/7347952","firstSeen":"2026-01-10T09:10:07.281Z","lastSeen":"2026-01-11T01:50:45.392Z"},{"id":1086857,"title":"Provider Experience Specialist (Virginia Beach)","company":"Zocdoc","companyDomain":"zocdoc.com","department":"Customer Experience","category":"customer-success","location":"USA Remote","url":"https://job-boards.greenhouse.io/zocdoc/jobs/7348005","firstSeen":"2026-01-10T09:10:07.281Z","lastSeen":"2026-01-11T01:50:45.392Z"},{"id":1086532,"title":"Technical Account Manager Architect - AMER","company":"ClickHouse","companyDomain":"clickhouse.com","department":"Support Services","category":"customer-success","location":"United States (Remote)","url":"https://job-boards.greenhouse.io/clickhouse/jobs/5740982004","firstSeen":"2026-01-10T09:02:04.273Z","lastSeen":"2026-01-11T01:45:10.708Z"},{"id":1086533,"title":"Technical Account Manager Architect - APJ","company":"ClickHouse","companyDomain":"clickhouse.com","department":"Support Services","category":"customer-success","location":"Australia (Remote)","url":"https://job-boards.greenhouse.io/clickhouse/jobs/5745866004","firstSeen":"2026-01-10T09:02:04.273Z","lastSeen":"2026-01-11T01:45:10.708Z"},{"id":1086534,"title":"Technical Account Manager Architect - EMEA","company":"ClickHouse","companyDomain":"clickhouse.com","department":"Support Services","category":"customer-success","location":"EMEA (Remote)","url":"https://job-boards.greenhouse.io/clickhouse/jobs/5655517004","firstSeen":"2026-01-10T09:02:04.273Z","lastSeen":"2026-01-11T01:45:10.708Z"},{"id":1086535,"title":"Technical Account Manager Architect - India","company":"ClickHouse","companyDomain":"clickhouse.com","department":"Support Services","category":"customer-success","location":"India (Remote)","url":"https://job-boards.greenhouse.io/clickhouse/jobs/5655521004","firstSeen":"2026-01-10T09:02:04.273Z","lastSeen":"2026-01-11T01:45:10.708Z"},{"id":1086536,"title":"Technical Customer Support Engineer - AMER (EST)","company":"ClickHouse","companyDomain":"clickhouse.com","department":"Support Services","category":"customer-success","location":"United States (Remote)","url":"https://job-boards.greenhouse.io/clickhouse/jobs/5706781004","firstSeen":"2026-01-10T09:02:04.273Z","lastSeen":"2026-01-11T01:45:10.708Z"},{"id":1086537,"title":"Technical Customer Support Engineer - APJ","company":"ClickHouse","companyDomain":"clickhouse.com","department":"Support Services","category":"customer-success","location":"Australia (Remote)","url":"https://job-boards.greenhouse.io/clickhouse/jobs/5749051004","firstSeen":"2026-01-10T09:02:04.273Z","lastSeen":"2026-01-11T01:45:10.708Z"},{"id":1086538,"title":"Technical Customer Support Engineer - APJ","company":"ClickHouse","companyDomain":"clickhouse.com","department":"Support Services","category":"customer-success","location":"Singapore (Remote)","url":"https://job-boards.greenhouse.io/clickhouse/jobs/5749053004","firstSeen":"2026-01-10T09:02:04.273Z","lastSeen":"2026-01-11T01:45:10.708Z"},{"id":1086539,"title":"Technical Customer Support Engineer - Dutch speaking (Remote)","company":"ClickHouse","companyDomain":"clickhouse.com","department":"Support Services","category":"customer-success","location":"Netherlands (Remote)","url":"https://job-boards.greenhouse.io/clickhouse/jobs/5585870004","firstSeen":"2026-01-10T09:02:04.273Z","lastSeen":"2026-01-11T01:45:10.708Z"},{"id":1086540,"title":"Technical Customer Support Engineer - Dutch speaking (Remote)","company":"ClickHouse","companyDomain":"clickhouse.com","department":"Support Services","category":"customer-success","location":"United Kingdom (Remote)","url":"https://job-boards.greenhouse.io/clickhouse/jobs/5585873004","firstSeen":"2026-01-10T09:02:04.273Z","lastSeen":"2026-01-11T01:45:10.708Z"},{"id":1086541,"title":"Technical Customer Support Engineer - Dutch speaking (Remote)","company":"ClickHouse","companyDomain":"clickhouse.com","department":"Support Services","category":"customer-success","location":"Germany (Remote)","url":"https://job-boards.greenhouse.io/clickhouse/jobs/5585871004","firstSeen":"2026-01-10T09:02:04.273Z","lastSeen":"2026-01-11T01:45:10.708Z"},{"id":1086542,"title":"Technical Customer Support Engineer - EMEA","company":"ClickHouse","companyDomain":"clickhouse.com","department":"Support Services","category":"customer-success","location":"United Kingdom (Remote)","url":"https://job-boards.greenhouse.io/clickhouse/jobs/5726600004","firstSeen":"2026-01-10T09:02:04.273Z","lastSeen":"2026-01-11T01:45:10.708Z"},{"id":1086543,"title":"Technical Customer Support Engineer - EMEA","company":"ClickHouse","companyDomain":"clickhouse.com","department":"Support Services","category":"customer-success","location":"EMEA (Remote)","url":"https://job-boards.greenhouse.io/clickhouse/jobs/5726597004","firstSeen":"2026-01-10T09:02:04.273Z","lastSeen":"2026-01-11T01:45:10.708Z"},{"id":1086544,"title":"Technical Customer Support Engineer - EMEA","company":"ClickHouse","companyDomain":"clickhouse.com","department":"Support Services","category":"customer-success","location":"France (Remote)","url":"https://job-boards.greenhouse.io/clickhouse/jobs/5726599004","firstSeen":"2026-01-10T09:02:04.273Z","lastSeen":"2026-01-11T01:45:10.708Z"},{"id":1086545,"title":"Technical Customer Support Engineer - German speaking (Remote)","company":"ClickHouse","companyDomain":"clickhouse.com","department":"Support Services","category":"customer-success","location":"Germany (Remote)","url":"https://job-boards.greenhouse.io/clickhouse/jobs/5585851004","firstSeen":"2026-01-10T09:02:04.273Z","lastSeen":"2026-01-11T01:45:10.708Z"},{"id":1086201,"title":"Technical Account Manager","company":"Docker","companyDomain":"docker.com","department":"Sales","category":"customer-success","location":"Canada - Remote","url":"https://jobs.ashbyhq.com/docker/e3032a15-e5ba-4a0b-aa50-008991ad3e03","salary":{"min":138000,"max":172500},"firstSeen":"2026-01-10T08:56:26.248Z","lastSeen":"2026-01-11T01:42:37.128Z"},{"id":1086222,"title":"Renewals Manager","company":"Docker","companyDomain":"docker.com","department":"Sales","category":"customer-success","location":"Australia - Remote","url":"https://jobs.ashbyhq.com/docker/7bb9cb8e-6758-4b98-b7b4-fab80a1fdaec","firstSeen":"2026-01-10T08:56:26.248Z","lastSeen":"2026-01-11T01:42:37.128Z"},{"id":1085939,"title":"Manager, CXO Experiences & Community","company":"Rubrik","companyDomain":"rubrik.com","department":"Transformation","category":"customer-success","location":"Remote","url":"https://www.rubrik.com/company/careers/departments/job.7394708?gh_jid=7394708","firstSeen":"2026-01-10T08:50:03.268Z","lastSeen":"2026-01-11T01:40:52.333Z"},{"id":1085784,"title":"Product Manager, Client Support","company":"Stitch Fix","companyDomain":"stichfix.com","department":"Product Management","category":"customer-success","location":"Remote, USA","url":"https://www.stitchfix.com/careers/jobs?gh_jid=7484686&gh_jid=7484686","firstSeen":"2026-01-10T08:47:22.917Z","lastSeen":"2026-01-11T01:40:05.562Z"},{"id":1085748,"title":"Client Success Manager, Distributed Retail","company":"Better","companyDomain":"better.com","department":"Distributed Retail","category":"customer-success","location":"Remote","url":"https://jobs.lever.co/better/4a824a6f-9ab4-4d09-a27a-bf634a8e9909","firstSeen":"2026-01-10T08:46:50.502Z","lastSeen":"2026-01-11T01:39:51.576Z"},{"id":1085734,"title":"Leasing Agent","company":"Kasa","companyDomain":"kasa.com","department":"Corporate Sales","category":"customer-success","location":"Remote - United States","url":"https://job-boards.greenhouse.io/kasaliving/jobs/7568716003","firstSeen":"2026-01-10T08:46:14.721Z","lastSeen":"2026-01-11T01:39:38.448Z"},{"id":1085735,"title":"Leasing Agent","company":"Kasa","companyDomain":"kasa.com","department":"Corporate Sales","category":"customer-success","location":"Remote - Philippines","url":"https://job-boards.greenhouse.io/kasaliving/jobs/7570545003","firstSeen":"2026-01-10T08:46:14.721Z","lastSeen":"2026-01-11T01:39:38.448Z"},{"id":1085649,"title":"Service Agent, Patient Care Coordinator","company":"Talkiatry","companyDomain":"talkiatry.com","department":"Patient Care Coordination","category":"customer-success","location":"Remote","url":"https://jobs.lever.co/talkiatry/ea88afe2-5e31-4201-bf71-d8f07a35d8fe","firstSeen":"2026-01-10T08:43:18.917Z","lastSeen":"2026-01-11T01:38:53.802Z"},{"id":1088989,"title":"Case Management Nurse","company":"Oscar","companyDomain":"hioscar.com","department":"Clinical","category":"customer-success","location":"Remote","url":"http://www.hioscar.com/careers/7527167?gh_jid=7527167","firstSeen":"2026-01-10T13:44:36.511Z","lastSeen":"2026-01-11T01:37:27.814Z"},{"id":1089044,"title":"NP/PA - Virtual Urgent Care","company":"Oscar","companyDomain":"hioscar.com","department":"Virtual","category":"customer-success","location":"Remote","url":"http://www.hioscar.com/careers/7490791?gh_jid=7490791","firstSeen":"2026-01-10T13:44:36.511Z","lastSeen":"2026-01-11T01:37:27.814Z"},{"id":1089055,"title":"Physician - Virtual Urgent Care (Part-time)","company":"Oscar","companyDomain":"hioscar.com","department":"Virtual","category":"customer-success","location":"Remote","url":"http://www.hioscar.com/careers/7452967?gh_jid=7452967","firstSeen":"2026-01-10T13:44:36.511Z","lastSeen":"2026-01-11T01:37:27.814Z"},{"id":1089121,"title":"Utilization Review Nurse","company":"Oscar","companyDomain":"hioscar.com","department":"Clinical","category":"customer-success","location":"Remote","url":"http://www.hioscar.com/careers/7452970?gh_jid=7452970","firstSeen":"2026-01-10T13:45:12.968Z","lastSeen":"2026-01-11T01:37:27.814Z"},{"id":1085328,"title":"Developer Engagement Representative - Creator Events Program, US/Canada (Part-time, Contract) ","company":"Roblox","companyDomain":"roblox.com","department":"Developer Relations (Non-Tech)","category":"customer-success","location":"Remote","url":"https://careers.roblox.com/jobs/7487287?gh_jid=7487287","firstSeen":"2026-01-10T08:37:36.244Z","lastSeen":"2026-01-11T01:36:38.028Z"},{"id":1085332,"title":"Developer Engagement Representative - Thailand (Part-Time Contract)","company":"Roblox","companyDomain":"roblox.com","department":"Developer Relations (Non-Tech)","category":"customer-success","location":"Remote","url":"https://careers.roblox.com/jobs/7379051?gh_jid=7379051","firstSeen":"2026-01-10T08:37:36.244Z","lastSeen":"2026-01-11T01:36:38.028Z"},{"id":1085333,"title":"Developer Engagement Representative - Vietnam (Part-Time Contract)","company":"Roblox","companyDomain":"roblox.com","department":"Developer Relations (Non-Tech)","category":"customer-success","location":"Remote","url":"https://careers.roblox.com/jobs/7379018?gh_jid=7379018","firstSeen":"2026-01-10T08:37:36.244Z","lastSeen":"2026-01-11T01:36:38.028Z"},{"id":1085302,"title":"Specialist, Community Support","company":"Kickstarter","companyDomain":"kickstarter.com","department":"Community Support","category":"customer-success","location":"Remote, Singapore","url":"https://job-boards.greenhouse.io/kickstarter/jobs/4959650007","firstSeen":"2026-01-10T08:37:03.962Z","lastSeen":"2026-01-11T01:36:06.986Z"},{"id":1063330,"title":"Customer Success Manager","company":"Spring Health","companyDomain":"springhealth.com","department":"Revenue","category":"customer-success","location":"Remote","url":"https://job-boards.greenhouse.io/springhealth66/jobs/4543797005","firstSeen":"2025-07-26T18:12:23.420Z","lastSeen":"2026-01-11T01:33:49.388Z"},{"id":1084887,"title":"Account Manager, Upsell and Renewal","company":"Spring Health","companyDomain":"springhealth.com","department":"Revenue","category":"customer-success","location":"Remote","url":"https://job-boards.greenhouse.io/springhealth66/jobs/4638577005","firstSeen":"2026-01-10T08:29:00.966Z","lastSeen":"2026-01-11T01:33:49.388Z"},{"id":1084894,"title":"Care Support Coordinator (Temporary) ","company":"Spring Health","companyDomain":"springhealth.com","department":"Operations","category":"customer-success","location":"Remote","url":"https://job-boards.greenhouse.io/springhealth66/jobs/4646618005","firstSeen":"2026-01-10T08:29:00.966Z","lastSeen":"2026-01-11T01:33:49.388Z"},{"id":1084895,"title":"Clinical Care Navigator, After Hours (Saturday to Wednesday 2pm-10pm ET)","company":"Spring Health","companyDomain":"springhealth.com","department":"Care Navigation","category":"customer-success","location":"Remote","url":"https://job-boards.greenhouse.io/springhealth66/jobs/4507349005","firstSeen":"2026-01-10T08:29:00.966Z","lastSeen":"2026-01-11T01:33:49.388Z"},{"id":1084896,"title":"Clinical Care Navigator (Monday-Friday 1pm-9pm ET)","company":"Spring Health","companyDomain":"springhealth.com","department":"Care Navigation","category":"customer-success","location":"Remote","url":"https://job-boards.greenhouse.io/springhealth66/jobs/4622303005","firstSeen":"2026-01-10T08:29:00.966Z","lastSeen":"2026-01-11T01:33:49.388Z"},{"id":1084897,"title":"Clinical Care Navigator (Monday to Friday 12pm-8pm ET)","company":"Spring Health","companyDomain":"springhealth.com","department":"Care Navigation","category":"customer-success","location":"Remote","url":"https://job-boards.greenhouse.io/springhealth66/jobs/4646906005","firstSeen":"2026-01-10T08:29:00.966Z","lastSeen":"2026-01-11T01:33:49.388Z"},{"id":1084898,"title":"Clinical Care Navigator (Wednesday to Sunday 8am-4pm ET)","company":"Spring Health","companyDomain":"springhealth.com","department":"Care Navigation","category":"customer-success","location":"Remote","url":"https://job-boards.greenhouse.io/springhealth66/jobs/4646928005","firstSeen":"2026-01-10T08:29:00.966Z","lastSeen":"2026-01-11T01:33:49.388Z"},{"id":1084909,"title":"EAP Dedicated Management Consultant (Remote)","company":"Spring Health","companyDomain":"springhealth.com","department":"Employer Services","category":"customer-success","location":"Remote","url":"https://job-boards.greenhouse.io/springhealth66/jobs/4635078005","firstSeen":"2026-01-10T08:29:00.966Z","lastSeen":"2026-01-11T01:33:49.388Z"},{"id":1084962,"title":"Strategic Customer Success Manager","company":"Spring Health","companyDomain":"springhealth.com","department":"Revenue","category":"customer-success","location":"Remote","url":"https://job-boards.greenhouse.io/springhealth66/jobs/4621812005","firstSeen":"2026-01-10T08:29:06.723Z","lastSeen":"2026-01-11T01:33:49.388Z"},{"id":1049836,"title":"Customer Success Manager","company":"SecurityScorecard","companyDomain":"securityscorecard.com","department":"Customer Success","category":"customer-success","location":"Remote (United States)","url":"https://securityscorecard.com/company/careers-list/?gh_jid=6945425","firstSeen":"2025-07-26T00:04:17.686Z","lastSeen":"2026-01-11T01:33:02.191Z"},{"id":1049913,"title":"Customer Success Manager - Brazil","company":"SecurityScorecard","companyDomain":"securityscorecard.com","department":"Customer Success","category":"customer-success","location":"Remote (Brazil)","url":"https://securityscorecard.com/company/careers-list/?gh_jid=6948895","firstSeen":"2025-07-26T00:04:17.686Z","lastSeen":"2026-01-11T01:33:02.191Z"},{"id":1050010,"title":"Customer Success Manager - Portugal","company":"SecurityScorecard","companyDomain":"securityscorecard.com","department":"Customer Success","category":"customer-success","location":"Remote (Portugal)","url":"https://securityscorecard.com/company/careers-list/?gh_jid=6848596","firstSeen":"2025-07-26T00:04:17.686Z","lastSeen":"2026-01-11T01:33:02.191Z"},{"id":1084775,"title":"Customer Success Specialist","company":"SecurityScorecard","companyDomain":"securityscorecard.com","department":"Customer Success","category":"customer-success","location":"Remote (US)","url":"https://securityscorecard.com/company/careers-list/?gh_jid=7380689","firstSeen":"2026-01-10T08:26:41.529Z","lastSeen":"2026-01-11T01:33:02.191Z"},{"id":1084776,"title":"Customer Success Specialist (Asia)","company":"SecurityScorecard","companyDomain":"securityscorecard.com","department":"Customer Success","category":"customer-success","location":"Remote (Asia)","url":"https://securityscorecard.com/company/careers-list/?gh_jid=7382686","firstSeen":"2026-01-10T08:26:41.529Z","lastSeen":"2026-01-11T01:33:02.191Z"},{"id":1084777,"title":"Customer Success Specialist (EMEA)","company":"SecurityScorecard","companyDomain":"securityscorecard.com","department":"Customer Success","category":"customer-success","location":"Remote (EMEA)","url":"https://securityscorecard.com/company/careers-list/?gh_jid=7382685","firstSeen":"2026-01-10T08:26:41.529Z","lastSeen":"2026-01-11T01:33:02.191Z"},{"id":1084778,"title":"Customer Success Specialist (Mexico)","company":"SecurityScorecard","companyDomain":"securityscorecard.com","department":"Customer Success","category":"customer-success","location":"Remote (Mexico)","url":"https://securityscorecard.com/company/careers-list/?gh_jid=7457830","firstSeen":"2026-01-10T08:26:41.529Z","lastSeen":"2026-01-11T01:33:02.191Z"},{"id":1083972,"title":"Customer Success Manager","company":"Samsara","companyDomain":"samsara.com","department":"Customer Success","category":"customer-success","location":"Remote - Canada","url":"https://www.samsara.com/company/careers/roles/7347533?gh_jid=7347533","firstSeen":"2026-01-10T08:13:43.324Z","lastSeen":"2026-01-11T01:28:21.995Z"},{"id":1083996,"title":"Enterprise Customer Success Manager","company":"Samsara","companyDomain":"samsara.com","department":"Customer Success","category":"customer-success","location":"Remote - IL","url":"https://www.samsara.com/company/careers/roles/7476014?gh_jid=7476014","firstSeen":"2026-01-10T08:13:43.324Z","lastSeen":"2026-01-11T01:28:21.995Z"},{"id":1083997,"title":"Enterprise Customer Success Manager","company":"Samsara","companyDomain":"samsara.com","department":"Customer Success","category":"customer-success","location":"Remote - FL","url":"https://www.samsara.com/company/careers/roles/7476009?gh_jid=7476009","firstSeen":"2026-01-10T08:13:43.324Z","lastSeen":"2026-01-11T01:28:21.995Z"},{"id":1083998,"title":"Enterprise Customer Success Manager","company":"Samsara","companyDomain":"samsara.com","department":"Customer Success","category":"customer-success","location":"Remote - Canada","url":"https://www.samsara.com/company/careers/roles/7482877?gh_jid=7482877","firstSeen":"2026-01-10T08:13:43.324Z","lastSeen":"2026-01-11T01:28:21.995Z"},{"id":1083999,"title":"Enterprise Customer Success Manager","company":"Samsara","companyDomain":"samsara.com","department":"Customer Success","category":"customer-success","location":"Remote - GA","url":"https://www.samsara.com/company/careers/roles/7476016?gh_jid=7476016","firstSeen":"2026-01-10T08:13:43.324Z","lastSeen":"2026-01-11T01:28:21.995Z"},{"id":1084000,"title":"Enterprise Customer Success Manager","company":"Samsara","companyDomain":"samsara.com","department":"Customer Success","category":"customer-success","location":"Remote - NC","url":"https://www.samsara.com/company/careers/roles/7442877?gh_jid=7442877","firstSeen":"2026-01-10T08:13:43.324Z","lastSeen":"2026-01-11T01:28:21.995Z"},{"id":1084001,"title":"Enterprise Customer Success Manager","company":"Samsara","companyDomain":"samsara.com","department":"Customer Success","category":"customer-success","location":"Remote - GA","url":"https://www.samsara.com/company/careers/roles/7482459?gh_jid=7482459","firstSeen":"2026-01-10T08:13:43.324Z","lastSeen":"2026-01-11T01:28:21.995Z"},{"id":1084002,"title":"Enterprise Customer Success Manager","company":"Samsara","companyDomain":"samsara.com","department":"Customer Success","category":"customer-success","location":"Remote - US","url":"https://www.samsara.com/company/careers/roles/7156222?gh_jid=7156222","firstSeen":"2026-01-10T08:13:43.324Z","lastSeen":"2026-01-11T01:28:21.995Z"},{"id":1084003,"title":"Enterprise Customer Success Manager","company":"Samsara","companyDomain":"samsara.com","department":"Customer Success","category":"customer-success","location":"Remote - TX","url":"https://www.samsara.com/company/careers/roles/7476015?gh_jid=7476015","firstSeen":"2026-01-10T08:13:43.324Z","lastSeen":"2026-01-11T01:28:21.995Z"},{"id":1084004,"title":"Enterprise Customer Success Manager","company":"Samsara","companyDomain":"samsara.com","department":"Customer Success","category":"customer-success","location":"Remote - US","url":"https://www.samsara.com/company/careers/roles/7347395?gh_jid=7347395","firstSeen":"2026-01-10T08:13:43.324Z","lastSeen":"2026-01-11T01:28:21.995Z"},{"id":1084005,"title":"Enterprise Customer Success Manager","company":"Samsara","companyDomain":"samsara.com","department":"Customer Success","category":"customer-success","location":"Remote - OH","url":"https://www.samsara.com/company/careers/roles/7442876?gh_jid=7442876","firstSeen":"2026-01-10T08:13:43.324Z","lastSeen":"2026-01-11T01:28:21.995Z"},{"id":1084006,"title":"Enterprise Customer Success Manager","company":"Samsara","companyDomain":"samsara.com","department":"Customer Success","category":"customer-success","location":"Remote - TX","url":"https://www.samsara.com/company/careers/roles/7435731?gh_jid=7435731","firstSeen":"2026-01-10T08:13:43.324Z","lastSeen":"2026-01-11T01:28:21.995Z"},{"id":1082987,"title":"Customer Success Engineer, Dubai","company":"Cribl","companyDomain":"cribl.io","department":"Customer Experience","category":"customer-success","location":"Remote - Dubai","url":"https://job-boards.greenhouse.io/cribl/jobs/5696471004","firstSeen":"2026-01-10T08:01:49.215Z","lastSeen":"2026-01-11T01:23:28.209Z"},{"id":1082988,"title":"Customer Success Engineer, Federal","company":"Cribl","companyDomain":"cribl.io","department":"Customer Experience","category":"customer-success","location":"Remote - Washington, D.C.","url":"https://job-boards.greenhouse.io/cribl/jobs/5718614004","firstSeen":"2026-01-10T08:01:49.215Z","lastSeen":"2026-01-11T01:23:28.209Z"},{"id":1082452,"title":"Creative Support Specialist (contract)","company":"Runway ML","companyDomain":"runwayml.com","department":"Support","category":"customer-success","location":"Remote","url":"https://job-boards.greenhouse.io/runwayml/jobs/4553149005","firstSeen":"2026-01-10T07:52:13.291Z","lastSeen":"2026-01-11T01:18:04.503Z"},{"id":1082446,"title":"Technical Support Expert 2 - Segment","company":"Twilio","companyDomain":"twilio.com","department":"Customer Support","category":"customer-success","location":"Remote - Colombia","url":"https://job-boards.greenhouse.io/twilio/jobs/7426230","firstSeen":"2026-01-10T07:50:46.763Z","lastSeen":"2026-01-11T01:17:33.085Z"},{"id":1082342,"title":"Renewals Manager","company":"Zapier","companyDomain":"zapier.com","department":"Sales & Success","category":"customer-success","location":"NAMER - Remote","url":"https://jobs.ashbyhq.com/zapier/8c22a7e0-772b-4ae9-8d57-ae73ca5b3c5b","firstSeen":"2026-01-10T07:50:16.311Z","lastSeen":"2026-01-11T01:17:16.659Z"},{"id":1081851,"title":"Customer Support (German-speaking, Part-time)","company":"Via","companyDomain":"ridewithvia.com","department":"Support Operations","category":"customer-success","location":"Remote - England","url":"https://job-boards.greenhouse.io/via/jobs/8357575002","firstSeen":"2026-01-10T07:45:29.336Z","lastSeen":"2026-01-11T01:13:21.961Z"},{"id":1081852,"title":"Customer Support (German-speaking, Part-time)","company":"Via","companyDomain":"ridewithvia.com","department":"Support Operations","category":"customer-success","location":"Remote - Germany","url":"https://job-boards.greenhouse.io/via/jobs/8357576002","firstSeen":"2026-01-10T07:45:29.336Z","lastSeen":"2026-01-11T01:13:21.961Z"},{"id":1081833,"title":"Enterprise Customer Success Manager (Spanish Speaking)","company":"Maze","companyDomain":"maze.co","department":"Sales & Customer Success","category":"customer-success","location":"United States - Remote","url":"https://jobs.ashbyhq.com/mazedesign/53cf329f-2913-449a-9457-412d8220e01d","salary":{"min":97700,"max":143600},"firstSeen":"2026-01-10T07:45:12.954Z","lastSeen":"2026-01-11T01:13:10.001Z"},{"id":1081683,"title":"Enterprise Customer Success Manager","company":"Virtuous","companyDomain":"virtuous.org","department":"Customer Success","category":"customer-success","location":"Remote, USA - Remote","url":"https://jobs.ashbyhq.com/virtuous/7e72cd43-275e-47d8-9027-fde512f9c28c","firstSeen":"2026-01-10T07:42:41.565Z","lastSeen":"2026-01-11T01:12:00.243Z"},{"id":1081310,"title":"Customer Success Manager, Enterprise ","company":"AcuityMD","companyDomain":"acuitymd.com","department":"Customer Success","category":"customer-success","location":"Boston or Remote","url":"https://acuitymd.com/job?gh_jid=5687495004","firstSeen":"2026-01-10T07:37:16.013Z","lastSeen":"2026-01-11T01:10:02.339Z"},{"id":1081083,"title":"Program Manager, Dispute Experience","company":"Chime","companyDomain":"chime.com","department":"Member Experience","category":"customer-success","location":"US - Remote","url":"https://boards.greenhouse.io/chime/jobs/8326088002?gh_jid=8326088002","firstSeen":"2026-01-10T07:32:18.395Z","lastSeen":"2026-01-11T01:08:39.252Z"},{"id":1048699,"title":"Customer Account Manager - US","company":"Iterable","companyDomain":"iterable.com","department":"Sales","category":"customer-success","location":"REMOTE - US","url":"https://job-boards.greenhouse.io/iterable/jobs/6587278","firstSeen":"2025-07-26T00:03:51.583Z","lastSeen":"2026-01-11T01:08:07.483Z"},{"id":1080897,"title":"Customer Success Manager - DACH","company":"Abnormal","companyDomain":"abnormalsecurity.com","department":"CSM & Renewals","category":"customer-success","location":"Remote - Germany","url":"https://abnormal.ai/careers/jobs/7510758003?gh_jid=7510758003","firstSeen":"2026-01-10T07:29:40.464Z","lastSeen":"2026-01-11T01:07:37.346Z"},{"id":1080898,"title":"Customer Success Manager - German Speaking ","company":"Abnormal","companyDomain":"abnormalsecurity.com","department":"CSM & Renewals","category":"customer-success","location":"Remote - UK","url":"https://abnormal.ai/careers/jobs/7510611003?gh_jid=7510611003","firstSeen":"2026-01-10T07:29:40.464Z","lastSeen":"2026-01-11T01:07:37.346Z"},{"id":1080927,"title":"Mid-Market Account Executive - Northwest ","company":"Abnormal","companyDomain":"abnormalsecurity.com","department":"MidMarket","category":"customer-success","location":"Remote - USA","url":"https://abnormal.ai/careers/jobs/7571313003?gh_jid=7571313003","firstSeen":"2026-01-10T07:29:40.464Z","lastSeen":"2026-01-11T01:07:37.346Z"},{"id":1080945,"title":"Renewals Manager","company":"Abnormal","companyDomain":"abnormalsecurity.com","department":"CSM & Renewals","category":"customer-success","location":"Remote - USA","url":"https://abnormal.ai/careers/jobs/7578696003?gh_jid=7578696003","firstSeen":"2026-01-10T07:29:40.464Z","lastSeen":"2026-01-11T01:07:37.346Z"},{"id":1080946,"title":"Renewals Manager - APJ","company":"Abnormal","companyDomain":"abnormalsecurity.com","department":"CSM & Renewals","category":"customer-success","location":"Remote - Australia","url":"https://abnormal.ai/careers/jobs/7580386003?gh_jid=7580386003","firstSeen":"2026-01-10T07:29:40.464Z","lastSeen":"2026-01-11T01:07:37.346Z"},{"id":1080947,"title":"Renewals Manager, Public Sector","company":"Abnormal","companyDomain":"abnormalsecurity.com","department":"CSM & Renewals","category":"customer-success","location":"Remote - USA","url":"https://abnormal.ai/careers/jobs/7574718003?gh_jid=7574718003","firstSeen":"2026-01-10T07:29:40.464Z","lastSeen":"2026-01-11T01:07:37.346Z"},{"id":1080412,"title":"Customer Success Manager, Corporate","company":"AlphaSense","companyDomain":"alpha-sense.com","department":"Pre & Post Sales","category":"customer-success","location":"Remote - United States","url":"https://job-boards.greenhouse.io/alphasense/jobs/8191964002","firstSeen":"2026-01-10T07:22:39.162Z","lastSeen":"2026-01-11T01:06:05.289Z"},{"id":1043564,"title":"Account Manager, Enterprise","company":"Vanta","companyDomain":"vanta.com","department":"Sales","category":"customer-success","location":"Remote U.S. - Remote","url":"https://jobs.ashbyhq.com/vanta/584b82e9-0ab9-4e69-9ead-91161337b2e5","salary":{"min":242000,"max":285000},"firstSeen":"2025-07-26T00:01:55.506Z","lastSeen":"2026-01-11T01:05:07.870Z"},{"id":1089906,"title":"Customer Success Manager, Startups","company":"Vanta","companyDomain":"vanta.com","department":"Customer Success","category":"customer-success","location":"London, UK - Remote","url":"https://jobs.ashbyhq.com/vanta/a82d4678-7aca-4744-9025-458a68f56312","postedAt":"2025-12-18T22:02:01.661Z","firstSeen":"2026-01-10T19:47:43.750Z","lastSeen":"2026-01-11T01:05:07.870Z"},{"id":1089916,"title":"Manager, Renewals Team","company":"Vanta","companyDomain":"vanta.com","department":"Sales","category":"customer-success","location":"Remote U.S. - Remote","url":"https://jobs.ashbyhq.com/vanta/6be8dc0c-c968-4537-a80e-90a623e14933","salary":{"min":189000,"max":222000},"postedAt":"2025-12-30T18:02:44.760Z","firstSeen":"2026-01-10T19:47:43.750Z","lastSeen":"2026-01-11T01:05:07.870Z"},{"id":1089923,"title":"Account Manager, Early Stage","company":"Vanta","companyDomain":"vanta.com","department":"Sales","category":"customer-success","location":"Remote U.S. - Remote","url":"https://jobs.ashbyhq.com/vanta/b9261cd2-4c01-468e-a448-c1e4cb4b84fc","salary":{"min":157000,"max":185000},"postedAt":"2025-12-29T17:43:51.024Z","firstSeen":"2026-01-10T19:47:43.750Z","lastSeen":"2026-01-11T01:05:07.870Z"},{"id":1089926,"title":"Customer Success Manager (Mid Market)- EMEA","company":"Vanta","companyDomain":"vanta.com","department":"Customer Success","category":"customer-success","location":"London, UK - Remote","url":"https://jobs.ashbyhq.com/vanta/84cb4e1e-245c-4a14-ad29-983a3f24fbb1","postedAt":"2025-07-03T15:14:47.022Z","firstSeen":"2026-01-10T19:47:43.750Z","lastSeen":"2026-01-11T01:05:07.870Z"},{"id":1089929,"title":"Customer Success Manager, Mid Market (East Region)","company":"Vanta","companyDomain":"vanta.com","department":"Customer Success","category":"customer-success","location":"Remote U.S. - Remote","url":"https://jobs.ashbyhq.com/vanta/2c9ad0ca-7c28-4344-b0c1-4735d0f61f2a","salary":{"min":134000,"max":158000},"postedAt":"2025-09-03T20:39:15.161Z","firstSeen":"2026-01-10T19:47:43.750Z","lastSeen":"2026-01-11T01:05:07.870Z"},{"id":1089978,"title":"DACH Customer Success Manager, SMB ","company":"Vanta","companyDomain":"vanta.com","department":"Customer Success","category":"customer-success","location":"London, UK - Remote","url":"https://jobs.ashbyhq.com/vanta/145b9d2e-13eb-4c7a-a5ad-1268d65eac45","postedAt":"2025-09-25T15:15:05.949Z","firstSeen":"2026-01-10T19:47:43.750Z","lastSeen":"2026-01-11T01:05:07.870Z"},{"id":1089979,"title":"Program Manager, AI Transformation (Customer Success)","company":"Vanta","companyDomain":"vanta.com","department":"Customer Success","category":"customer-success","location":"Remote U.S. - Remote","url":"https://jobs.ashbyhq.com/vanta/50761522-d82f-488d-98cc-0ec6ea34909b","salary":{"min":127000,"max":149000},"postedAt":"2025-12-23T15:44:13.466Z","firstSeen":"2026-01-10T19:47:43.750Z","lastSeen":"2026-01-11T01:05:07.870Z"},{"id":1089980,"title":"Post-Sales GRC SME","company":"Vanta","companyDomain":"vanta.com","department":"Security","category":"customer-success","location":"Remote U.S. - Remote","url":"https://jobs.ashbyhq.com/vanta/e5650256-068b-4365-961e-1758da1056b6","salary":{"min":163000,"max":192000},"postedAt":"2025-11-18T20:06:10.720Z","firstSeen":"2026-01-10T19:47:43.750Z","lastSeen":"2026-01-11T01:05:07.870Z"},{"id":1089982,"title":"Manager, Partner Customer Success","company":"Vanta","companyDomain":"vanta.com","department":"Customer Success","category":"customer-success","location":"Remote U.S. - Remote","url":"https://jobs.ashbyhq.com/vanta/50d231e8-8b16-4733-8d09-ec7d3c117e4e","salary":{"min":174000,"max":205000},"postedAt":"2025-12-11T21:26:20.233Z","firstSeen":"2026-01-10T19:47:43.750Z","lastSeen":"2026-01-11T01:05:07.870Z"},{"id":1090002,"title":"Manager, Customer Success","company":"Vanta","companyDomain":"vanta.com","department":"Customer Success","category":"customer-success","location":"Remote U.S. - Remote","url":"https://jobs.ashbyhq.com/vanta/7856d21d-b698-40fd-84c2-89592669b779","salary":{"min":174000,"max":205000},"postedAt":"2025-12-02T17:18:22.121Z","firstSeen":"2026-01-10T19:47:43.750Z","lastSeen":"2026-01-11T01:05:07.870Z"},{"id":1090029,"title":"Collections Lead","company":"Vanta","companyDomain":"vanta.com","department":"Finance","category":"customer-success","location":"Remote U.S. - Remote","url":"https://jobs.ashbyhq.com/vanta/b1cb6a4e-974f-4915-ada5-0135954c9902","postedAt":"2025-12-29T17:09:18.356Z","firstSeen":"2026-01-10T19:47:43.750Z","lastSeen":"2026-01-11T01:05:07.870Z"},{"id":1090030,"title":"Renewal Specialist","company":"Vanta","companyDomain":"vanta.com","department":"Sales","category":"customer-success","location":"Remote U.S. - Remote","url":"https://jobs.ashbyhq.com/vanta/a34eea66-b0ee-4b33-ae8f-492a7cd8751f","salary":{"min":122000,"max":143000},"postedAt":"2025-12-31T16:32:54.264Z","firstSeen":"2026-01-10T19:47:43.750Z","lastSeen":"2026-01-11T01:05:07.870Z"},{"id":1090673,"title":"Future Opportunities - Customer Success - US ","company":"PagerDuty","companyDomain":"pagerduty.com","department":"Customer Success","category":"customer-success","location":"Remote (USA)","url":"https://job-boards.greenhouse.io/pagerduty/jobs/5751678004","postedAt":"2026-01-08T16:06:59.000Z","firstSeen":"2026-01-11T01:04:06.317Z","lastSeen":"2026-01-11T01:04:06.317Z"},{"id":1087777,"title":"Growth Customer Success Manager","company":"Anaconda","companyDomain":"anaconda.com","department":"Customer Success","category":"customer-success","location":"Remote (United States)","url":"https://ats.rippling.com/anaconda/jobs/672198cc-3bea-42f9-a559-44295b4ddecb","firstSeen":"2026-01-10T12:27:38.646Z","lastSeen":"2026-01-11T00:50:30.842Z"},{"id":1087791,"title":"Support Engineer, APAC","company":"Anaconda","companyDomain":"anaconda.com","department":"Customer Services","category":"customer-success","location":"Remote (Tokyo, JP)","url":"https://ats.rippling.com/anaconda/jobs/e0d496d6-e6f3-49eb-b6e9-4bfcd631d3b1","firstSeen":"2026-01-10T12:27:38.646Z","lastSeen":"2026-01-11T00:50:30.842Z"},{"id":1077836,"title":"Implementation Manager, Consultative (Mid-Market)","company":"Rippling","companyDomain":"rippling.com","department":"Implementation","category":"customer-success","location":"Remote (United States)","url":"https://ats.rippling.com/rippling/jobs/23c090db-ee2d-4789-956e-6f1ebe71a327","firstSeen":"2026-01-10T06:15:40.162Z","lastSeen":"2026-01-11T00:13:14.758Z"},{"id":1077847,"title":"Implementation Specialist, Talent","company":"Rippling","companyDomain":"rippling.com","department":"Implementation","category":"customer-success","location":"Remote (United States)","url":"https://ats.rippling.com/rippling/jobs/2f11b6cf-daf8-4a8e-93a5-dec870598328","firstSeen":"2026-01-10T06:15:40.162Z","lastSeen":"2026-01-11T00:13:14.758Z"},{"id":1077340,"title":"Account Manager, Payer  ","company":"Maven Clinic","companyDomain":"mavenclinic.com","department":"Payer Growth","category":"customer-success","location":"Remote","url":"https://job-boards.greenhouse.io/mavenclinic/jobs/8182776002","firstSeen":"2026-01-10T06:03:49.861Z","lastSeen":"2026-01-11T00:03:50.217Z"},{"id":1077353,"title":"Manager, Member Services ","company":"Maven Clinic","companyDomain":"mavenclinic.com","department":"Benefits Support Operations","category":"customer-success","location":"Remote","url":"https://job-boards.greenhouse.io/mavenclinic/jobs/8091293002","firstSeen":"2026-01-10T06:03:49.861Z","lastSeen":"2026-01-11T00:03:50.217Z"},{"id":1077354,"title":"Manager, Member Services – Medication Access & Support Programs","company":"Maven Clinic","companyDomain":"mavenclinic.com","department":"Benefits Support Delivery ","category":"customer-success","location":"Remote","url":"https://job-boards.greenhouse.io/mavenclinic/jobs/8355933002","firstSeen":"2026-01-10T06:03:49.861Z","lastSeen":"2026-01-11T00:03:50.217Z"},{"id":1077355,"title":"Member Services Specialist – Medication Access & Support Programs","company":"Maven Clinic","companyDomain":"mavenclinic.com","department":"Benefits Support Delivery ","category":"customer-success","location":"Remote","url":"https://job-boards.greenhouse.io/mavenclinic/jobs/8350545002","firstSeen":"2026-01-10T06:03:49.861Z","lastSeen":"2026-01-11T00:03:50.217Z"},{"id":1077373,"title":"Team Lead – Medication Access & Support Programs","company":"Maven Clinic","companyDomain":"mavenclinic.com","department":"Benefits Support Operations","category":"customer-success","location":"Remote","url":"https://job-boards.greenhouse.io/mavenclinic/jobs/8355939002","firstSeen":"2026-01-10T06:03:49.861Z","lastSeen":"2026-01-11T00:03:50.217Z"},{"id":1058443,"title":"Strategic customer success manager","company":"Writer","companyDomain":"writer.com","department":"Delivery & customer success","category":"customer-success","location":"Chicago, IL - Remote","url":"https://jobs.ashbyhq.com/writer/80159fc3-cf1e-4563-b979-3db3681ede0e","salary":{"min":184800,"max":233700},"firstSeen":"2025-07-26T00:06:48.987Z","lastSeen":"2026-01-11T00:02:55.190Z"},{"id":1058470,"title":"Strategic customer success manager","company":"Writer","companyDomain":"writer.com","department":"Delivery & customer success","category":"customer-success","location":"Austin, TX - Remote","url":"https://jobs.ashbyhq.com/writer/e86f3591-1450-413a-8719-57c148119f8f","salary":{"min":184800,"max":233700},"firstSeen":"2025-07-26T00:06:48.987Z","lastSeen":"2026-01-11T00:02:55.190Z"},{"id":1077034,"title":"VP, customer success (EMEA)","company":"Writer","companyDomain":"writer.com","department":"Delivery & customer success","category":"customer-success","location":"London, UK - Remote","url":"https://jobs.ashbyhq.com/writer/9be101a6-9ad5-40dc-a151-a5d54c610d03","firstSeen":"2025-11-18T12:03:37.639Z","lastSeen":"2026-01-11T00:02:55.190Z"},{"id":1089810,"title":"Customer Success Manager","company":"Zip","companyDomain":"ziphq.com","department":"Customer Success","category":"customer-success","location":"Tel-Aviv, Israel - Remote","url":"https://jobs.ashbyhq.com/zip/165cf69e-591f-469e-81c0-f49277985181","postedAt":"2025-10-02T20:41:46.931Z","firstSeen":"2026-01-10T18:58:19.951Z","lastSeen":"2026-01-10T21:56:41.983Z"},{"id":1089124,"title":"Client Success Manager","company":"Seatgeek","companyDomain":"seatgeek.com","department":"Supply","category":"customer-success","location":"Remote - United States","url":"https://seatgeek.com/jobs/7441750?gh_jid=7441750","firstSeen":"2026-01-10T13:47:42.985Z","lastSeen":"2026-01-10T21:28:45.267Z"},{"id":1089138,"title":"Product Support Analyst","company":"Seatgeek","companyDomain":"seatgeek.com","department":"Client & Customer Support","category":"customer-success","location":"Remote - United Kingdom","url":"https://seatgeek.com/jobs/7482928?gh_jid=7482928","firstSeen":"2026-01-10T13:47:42.985Z","lastSeen":"2026-01-10T21:28:45.267Z"},{"id":1059255,"title":"Software Engineer II, Back-end (Financial Platform)","company":"Affirm","companyDomain":"affirm.com","department":"Financial Platforms - Engineering","category":"customer-success","location":"Remote Poland","url":"https://job-boards.greenhouse.io/affirm/jobs/6652027003","firstSeen":"2025-07-26T00:07:22.699Z","lastSeen":"2025-08-16T00:14:22.611Z"},{"id":1073805,"title":" Solutions Architect","company":"ServiceNow","companyDomain":"servicenow.com","department":"Consulting","category":"customer-success","location":"Addison, Texas - Remote","url":"https://jobs.smartrecruiters.com/ServiceNow/744000075580065--solutions-architect","firstSeen":"2025-08-12T18:19:52.522Z","lastSeen":"2025-08-15T06:38:33.826Z"},{"id":1063885,"title":"Customer Support Advisor","company":"Booksy","companyDomain":"booksy.com","department":"Customer Success","category":"customer-success","location":"Poland - Remote","url":"https://apply.workable.com/j/B66469F812","firstSeen":"2025-07-27T12:11:26.429Z","lastSeen":"2025-08-14T12:38:51.651Z"},{"id":1063886,"title":"Customer Support Team Leader","company":"Booksy","companyDomain":"booksy.com","department":"Customer Success","category":"customer-success","location":"Poland - Remote","url":"https://apply.workable.com/j/30EE56ACBD","firstSeen":"2025-07-27T12:11:26.429Z","lastSeen":"2025-08-14T12:38:51.651Z"},{"id":1068626,"title":"Communications (CX) Technology Specialist","company":"Booksy","companyDomain":"booksy.com","category":"customer-success","location":"Poland - Remote","url":"https://apply.workable.com/j/15EAE3D5E7","firstSeen":"2025-08-03T06:18:20.510Z","lastSeen":"2025-08-14T12:38:51.651Z"},{"id":1062231,"title":"Global Technology Partnerships, Growth Partner Manager","company":"ServiceNow","companyDomain":"servicenow.com","department":"Sales","category":"customer-success","location":"Addison, Texas - Remote","url":"https://jobs.smartrecruiters.com/ServiceNow/744000072687685-global-technology-partnerships-growth-partner-manager","firstSeen":"2025-07-26T00:14:06.010Z","lastSeen":"2025-08-09T00:37:57.941Z"},{"id":1062312,"title":"LATAM Area Lead Customer Excellence Group","company":"ServiceNow","companyDomain":"servicenow.com","department":"Customer Service","category":"customer-success","location":"Brasilia, BRASILIA - Remote","url":"https://jobs.smartrecruiters.com/ServiceNow/744000072326935-latam-area-lead-customer-excellence-group","firstSeen":"2025-07-26T00:14:06.010Z","lastSeen":"2025-08-06T00:42:29.509Z"},{"id":1062394,"title":"Advisory Solution Consultant - Creator Workflows","company":"ServiceNow","companyDomain":"servicenow.com","department":"Sales","category":"customer-success","location":"Calgary, Alberta - Remote","url":"https://jobs.smartrecruiters.com/ServiceNow/744000071834780-advisory-solution-consultant-creator-workflows","firstSeen":"2025-07-26T00:14:06.010Z","lastSeen":"2025-08-01T06:36:49.858Z"},{"id":1062409,"title":"Advisory Solution Consultant - Creator Workflows","company":"ServiceNow","companyDomain":"servicenow.com","department":"Sales","category":"customer-success","location":"Waltham, Massachusetts - Remote","url":"https://jobs.smartrecruiters.com/ServiceNow/744000071608930-advisory-solution-consultant-creator-workflows","firstSeen":"2025-07-26T00:14:06.010Z","lastSeen":"2025-08-01T06:36:49.858Z"}]