{
    "python": {
        "root_node_name": "module",
        "shared_token_queries": {
            "identifier_class": {
                "general_queries": [
                    "((identifier) @placeholder)"
                ],
                "definition_queries": [
                    "(assignment left: (identifier) @placeholder)",
                    "(class_definition name: (identifier) @placeholder)",
                    "(function_definition name: (identifier) @placeholder)",
                    "(import_statement name: (dotted_name) @placeholder)",
                    "(import_from_statement name: (dotted_name) @placeholder)",
                    "(import_from_statement name: (aliased_import (identifier) @placeholder))",
                    "(for_statement left: (identifier) @placeholder)",
                    "(assignment left: (pattern_list (identifier) @placeholder))",
                    "(assignment left: (tuple_pattern (identifier) @placeholder))"
                ]
            }
        },
        "scope_queries": {
            "named_scope": [
                {
                    "query": "((function_definition name: (identifier) @placeholder.name) @placeholder)",
                    "type": "function"
                },
                {
                    "query": "((decorated_definition definition: (function_definition name: (identifier) @placeholder.name)) @placeholder)",
                    "type": "function"
                },
                {
                    "query": "((class_definition name: (identifier) @placeholder.name) @placeholder)",
                    "type": "class"
                }
            ]
        },
        "comment_queries": [
            "((comment) @placeholder)",
            "(expression_statement (string) @placeholder)"
        ],
        "share_tokens_between_files": true
    },
    "javascript": {
        "root_node_name": "program",
        "shared_token_queries": {
            "identifier_class": {
                "general_queries": [
                    "((identifier) @placeholder)"
                ],
                "definition_queries": [
                    "(variable_declarator name: (identifier) @placeholder)",
                    "(function_declaration name: (identifier) @placeholder)",
                    "(class_declaration name: (identifier) @placeholder)",
                    "(method_definition name: (property_identifier) @placeholder)",
                    "(import_specifier name: (identifier) @placeholder)",
                    "(import_clause (identifier) @placeholder)"
                ]
            }
        },
        "scope_queries": {
            "named_scope": [
                {
                    "query": "((function_declaration name: (identifier) @placeholder.name) @placeholder)",
                    "type": "function"
                },
                {
                    "query": "((class_declaration name: (identifier) @placeholder.name) @placeholder)",
                    "type": "class"
                }
            ]
        },
        "comment_queries": [
            "((comment) @placeholder)"
        ],
        "share_tokens_between_files": true
    },
    "typescript": {
        "root_node_name": "program",
        "shared_token_queries": {
            "identifier_class": {
                "general_queries": [
                    "((identifier) @placeholder)",
                    "((type_identifier) @placeholder)"
                ],
                "definition_queries": [
                    "(variable_declarator name: (identifier) @placeholder)",
                    "(function_declaration name: (identifier) @placeholder)",
                    "(class_declaration name: (type_identifier) @placeholder)",
                    "(method_definition name: (property_identifier) @placeholder)",
                    "(import_specifier name: (identifier) @placeholder)",
                    "(import_clause (identifier) @placeholder)",
                    "(import_clause (namespace_import (identifier) @placeholder))",
                    "(interface_declaration name: (type_identifier) @placeholder)",
                    "(type_alias_declaration name: (type_identifier) @placeholder)",
                    "(enum_declaration name: (identifier) @placeholder)"
                ]
            }
        },
        "scope_queries": {
            "named_scope": [
                {
                    "query": "((function_declaration name: (identifier) @placeholder.name) @placeholder)",
                    "type": "function"
                },
                {
                    "query": "((class_declaration name: (type_identifier) @placeholder.name) @placeholder)",
                    "type": "class"
                },
                {
                    "query": "((interface_declaration name: (type_identifier) @placeholder.name) @placeholder)",
                    "type": "interface"
                },
                {
                    "query": "((enum_declaration name: (identifier) @placeholder.name) @placeholder)",
                    "type": "enum"
                }
            ]
        },
        "comment_queries": [
            "((comment) @placeholder)"
        ],
        "share_tokens_between_files": true
    },
    "java": {
        "root_node_name": "program",
        "shared_token_queries": {
            "identifier_class": {
                "general_queries": [
                    "((identifier) @placeholder)",
                    "((type_identifier) @placeholder)"
                ],
                "definition_queries": [
                    "(variable_declarator name: (identifier) @placeholder)",
                    "(import_declaration (scoped_identifier name: (identifier) @placeholder))",
                    "(import_declaration (scoped_identifier scope: (scoped_identifier name: (identifier) @placeholder)))",
                    "(method_declaration name: (identifier) @placeholder)",
                    "(class_declaration name: (identifier) @placeholder)",
                    "(interface_declaration name: (identifier) @placeholder)",
                    "(enum_declaration name: (identifier) @placeholder)",
                    "(import_declaration (asterisk) @placeholder)",
                    "(import_declaration (scoped_identifier) @placeholder)"
                ]
            }
        },
        "scope_queries": {
            "named_scope": [
                {
                    "query": "((method_declaration name: (identifier) @placeholder.name) @placeholder)",
                    "type": "method"
                },
                {
                    "query": "((class_declaration name: (identifier) @placeholder.name) @placeholder)",
                    "type": "class"
                },
                {
                    "query": "((interface_declaration name: (identifier) @placeholder.name) @placeholder)",
                    "type": "interface"
                },
                {
                    "query": "((constructor_declaration name: (identifier) @placeholder.name) @placeholder)",
                    "type": "method"
                }
            ]
        },
        "comment_queries": [
            "((line_comment) @placeholder)",
            "((block_comment) @placeholder)"
        ],
        "share_tokens_between_files": true
    },
    "cpp": {
        "root_node_name": "translation_unit",
        "shared_token_queries": {
            "identifier_class": {
                "general_queries": [
                    "((identifier) @placeholder)",
                    "((field_identifier) @placeholder)",
                    "((namespace_identifier) @placeholder)",
                    "((type_identifier) @placeholder)"
                ],
                "definition_queries": [
                    "(declaration declarator: (identifier) @placeholder)",
                    "(function_definition declarator: (function_declarator declarator: (identifier) @placeholder))",
                    "(class_specifier name: (type_identifier) @placeholder)",
                    "(struct_specifier name: (type_identifier) @placeholder)",
                    "(union_specifier name: (type_identifier) @placeholder)",
                    "(enum_specifier name: (type_identifier) @placeholder)",
                    "(namespace_definition (namespace_identifier) @placeholder)"
                ]
            }
        },
        "scope_queries": {
            "named_scope": [
                {
                    "query": "((function_definition declarator: (function_declarator declarator: (identifier) @placeholder.name)) @placeholder)",
                    "type": "function"
                },
                {
                    "query": "((class_specifier name: (type_identifier) @placeholder.name) @placeholder)",
                    "type": "class"
                },
                {
                    "query": "((namespace_definition name: (namespace_identifier) @placeholder.name) @placeholder)",
                    "type": "namespace"
                }
            ]
        },
        "comment_queries": [
            "((comment) @placeholder)"
        ],
        "share_tokens_between_files": true
    },
    "csharp": {
        "root_node_name": "compilation_unit",
        "shared_token_queries": {
            "identifier_class": {
                "general_queries": [
                    "((identifier) @placeholder)"
                ],
                "definition_queries": [
                    "(variable_declarator (identifier) @placeholder)",
                    "(method_declaration (identifier) @placeholder)",
                    "(class_declaration (identifier) @placeholder)",
                    "(struct_declaration (identifier) @placeholder)",
                    "(interface_declaration (identifier) @placeholder)",
                    "(enum_declaration (identifier) @placeholder)",
                    "(namespace_declaration (identifier) @placeholder)",
                    "(using_directive (identifier) @placeholder)"
                ]
            }
        },
        "scope_queries": {
            "named_scope": [
                {
                    "query": "((method_declaration name: (identifier) @placeholder.name) @placeholder)",
                    "type": "method"
                },
                {
                    "query": "((class_declaration name: (identifier) @placeholder.name) @placeholder)",
                    "type": "class"
                },
                {
                    "query": "((namespace_declaration name: (identifier) @placeholder.name) @placeholder)",
                    "type": "namespace"
                },
                {
                    "query": "((constructor_declaration name: (identifier) @placeholder.name) @placeholder)",
                    "type": "method"
                }
            ]
        },
        "comment_queries": [
            "((comment) @placeholder)"
        ],
        "share_tokens_between_files": true
    },
    "go": {
        "root_node_name": "source_file",
        "shared_token_queries": {
            "identifier_class": {
                "general_queries": [
                    "((identifier) @placeholder)",
                    "((type_identifier) @placeholder)"
                ],
                "definition_queries": [
                    "(var_spec name: (identifier) @placeholder)",
                    "(function_declaration name: (identifier) @placeholder)",
                    "(method_declaration name: (field_identifier) @placeholder)",
                    "(type_declaration (type_spec name: (type_identifier) @placeholder))",
                    "(const_spec name: (identifier) @placeholder)",
                    "(method_declaration receiver: (parameter_list (parameter_declaration type: (pointer_type (type_identifier) @placeholder))))",
                    "(method_declaration receiver: (parameter_list (parameter_declaration type: (type_identifier) @placeholder)))"
                ]
            },
            "reciever_class": {
                "general_queries": [
                    "((type_identifier) @placeholder)"
                ],
                "definition_queries": [
                    "(method_declaration receiver: (parameter_list (parameter_declaration type: (pointer_type (type_identifier) @placeholder))))",
                    "(method_declaration receiver: (parameter_list (parameter_declaration type: (type_identifier) @placeholder)))"
                ]
            }
        },
        "scope_queries": {
            "named_scope": [
                {
                    "query": "((function_declaration name: (identifier) @placeholder.name) @placeholder)",
                    "type": "function"
                },
                {
                    "query": "((method_declaration name: (field_identifier) @placeholder.name) @placeholder)",
                    "type": "method"
                }
            ]
        },
        "comment_queries": [
            "((comment) @placeholder)"
        ],
        "share_tokens_between_files": true
    },
    "rust": {
        "root_node_name": "source_file",
        "shared_token_queries": {
            "identifier_class": {
                "general_queries": [
                    "((identifier) @placeholder)",
                    "((field_identifier) @placeholder)",
                    "((type_identifier) @placeholder)"
                ],
                "definition_queries": [
                    "(let_declaration pattern: (identifier) @placeholder)",
                    "(function_item name: (identifier) @placeholder)",
                    "(struct_item name: (type_identifier) @placeholder)",
                    "(enum_item name: (type_identifier) @placeholder)",
                    "(trait_item name: (type_identifier) @placeholder)",
                    "(type_item name: (type_identifier) @placeholder)",
                    "(mod_item name: (identifier) @placeholder)",
                    "(use_declaration (scoped_identifier) @placeholder)"
                ]
            }
        },
        "scope_queries": {
            "named_scope": [
                {
                    "query": "((function_item name: (identifier) @placeholder.name) @placeholder)",
                    "type": "function"
                },
                {
                    "query": "((impl_item type: (type_identifier) @placeholder.name) @placeholder)",
                    "type": "impl"
                },
                {
                    "query": "((struct_item name: (type_identifier) @placeholder.name) @placeholder)",
                    "type": "struct"
                },
                {
                    "query": "((enum_item name: (type_identifier) @placeholder.name) @placeholder)",
                    "type": "enum"
                },
                {
                    "query": "((mod_item name: (identifier) @placeholder.name) @placeholder)",
                    "type": "module"
                }
            ]
        },
        "comment_queries": [
            "((line_comment) @placeholder)",
            "((block_comment) @placeholder)"
        ],
        "share_tokens_between_files": true
    },
    "ruby": {
        "root_node_name": "program",
        "shared_token_queries": {
            "identifier_class": {
                "general_queries": [
                    "((identifier) @placeholder)",
                    "((constant) @placeholder)"
                ],
                "definition_queries": [
                    "(assignment left: (identifier) @placeholder)",
                    "(assignment left: (constant) @placeholder)",
                    "(method (identifier) @placeholder)",
                    "(singleton_method name: (identifier) @placeholder)",
                    "(class (constant) @placeholder)",
                    "(module (constant) @placeholder)",
                    "(for pattern: (identifier) @placeholder)"
                ]
            }
        },
        "scope_queries": {
            "named_scope": [
                {
                    "query": "((method name: (identifier) @placeholder.name) @placeholder)",
                    "type": "method"
                },
                {
                    "query": "((singleton_method name: (identifier) @placeholder.name) @placeholder)",
                    "type": "method"
                },
                {
                    "query": "((class name: (constant) @placeholder.name) @placeholder)",
                    "type": "class"
                },
                {
                    "query": "((module name: (constant) @placeholder.name) @placeholder)",
                    "type": "module"
                }
            ]
        },
        "comment_queries": [
            "((comment) @placeholder)"
        ],
        "share_tokens_between_files": true
    },
    "php": {
        "root_node_name": "",
        "shared_token_queries": {
            "identifier_class": {
                "general_queries": [
                    "((name) @placeholder)",
                    "((variable_name) @placeholder)"
                ],
                "definition_queries": [
                    "(assignment_expression left: (variable_name) @placeholder)",
                    "(function_definition name: (name) @placeholder)",
                    "(method_declaration name: (name) @placeholder)",
                    "(class_declaration name: (name) @placeholder)",
                    "(interface_declaration name: (name) @placeholder)",
                    "(trait_declaration name: (name) @placeholder)",
                    "(namespace_definition name: (namespace_name) @placeholder)",
                    "(namespace_use_declaration (namespace_use_clause (qualified_name)) @placeholder)"
                ]
            }
        },
        "scope_queries": {
            "named_scope": [
                {
                    "query": "((function_definition name: (name) @placeholder.name) @placeholder)",
                    "type": "function"
                },
                {
                    "query": "((method_declaration name: (name) @placeholder.name) @placeholder)",
                    "type": "method"
                },
                {
                    "query": "((class_declaration name: (name) @placeholder.name) @placeholder)",
                    "type": "class"
                },
                {
                    "query": "((namespace_definition name: (namespace_name) @placeholder.name) @placeholder)",
                    "type": "namespace"
                }
            ]
        },
        "comment_queries": [
            "((comment) @placeholder)"
        ],
        "share_tokens_between_files": true
    },
    "swift": {
        "root_node_name": "source_file",
        "shared_token_queries": {
            "identifier_class": {
                "general_queries": [
                    "((simple_identifier) @placeholder)",
                    "((type_identifier) @placeholder)"
                ],
                "definition_queries": [
                    "(property_declaration (pattern (simple_identifier)) @placeholder)",
                    "(function_declaration name: (simple_identifier) @placeholder)",
                    "(class_declaration name: (type_identifier) @placeholder)",
                    "(protocol_declaration name: (type_identifier) @placeholder)",
                    "(typealias_declaration name: (type_identifier) @placeholder)"
                ]
            }
        },
        "scope_queries": {
            "named_scope": [
                {
                    "query": "((function_declaration name: (simple_identifier) @placeholder.name) @placeholder)",
                    "type": "function"
                },
                {
                    "query": "((class_declaration name: (type_identifier) @placeholder.name) @placeholder)",
                    "type": "class"
                },
                {
                    "query": "((protocol_declaration name: (type_identifier) @placeholder.name) @placeholder)",
                    "type": "interface"
                }
            ]
        },
        "comment_queries": [
            "((comment) @placeholder)",
            "((multiline_comment) @placeholder)"
        ],
        "share_tokens_between_files": true
    },
    "kotlin": {
        "root_node_name": "source_file",
        "shared_token_queries": {
            "identifier_class": {
                "general_queries": [
                    "((simple_identifier) @placeholder)",
                    "((type_identifier) @placeholder)"
                ],
                "definition_queries": [
                    "(property_declaration (variable_declaration (simple_identifier) @placeholder))",
                    "(function_declaration (simple_identifier) @placeholder)",
                    "(class_declaration (type_identifier) @placeholder)",
                    "(object_declaration (type_identifier) @placeholder)"
                ]
            }
        },
        "scope_queries": {
            "named_scope": [
                {
                    "query": "((function_declaration (simple_identifier) @placeholder.name) @placeholder)",
                    "type": "function"
                },
                {
                    "query": "((class_declaration (type_identifier) @placeholder.name) @placeholder)",
                    "type": "class"
                },
                {
                    "query": "((object_declaration (type_identifier) @placeholder.name) @placeholder)",
                    "type": "class"
                }
            ]
        },
        "comment_queries": [
            "((line_comment) @placeholder)",
            "((multiline_comment) @placeholder)"
        ],
        "share_tokens_between_files": true
    },
    "scala": {
        "root_node_name": "compilation_unit",
        "shared_token_queries": {
            "identifier_class": {
                "general_queries": [
                    "((identifier) @placeholder)",
                    "((type_identifier) @placeholder)"
                ],
                "definition_queries": [
                    "(val_definition (identifier) @placeholder)",
                    "(var_definition (identifier) @placeholder)",
                    "(function_definition (identifier) @placeholder)",
                    "(class_definition (identifier) @placeholder)",
                    "(object_definition (identifier) @placeholder)",
                    "(trait_definition (identifier) @placeholder)"
                ]
            }
        },
        "scope_queries": {
            "named_scope": [
                {
                    "query": "((function_definition name: (identifier) @placeholder.name) @placeholder)",
                    "type": "function"
                },
                {
                    "query": "((class_definition name: (identifier) @placeholder.name) @placeholder)",
                    "type": "class"
                },
                {
                    "query": "((object_definition name: (identifier) @placeholder.name) @placeholder)",
                    "type": "class"
                },
                {
                    "query": "((trait_definition name: (identifier) @placeholder.name) @placeholder)",
                    "type": "trait"
                }
            ]
        },
        "comment_queries": [
            "((comment) @placeholder)",
            "((block_comment) @placeholder)"
        ],
        "share_tokens_between_files": true
    },
    "r": {
        "root_node_name": "program",
        "shared_token_queries": {
            "identifier_class": {
                "general_queries": [
                    "((identifier) @placeholder)"
                ],
                "definition_queries": [
                    "(binary_operator (identifier) @placeholder)",
                    "(for_statement (identifier) @placeholder)"
                ]
            }
        },
        "scope_queries": {
            "named_scope": []
        },
        "comment_queries": [
            "((comment) @placeholder)"
        ],
        "share_tokens_between_files": true
    },
    "lua": {
        "root_node_name": "chunk",
        "shared_token_queries": {
            "identifier_class": {
                "general_queries": [
                    "((identifier) @placeholder)"
                ],
                "definition_queries": [
                    "(assignment_statement (variable_list (identifier)) @placeholder)",
                    "(function_declaration (identifier) @placeholder)",
                    "(function_declaration (dot_index_expression (identifier) @placeholder))",
                    "(field (identifier) @placeholder)",
                    "(for_generic_clause (variable_list (identifier)) @placeholder)",
                    "(for_numeric_clause (identifier) @placeholder)"
                ]
            }
        },
        "scope_queries": {
            "named_scope": [
                {
                    "query": "((function_declaration name: (identifier) @placeholder.name) @placeholder)",
                    "type": "function"
                }
            ]
        },
        "comment_queries": [
            "((comment) @placeholder)"
        ],
        "share_tokens_between_files": true
    },
    "dart": {
        "root_node_name": "program",
        "shared_token_queries": {
            "identifier_class": {
                "general_queries": [
                    "((identifier) @placeholder)",
                    "((type_identifier) @placeholder)"
                ],
                "definition_queries": [
                    "(initialized_variable_definition (identifier) @placeholder)",
                    "(function_signature (identifier) @placeholder)",
                    "(class_definition (identifier) @placeholder)",
                    "(enum_declaration (identifier) @placeholder)",
                    "(mixin_declaration (identifier) @placeholder)",
                    "(extension_declaration (identifier) @placeholder)",
                    "(type_alias (type_identifier) @placeholder)",
                    "(import_specification (identifier) @placeholder)"
                ]
            }
        },
        "scope_queries": {
            "named_scope": [
                {
                    "query": "((class_definition name: (identifier) @placeholder.name) @placeholder)",
                    "type": "class"
                },
                {
                    "query": "((enum_declaration name: (identifier) @placeholder.name) @placeholder)",
                    "type": "enum"
                }
            ]
        },
        "comment_queries": [
            "((comment) @placeholder)",
            "((documentation_comment) @placeholder)"
        ],
        "share_tokens_between_files": true
    },
    "elixir": {
        "root_node_name": "source_file",
        "shared_token_queries": {
            "identifier_class": {
                "general_queries": [
                    "((identifier) @placeholder)",
                    "((atom) @placeholder)"
                ],
                "definition_queries": [
                    "(call target: (identifier) @placeholder (#match? @placeholder \"^def$|^defp$|^defmacro$|^defmodule$\"))",
                    "(binary_operator left: (identifier) @placeholder operator: \"=\")",
                    "(unary_operator operator: \"@\" operand: (call target: (identifier) @placeholder))"
                ]
            }
        },
        "scope_queries": {
            "named_scope": []
        },
        "comment_queries": [
            "((comment) @placeholder)"
        ],
        "share_tokens_between_files": true
    },
    "haskell": {
        "root_node_name": [
            "haskell",
            "declarations"
        ],
        "shared_token_queries": {
            "identifier_class": {
                "general_queries": [
                    "((variable) @placeholder)",
                    "((type) @placeholder)"
                ],
                "definition_queries": [
                    "(function (variable) @placeholder)",
                    "(type_alias (type) @placeholder)",
                    "(newtype (type) @placeholder)",
                    "(algebraic_datatype (type) @placeholder)",
                    "(class_declaration (type) @placeholder)",
                    "(instance_declaration (type) @placeholder)",
                    "(import_declaration (module) @placeholder)"
                ]
            }
        },
        "scope_queries": {
            "named_scope": [
                {
                    "query": "((function name: (variable) @placeholder.name) @placeholder)",
                    "type": "function"
                }
            ]
        },
        "comment_queries": [
            "((comment) @placeholder)",
            "((pragma) @placeholder)"
        ],
        "share_tokens_between_files": false
    },
    "ocaml": {
        "root_node_name": "compilation_unit",
        "shared_token_queries": {
            "identifier_class": {
                "general_queries": [
                    "((value_name) @placeholder)",
                    "((type_constructor) @placeholder)"
                ],
                "definition_queries": [
                    "(value_definition (let_binding pattern: (value_name) @placeholder))",
                    "(type_definition (type_binding (type_constructor) @placeholder))",
                    "(module_definition name: (module_name) @placeholder)",
                    "(class_definition (class_binding (class_name) @placeholder))",
                    "(open_statement (module_path) @placeholder)"
                ]
            }
        },
        "scope_queries": {
            "named_scope": [
                {
                    "query": "((module_definition (module_binding (module_name) @placeholder.name)) @placeholder)",
                    "type": "module"
                }
            ]
        },
        "comment_queries": [
            "((comment) @placeholder)"
        ],
        "share_tokens_between_files": false
    },
    "erlang": {
        "root_node_name": "source_file",
        "shared_token_queries": {
            "identifier_class": {
                "general_queries": [
                    "((atom) @placeholder)",
                    "((variable) @placeholder)"
                ],
                "definition_queries": [
                    "(function_clause name: (atom) @placeholder)",
                    "(record_decl name: (atom) @placeholder)",
                    "(type_alias name: (atom) @placeholder)",
                    "(module_attribute (atom) @placeholder)",
                    "(export_attribute (fa (atom) @placeholder))"
                ]
            }
        },
        "scope_queries": {
            "named_scope": [
                {
                    "query": "((function_clause name: (atom) @placeholder.name) @placeholder)",
                    "type": "function"
                }
            ]
        },
        "comment_queries": [
            "((comment) @placeholder)"
        ],
        "share_tokens_between_files": true
    },
    "clojure": {
        "root_node_name": "source",
        "shared_token_queries": {
            "identifier_class": {
                "general_queries": [
                    "((sym_lit) @placeholder)"
                ],
                "definition_queries": [
                    "(list_lit . (sym_lit) @defn (#match? @defn \"^def$|^defn$|^defn-$|^defmacro$|^defprotocol$|^defrecord$|^deftype$\") . (sym_lit) @placeholder)",
                    "(list_lit . (sym_lit) @ns (#eq? @ns \"ns\") . (sym_lit) @placeholder)"
                ]
            }
        },
        "scope_queries": {
            "named_scope": []
        },
        "comment_queries": [
            "((comment) @placeholder)",
            "((dis_expr) @placeholder)"
        ],
        "share_tokens_between_files": true
    },
    "solidity": {
        "root_node_name": "source_file",
        "shared_token_queries": {
            "identifier_class": {
                "general_queries": [
                    "((identifier) @placeholder)"
                ],
                "definition_queries": [
                    "(state_variable_declaration (identifier) @placeholder)",
                    "(function_definition name: (identifier) @placeholder)",
                    "(modifier_definition name: (identifier) @placeholder)",
                    "(contract_declaration name: (identifier) @placeholder)",
                    "(interface_declaration name: (identifier) @placeholder)",
                    "(library_declaration name: (identifier) @placeholder)",
                    "(struct_declaration name: (identifier) @placeholder)",
                    "(enum_declaration name: (identifier) @placeholder)",
                    "(import_directive (identifier) @placeholder)"
                ]
            }
        },
        "scope_queries": {
            "named_scope": [
                {
                    "query": "((function_definition name: (identifier) @placeholder.name) @placeholder)",
                    "type": "function"
                },
                {
                    "query": "((modifier_definition name: (identifier) @placeholder.name) @placeholder)",
                    "type": "function"
                },
                {
                    "query": "((contract_declaration name: (identifier) @placeholder.name) @placeholder)",
                    "type": "class"
                }
            ]
        },
        "comment_queries": [
            "((comment) @placeholder)"
        ],
        "share_tokens_between_files": true
    },
    "julia": {
        "root_node_name": "source_file",
        "shared_token_queries": {
            "identifier_class": {
                "general_queries": [
                    "((identifier) @placeholder)"
                ],
                "definition_queries": [
                    "(assignment_expression left: (identifier) @placeholder)",
                    "(function_definition (signature (call_expression (identifier) @placeholder)))",
                    "(short_function_definition (signature (call_expression (identifier) @placeholder)))",
                    "(macro_definition (signature (call_expression (identifier) @placeholder)))",
                    "(struct_definition (type_head (identifier) @placeholder))",
                    "(module_definition (identifier) @placeholder)",
                    "(for_clause (identifier) @placeholder)",
                    "(import_statement (identifier) @placeholder)",
                    "(using_statement (identifier) @placeholder)"
                ]
            }
        },
        "scope_queries": {
            "named_scope": [
                {
                    "query": "((function_definition (signature (call_expression (identifier) @placeholder.name))) @placeholder)",
                    "type": "function"
                },
                {
                    "query": "((macro_definition (signature (call_expression (identifier) @placeholder.name))) @placeholder)",
                    "type": "function"
                },
                {
                    "query": "((struct_definition (type_head (identifier) @placeholder.name)) @placeholder)",
                    "type": "struct"
                },
                {
                    "query": "((module_definition (identifier) @placeholder.name) @placeholder)",
                    "type": "module"
                }
            ]
        },
        "comment_queries": [
            "((line_comment) @placeholder)",
            "((block_comment) @placeholder)"
        ],
        "share_tokens_between_files": true
    },
    "bash": {
        "root_node_name": "program",
        "shared_token_queries": {
            "identifier_class": {
                "general_queries": [
                    "((variable_name) @placeholder)",
                    "((word) @placeholder)"
                ],
                "definition_queries": [
                    "(variable_assignment name: (variable_name) @placeholder)",
                    "(function_definition name: (word) @placeholder)",
                    "(for_statement variable: (variable_name) @placeholder)",
                    "(declaration_command (variable_assignment name: (variable_name) @placeholder))"
                ]
            }
        },
        "scope_queries": {
            "named_scope": [
                {
                    "query": "((function_definition name: (word) @placeholder.name) @placeholder)",
                    "type": "function"
                }
            ]
        },
        "comment_queries": [
            "((comment) @placeholder)"
        ],
        "share_tokens_between_files": true
    },
    "c": {
        "root_node_name": "translation_unit",
        "shared_token_queries": {
            "identifier_class": {
                "general_queries": [
                    "((identifier) @placeholder)",
                    "((field_identifier) @placeholder)",
                    "((type_identifier) @placeholder)"
                ],
                "definition_queries": [
                    "(declaration declarator: (identifier) @placeholder)",
                    "(declaration declarator: (init_declarator declarator: (identifier) @placeholder))",
                    "(function_definition declarator: (function_declarator declarator: (identifier) @placeholder))",
                    "(parameter_declaration declarator: (identifier) @placeholder)",
                    "(struct_specifier name: (type_identifier) @placeholder)",
                    "(union_specifier name: (type_identifier) @placeholder)",
                    "(enum_specifier name: (type_identifier) @placeholder)",
                    "(type_definition declarator: (type_identifier) @placeholder)"
                ]
            }
        },
        "scope_queries": {
            "named_scope": [
                {
                    "query": "((function_definition declarator: (function_declarator declarator: (identifier) @placeholder.name)) @placeholder)",
                    "type": "function"
                },
                {
                    "query": "((struct_specifier name: (type_identifier) @placeholder.name) @placeholder)",
                    "type": "struct"
                },
                {
                    "query": "((union_specifier name: (type_identifier) @placeholder.name) @placeholder)",
                    "type": "struct"
                },
                {
                    "query": "((enum_specifier name: (type_identifier) @placeholder.name) @placeholder)",
                    "type": "enum"
                }
            ]
        },
        "comment_queries": [
            "((comment) @placeholder)"
        ],
        "share_tokens_between_files": true
    },
    "toml": {
        "root_node_name": "document",
        "shared_token_queries": {
            "identifier_class": {
                "general_queries": [
                    "((bare_key) @placeholder)",
                    "((quoted_key) @placeholder)"
                ],
                "definition_queries": [
                    "(table (bare_key) @placeholder)",
                    "(table (dotted_key (bare_key) @placeholder))",
                    "(table_array_element (bare_key) @placeholder)",
                    "(table_array_element (dotted_key (bare_key) @placeholder))"
                ]
            }
        },
        "scope_queries": {
            "named_scope": []
        },
        "comment_queries": [
            "((comment) @placeholder)"
        ],
        "share_tokens_between_files": false
    },
    "json": {
        "root_node_name": "document",
        "shared_token_queries": {
            "identifier_class": {
                "general_queries": [
                    "((string_content) @placeholder)"
                ],
                "definition_queries": [
                    "(pair key: (string (string_content) @placeholder))"
                ]
            }
        },
        "scope_queries": {
            "named_scope": []
        },
        "comment_queries": [],
        "share_tokens_between_files": false
    },
    "yaml": {
        "root_node_name": "stream",
        "shared_token_queries": {
            "identifier_class": {
                "general_queries": [
                    "((string_scalar) @placeholder)"
                ],
                "definition_queries": [
                    "(block_mapping_pair key: (flow_node (plain_scalar (string_scalar) @placeholder)))"
                ]
            }
        },
        "scope_queries": {
            "named_scope": []
        },
        "comment_queries": [
            "((comment) @placeholder)"
        ],
        "share_tokens_between_files": false
    },
    "markdown": {
        "root_node_name": "document",
        "shared_token_queries": {
            "identifier_class": {
                "general_queries": [],
                "definition_queries": []
            }
        },
        "scope_queries": {
            "named_scope": []
        },
        "comment_queries": [
            "((html_block) @placeholder)"
        ],
        "share_tokens_between_files": false
    },
    "rst": {
        "root_node_name": "document",
        "shared_token_queries": {
            "identifier_class": {
                "general_queries": [],
                "definition_queries": []
            }
        },
        "scope_queries": {
            "named_scope": []
        },
        "comment_queries": [
            "((comment) @placeholder)"
        ],
        "share_tokens_between_files": false
    },
    "html": {
        "root_node_name": "document",
        "shared_token_queries": {
            "identifier_class": {
                "general_queries": [
                    "((tag_name) @placeholder)",
                    "((attribute_name) @placeholder)"
                ],
                "definition_queries": [
                    "(element (start_tag (tag_name) @placeholder))",
                    "(attribute (attribute_name) @placeholder)"
                ]
            }
        },
        "scope_queries": {
            "named_scope": []
        },
        "comment_queries": [
            "((comment) @placeholder)"
        ],
        "share_tokens_between_files": false
    }
}