{
  "license": {
    "compatibility": {
      "contamination_effect": "module",
      "dynamic_linking": {
        "compatible_with": [
          "GPL-2.0",
          "GPL-3.0",
          "AGPL-3.0",
          "LGPL-2.1",
          "LGPL-3.0",
          "MIT",
          "Apache-2.0"
        ],
        "incompatible_with": [
          "Proprietary",
          "Commercial licenses without exceptions"
        ],
        "requires_review": [
          "MPL-2.0",
          "EPL-1.0",
          "BSD-3-Clause"
        ]
      },
      "notes": "The GPL-2.0-with-autoconf-exception allows linking with certain licenses, but care must be taken with proprietary licenses. The exception allows for the use of the library in a way that does not impose the GPL on the entire application.",
      "static_linking": {
        "compatible_with": [
          "GPL-2.0",
          "GPL-3.0",
          "AGPL-3.0",
          "LGPL-2.1",
          "LGPL-3.0",
          "MIT",
          "Apache-2.0"
        ],
        "incompatible_with": [
          "Proprietary",
          "Commercial licenses without exceptions"
        ],
        "requires_review": [
          "MPL-2.0",
          "EPL-1.0",
          "BSD-3-Clause"
        ]
      }
    },
    "id": "GPL-2.0-with-autoconf-exception",
    "key_requirements": [
      "Comply with the terms of the GPL v2 for all uses except for the configure scripts generated by Autoconf.",
      "If modifying Autoconf, ensure that the special exception is not included if non-data portions are copied."
    ],
    "limitations": {
      "liability": true,
      "trademark_use": false,
      "warranty": true
    },
    "name": "GPL-2.0-with-autoconf-exception",
    "obligations": [
      "Must disclose source code when distributing modified versions.",
      "Must include a copy of the GPL license when distributing the software.",
      "Must include copyright notices from the original authors.",
      "Must include notices of any changes made to the original software.",
      "If distributing modified versions of Autoconf, must not include the Autoconf exception if the modifications could copy non-data portions."
    ],
    "properties": {
      "commercial_use": true,
      "distribution": true,
      "modification": true,
      "patent_grant": true,
      "private_use": true
    },
    "requirements": {
      "disclose_source": true,
      "include_copyright": true,
      "include_license": true,
      "include_notice": true,
      "network_use_disclosure": false,
      "same_license": true,
      "state_changes": true
    },
    "spdx_id": "GPL-2.0-with-autoconf-exception",
    "type": "copyleft_strong"
  }
}